Workbook

Sheet LEIA-ME
A1: IRPF JOSÉ ADALMO — MEMÓRIA DE CÁLCULO PARA REGULARIZAÇÃO (BR–EUA)
A2: Contribuinte: José Adalmo Carvalho de Barros — CPF 069.351.996-70 | Cônjuge: Márcia Novais de Melo Barros — CPF 023.515.229-31
A3: Responsável técnico: Robson Soares Bezerra — CRC/PR 062711/O | Elaborado em 24/07/2026 | Data-base editável em 00_PARAMETROS!B4
A5: TRILHA DE AUDITORIA: Documento → valor extraído → câmbio → R$ → regra → imposto → crédito → juros/multa → saldo (abas 03 → 05/04 → 07 → 06 → 08 → 01).
A6: LEGENDA: células amarelas com fonte azul = entrada editável | laranja = pendência | azul-claro = totais | todas as demais são fórmulas.
A7: TAGS: [FATO CONFIRMADO] documento lido | [INFERÊNCIA TÉCNICA] conclusão a partir de norma + fato | [HIPÓTESE] premissa não comprovada | [SUGESTÃO] recomendação.
A9: REGRA CRÍTICA: nenhum valor PENDENTE vira imposto devido. Os cenários A/B medem exposição máxima; o 'Total payable' inclui só o apurado e exigível.
A11: COMO USAR
A12: 1. Em 04_BANK_TRANSACTIONS, coluna K, escolha a natureza comprovada de cada entrada de terceiros. Para GCAP, informe o ganho na coluna M.
A13: 2. Ajuste a data-base (00_PARAMETROS!B4) para a data do pagamento pretendido; os juros SELIC e a multa recalculam sozinhos.
A14: 3. Atualize a tabela SELIC com os meses seguintes (fonte BCB SGS 4390 / tabela RFB).
A15: 4. Se surgir prova de outra data de saída, altere 00_PARAMETROS!B5 — a linha do tempo é ajustada manualmente na aba 02 (colunas B/C).
... A18: Limitação: esta memória não substitui parecer jurídico-tributário individualizado. Os valores do AC 2018 são informativos (crédito extinto pela decadência).

Sheet 01_EXECUTIVE_SUMMARY
A1: 01 — RESUMO EXECUTIVO POR ANO (valores em R$)
A2: José Adalmo Carvalho de Barros — CPF 069.351.996-70 | Resp. técnico: Robson Soares Bezerra — CRC/PR 062711/O
A3: ="Data-base: "&TEXT('00_PARAMETROS'!$B$4,"DD/MM/YYYY")&" — Total payable = somente valores exigíveis e apurados. Cenários = exposição se as entradas PENDENTES forem renda de fonte BR (não é imposto devido)." -> Data-base: 30/09/2026 — Total payable = somente valores exigíveis e apurados. Cenários = exposição se as entradas PENDENTES forem renda de fonte BR (não é imposto devido).
A5: Year | B5: Tax residency | C5: Taxable income (BR) | D5: Brazilian tax | E5: U.S. tax potentially creditable | F5: Tax already paid | G5: Interest | H5: Penalties | I5: Updated balance | J5: Total payable | K5: Exposição Cenário A (atualiz.) | L5: Exposição Cenário B (atualiz.) | M5: Status
A6: 2018 | B6: ='02_TAX_TIMELINE'!B7 -> RESIDENTE | C6: ='07_BRAZIL_TAX_CALCULATION'!B22 -> 92634.55 | D6: ='07_BRAZIL_TAX_CALCULATION'!B30 -> 10434.74 | E6: ='06_FOREIGN_TAX_CREDIT'!B14 -> 0 | F6: ='07_BRAZIL_TAX_CALCULATION'!B31 -> 0 | G6: ='08_INTEREST_PENALTIES'!H6 -> 7167.62 | H6: ='08_INTEREST_PENALTIES'!I6 -> 2086.95 | I6: ='08_INTEREST_PENALTIES'!J6 -> 19689.31 | J6: ='08_INTEREST_PENALTIES'!K6 -> 0 | K6: 0 | L6: 0 | M6: ='02_TAX_TIMELINE'!G7&" — informativo" -> DECAÍDO — informativo
A7: 2019 | B7: ='02_TAX_TIMELINE'!B8 -> PARCIAL | C7: ='07_BRAZIL_TAX_CALCULATION'!E50+'07_BRAZIL_TAX_CALCULATION'!B43 -> 2569.89 | D7: ='07_BRAZIL_TAX_CALCULATION'!F50 -> 0 | E7: 0 | F7: 0 | G7: ='08_INTEREST_PENALTIES'!J8-'08_INTEREST_PENALTIES'!B8 -> 0 | H7: 0 | I7: ='08_INTEREST_PENALTIES'!J8 -> 0 | J7: ='08_INTEREST_PENALTIES'!K8 -> 0 | K7: ='08_INTEREST_PENALTIES'!J9 -> 0 | L7: ='08_INTEREST_PENALTIES'!J10 -> 0 | M7: ='02_TAX_TIMELINE'!G8&IF('07_BRAZIL_TAX_CALCULATION'!D50>0," — PENDENTE — DOCUMENTO NECESSÁRIO","") -> DECAÍDO
A8: 2020 | B8: ='02_TAX_TIMELINE'!B9 -> NÃO RESIDENTE | C8: ='07_BRAZIL_TAX_CALCULATION'!E51 -> 0 | D8: ='07_BRAZIL_TAX_CALCULATION'!F51 -> 0 | E8: 0 | F8: 0 | G8: ='08_INTEREST_PENALTIES'!J11-'08_INTEREST_PENALTIES'!B11 -> 0 | H8: 0 | I8: ='08_INTEREST_PENALTIES'!J11 -> 0 | J8: ='08_INTEREST_PENALTIES'!K11 -> 0 | K8: ='08_INTEREST_PENALTIES'!J12 -> 0 | L8: ='08_INTEREST_PENALTIES'!J13 -> 0 | M8: ='02_TAX_TIMELINE'!G9&IF('07_BRAZIL_TAX_CALCULATION'!D51>0," — PENDENTE — DOCUMENTO NECESSÁRIO","") -> DECAÍDO
A9: 2021 | B9: ='02_TAX_TIMELINE'!B10 -> NÃO RESIDENTE | C9: ='07_BRAZIL_TAX_CALCULATION'!E52 -> 0 | D9: ='07_BRAZIL_TAX_CALCULATION'!F52 -> 0 | E9: 0 | F9: 0 | G9: ='08_INTEREST_PENALTIES'!J14-'08_INTEREST_PENALTIES'!B14 -> 0 | H9: 0 | I9: ='08_INTEREST_PENALTIES'!J14 -> 0 | J9: ='08_INTEREST_PENALTIES'!K14 -> 0 | K9: ='08_INTEREST_PENALTIES'!J15 -> 0 | L9: ='08_INTEREST_PENALTIES'!J16 -> 0 | M9: ='02_TAX_TIMELINE'!G10&IF('07_BRAZIL_TAX_CALCULATION'!D52>0," — PENDENTE — DOCUMENTO NECESSÁRIO","") -> ABERTO
A10: 2022 | B10: ='02_TAX_TIMELINE'!B11 -> NÃO RESIDENTE | C10: ='07_BRAZIL_TAX_CALCULATION'!E53 -> 0 | D10: ='07_BRAZIL_TAX_CALCULATION'!F53 -> 0 | E10: 0 | F10: 0 | G10: ='08_INTEREST_PENALTIES'!J17-'08_INTEREST_PENALTIES'!B17 -> 0 | H10: 0 | I10: ='08_INTEREST_PENALTIES'!J17 -> 0 | J10: ='08_INTEREST_PENALTIES'!K17 -> 0 | K10: ='08_INTEREST_PENALTIES'!J18 -> 0 | L10: ='08_INTEREST_PENALTIES'!J19 -> 0 | M10: ='02_TAX_TIMELINE'!G11&IF('07_BRAZIL_TAX_CALCULATION'!D53>0," — PENDENTE — DOCUMENTO NECESSÁRIO","") -> ABERTO
A11: 2023 | B11: ='02_TAX_TIMELINE'!B12 -> NÃO RESIDENTE | C11: ='07_BRAZIL_TAX_CALCULATION'!E54 -> 0 | D11: ='07_BRAZIL_TAX_CALCULATION'!F54 -> 0 | E11: 0 | F11: 0 | G11: ='08_INTEREST_PENALTIES'!J20-'08_INTEREST_PENALTIES'!B20 -> 0 | H11: 0 | I11: ='08_INTEREST_PENALTIES'!J20 -> 0 | J11: ='08_INTEREST_PENALTIES'!K20 -> 0 | K11: ='08_INTEREST_PENALTIES'!J21 -> 0 | L11: ='08_INTEREST_PENALTIES'!J22 -> 0 | M11: ='02_TAX_TIMELINE'!G12&IF('07_BRAZIL_TAX_CALCULATION'!D54>0," — PENDENTE — DOCUMENTO NECESSÁRIO","") -> ABERTO
A12: 2024 | B12: ='02_TAX_TIMELINE'!B13 -> NÃO RESIDENTE | C12: ='07_BRAZIL_TAX_CALCULATION'!E55 -> 0 | D12: ='07_BRAZIL_TAX_CALCULATION'!F55 -> 0 | E12: 0 | F12: 0 | G12: ='08_INTEREST_PENALTIES'!J23-'08_INTEREST_PENALTIES'!B23 -> 0 | H12: 0 | I12: ='08_INTEREST_PENALTIES'!J23 -> 0 | J12: ='08_INTEREST_PENALTIES'!K23 -> 0 | K12: ='08_INTEREST_PENALTIES'!J24 -> 10275.31 | L12: ='08_INTEREST_PENALTIES'!J25 -> 17125.53 | M12: ='02_TAX_TIMELINE'!G13&IF('07_BRAZIL_TAX_CALCULATION'!D55>0," — PENDENTE — DOCUMENTO NECESSÁRIO","") -> ABERTO — PENDENTE — DOCUMENTO NECESSÁRIO
A13: 2025 | B13: ='02_TAX_TIMELINE'!B14 -> NÃO RESIDENTE | C13: ='07_BRAZIL_TAX_CALCULATION'!E56 -> 0 | D13: ='07_BRAZIL_TAX_CALCULATION'!F56 -> 0 | E13: 0 | F13: 0 | G13: ='08_INTEREST_PENALTIES'!J26-'08_INTEREST_PENALTIES'!B26 -> 0 | H13: 0 | I13: ='08_INTEREST_PENALTIES'!J26 -> 0 | J13: ='08_INTEREST_PENALTIES'!K26 -> 0 | K13: ='08_INTEREST_PENALTIES'!J27 -> 117339.42 | L13: ='08_INTEREST_PENALTIES'!J28 -> 195565.68 | M13: ='02_TAX_TIMELINE'!G14&IF('07_BRAZIL_TAX_CALCULATION'!D56>0," — PENDENTE — DOCUMENTO NECESSÁRIO","") -> ABERTO — PENDENTE — DOCUMENTO NECESSÁRIO
A14: 2026 | B14: ='02_TAX_TIMELINE'!B15 -> NÃO RESIDENTE | C14: ='07_BRAZIL_TAX_CALCULATION'!E57 -> 0 | D14: ='07_BRAZIL_TAX_CALCULATION'!F57 -> 0 | E14: 0 | F14: 0 | G14: ='08_INTEREST_PENALTIES'!J29-'08_INTEREST_PENALTIES'!B29 -> 0 | H14: 0 | I14: ='08_INTEREST_PENALTIES'!J29 -> 0 | J14: ='08_INTEREST_PENALTIES'!K29 -> 0 | K14: ='08_INTEREST_PENALTIES'!J30 -> 1506 | L14: ='08_INTEREST_PENALTIES'!J31 -> 2510 | M14: ='02_TAX_TIMELINE'!G15&IF('07_BRAZIL_TAX_CALCULATION'!D57>0," — PENDENTE — DOCUMENTO NECESSÁRIO","") -> ABERTO — PENDENTE — DOCUMENTO NECESSÁRIO
A15: TOTAL | C15: =SUM(C6:C14) -> 95204.44 | D15: =SUM(D6:D14) -> 10434.74 | E15: =SUM(E6:E14) -> 0 | F15: =SUM(F6:F14) -> 0 | G15: =SUM(G6:G14) -> 7167.62 | H15: =SUM(H6:H14) -> 2086.95 | I15: =SUM(I6:I14) -> 19689.31 | J15: =SUM(J6:J14) -> 0 | ... L15: =SUM(L6:L14) -> 215201.21
A17: Nota: nos anos de não residência, a coluna Interest mostra juros + multa de mora agregados (cálculo linha a linha na aba 04).
A19: INDICADORES-CHAVE
A20: Recebimentos de terceiros no BR sem natureza comprovada (R$) | E20: ='04_BANK_TRANSACTIONS'!F171 -> 623510
A21: Qtde. de recebimentos materiais pendentes | E21: ='04_BANK_TRANSACTIONS'!F172 -> 15
A22: Imóveis 2025 — preço contratado (R$) | E22: ='09_REAL_ESTATE'!D7 -> 1620265
A23: Imóveis — vencido em 2025 sem pagamento rastreado no Nubank (R$) | E23: ='09_REAL_ESTATE'!D12 -> 219215
A24: Pendências críticas em aberto | E24: =COUNTIFS('11_RISKS'!D:D,"ALTO",'11_RISKS'!H:H,"ABERTO")+COUNTIFS('11_RISKS'!D:D,"CRÍTICO",'11_RISKS'!H:H,"ABERTO") -> 5

Sheet 02_TAX_TIMELINE
A1: 02 — LINHA DO TEMPO DE RESIDÊNCIA E OBRIGAÇÕES (2016–2026)
A2: José Adalmo Carvalho de Barros — CPF 069.351.996-70 | Resp. técnico: Robson Soares Bezerra — CRC/PR 062711/O
A3: Decadência: sem declaração e sem pagamento → CTN art. 173, I (1º dia do exercício seguinte àquele em que o lançamento poderia ser efetuado + 5 anos) — STJ, Súmula 555 [INFERÊNCIA TÉCNICA]. Para AC 2020+ refere-se ao IRRF de fonte BR (fato gerador no próprio ano).
A4: AC | B4: Situação fiscal | C4: Período | D4: Obrigação declaratória | E4: Prazo de entrega | F4: Decadência (CTN 173, I) | G4: Status na data-base | H4: Tributo BR sobre renda EUA? | I4: Risco | J4: Nota técnica
A5: 2016 | B5: RESIDENTE | C5: 01/01–31/12/2016 | D5: DIRPF — ENTREGUE (recibo na pasta) | E5: 42853 | F5: =DATE(A5+6,12,31) -> 44926 | G5: =IF('00_PARAMETROS'!$B$4>F5,"DECAÍDO","ABERTO") -> DECAÍDO | H5: Não | I5: BAIXO | J5: [FATO CONFIRMADO] DEC + REC na pasta 2017/.
A6: 2017 | B6: RESIDENTE | C6: 01/01–31/12/2017 | D6: DIRPF — entrega informada, sem recibo | E6: 43220 | F6: =DATE(A6+6,12,31) -> 45291 | G6: =IF('00_PARAMETROS'!$B$4>F6,"DECAÍDO","ABERTO") -> DECAÍDO | H6: Não | I6: BAIXO | J6: [HIPÓTESE] Cliente afirma entrega; recibo não localizado. Decaído.
A7: 2018 | B7: RESIDENTE | C7: 01/01–31/12/2018 (ausente desde 25/01, sem CSDP) | D7: DIRPF obrigatória — NÃO ENTREGUE | E7: 43585 | F7: =DATE(A7+6,12,31) -> 45657 | G7: =IF('00_PARAMETROS'!$B$4>F7,"DECAÍDO","ABERTO") -> DECAÍDO | H7: SIM (rend. mundiais) | I7: MÉDIO | J7: [INFERÊNCIA TÉCNICA] W-2 US$ 25.628 > limite. Cálculo em 07 (informativo). Decaído pelo art. 173, I.
A8: 2019 | B8: PARCIAL | C8: Residente 01/01–24/01; não residente a partir de 25/01/2019 | D8: DSDP AC 2019 — NÃO ENTREGUE [INFERÊNCIA — confirmar obrigatoriedade] | E8: 44012 | F8: =DATE(YEAR(E8)+5,12,31) -> 46022 | G8: =IF('00_PARAMETROS'!$B$4>F8,"DECAÍDO","ABERTO") -> DECAÍDO | H8: Só no período residente | I8: BAIXO | J8: Prazo prorrogado para 30/06/2020 (IN RFB 1.930/2020 — confirmar). Renda do período residente < limite; sem imposto. MAED decaído.
A9: 2020 | B9: NÃO RESIDENTE | C9: Ano inteiro | D9: Sem DIRPF | F9: =DATE(A9+5,12,31) -> 46022 | G9: =IF('00_PARAMETROS'!$B$4>F9,"DECAÍDO","ABERTO") -> DECAÍDO | H9: NÃO | I9: BAIXO | J9: Renda EUA fora do alcance. Só IRRF sobre eventual renda de fonte BR.
A10: 2021 | B10: NÃO RESIDENTE | C10: Ano inteiro | D10: Sem DIRPF | F10: =DATE(A10+5,12,31) -> 46387 | G10: =IF('00_PARAMETROS'!$B$4>F10,"DECAÍDO","ABERTO") -> ABERTO | H10: NÃO | I10: BAIXO | J10: Idem. Sem extratos BR do período — PENDENTE.
A11: 2022 | B11: NÃO RESIDENTE | C11: Ano inteiro | D11: Sem DIRPF | F11: =DATE(A11+5,12,31) -> 46752 | G11: =IF('00_PARAMETROS'!$B$4>F11,"DECAÍDO","ABERTO") -> ABERTO | H11: NÃO | I11: BAIXO | J11: Idem. Extrato Nubank mai/2022 (03.pdf) referenciado; demais meses PENDENTES.
A12: 2023 | B12: NÃO RESIDENTE | C12: Ano inteiro | D12: Sem DIRPF | F12: =DATE(A12+5,12,31) -> 47118 | G12: =IF('00_PARAMETROS'!$B$4>F12,"DECAÍDO","ABERTO") -> ABERTO | H12: NÃO | I12: MÉDIO | J12: Form 1040/2023: digital assets = YES → origem/exchange PENDENTE.
A13: 2024 | B13: NÃO RESIDENTE | C13: Ano inteiro | D13: Sem DIRPF | F13: =DATE(A13+5,12,31) -> 47483 | G13: =IF('00_PARAMETROS'!$B$4>F13,"DECAÍDO","ABERTO") -> ABERTO | H13: NÃO | I13: ALTO | J13: Recebimentos de terceiros no BR (out–dez/2024) com natureza PENDENTE — ver 04.
A14: 2025 | B14: NÃO RESIDENTE | C14: Ano inteiro | D14: Sem DIRPF — NÃO transmitir o .DEC 2026 (endereço SP) | F14: =DATE(A14+5,12,31) -> 47848 | G14: =IF('00_PARAMETROS'!$B$4>F14,"DECAÍDO","ABERTO") -> ABERTO | H14: NÃO | I14: ALTO | J14: Terceiros BR R$ 574 mil + imóveis R$ 1,62 mi. Contrato Blue Ocean declara domicílio em Goioerê/PR (contradição).
A15: 2026 | B15: NÃO RESIDENTE | C15: Até a data-base | D15: Sem DIRPF | F15: =DATE(A15+5,12,31) -> 48213 | G15: =IF('00_PARAMETROS'!$B$4>F15,"DECAÍDO","ABERTO") -> ABERTO | H15: NÃO | I15: MÉDIO | J15: Reforços anuais N1 a partir de 25/07/2026 (R$ 88.850/ano) — origem dos recursos.

Sheet 03_INCOME
A1: 03 — RENDIMENTOS EXTRAÍDOS DOS DOCUMENTOS (Documento → Data → Contribuinte → Rendimento → Moeda → R$ → Tratamento → Fonte)
A2: José Adalmo Carvalho de Barros — CPF 069.351.996-70 | Resp. técnico: Robson Soares Bezerra — CRC/PR 062711/O
A4: Documento | B4: Período | C4: Contribuinte | D4: Rendimento / transação | E4: Moeda | F4: Valor original | G4: Câmbio | H4: Valor R$ | I4: Situação fiscal no período | J4: Tratamento tributário BR | K4: Status
A5: Form 1040/2018 | B5: 2018 | C5: José (MFJ c/ Márcia) | D5: W-2 wages (empregado) | E5: USD | F5: ='05_US_TAXES'!D5 -> 25628 | G5: ver 07 | H5: ='07_BRAZIL_TAX_CALCULATION'!E17 -> 92634.55 | I5: ='02_TAX_TIMELINE'!B7 -> RESIDENTE | J5: Tributável (residente) — carnê-leão + ajuste; DECAÍDO | K5: [FATO CONFIRMADO — OCR]
A6: Form 1040/2019 | B6: 2019 | C6: José | D6: Schedule C (autônomo) | E6: USD | F6: ='05_US_TAXES'!D6 -> 10000 | G6: ver 07 | H6: ='07_BRAZIL_TAX_CALCULATION'!B43 -> 2569.89 | I6: ='02_TAX_TIMELINE'!B8 -> PARCIAL | J6: Tributável só a fração 01–24/01 (abaixo do limite); restante fora do alcance | K6: [FATO CONFIRMADO — OCR]
A7: Form 1040/2020 | B7: 2020 | C7: José (MFJ c/ Márcia) | D7: Schedule C (autônomo) | E7: USD | F7: ='05_US_TAXES'!D7 -> 30152 | G7: N/A | I7: ='02_TAX_TIMELINE'!B9 -> NÃO RESIDENTE | J7: Fonte EUA, contribuinte não residente → não tributável no BR [INFERÊNCIA TÉCNICA] | K7: [FATO CONFIRMADO — OCR]
A8: Form 1040/2021 | B8: 2021 | C8: José (MFJ c/ Márcia) | D8: Schedule C (autônomo) | E8: USD | F8: ='05_US_TAXES'!D8 -> 35335 | G8: N/A | I8: ='02_TAX_TIMELINE'!B10 -> NÃO RESIDENTE | J8: Fonte EUA, contribuinte não residente → não tributável no BR [INFERÊNCIA TÉCNICA] | K8: [FATO CONFIRMADO — Fase 2]
A9: Form 1040/2022 | B9: 2022 | C9: José (MFJ c/ Márcia) | D9: Schedule C (autônomo) | E9: USD | F9: ='05_US_TAXES'!D9 -> 40550 | G9: N/A | I9: ='02_TAX_TIMELINE'!B11 -> NÃO RESIDENTE | J9: Fonte EUA, contribuinte não residente → não tributável no BR [INFERÊNCIA TÉCNICA] | K9: [FATO CONFIRMADO — OCR] (laudo F6 dizia 'a confirmar')
A10: Form 1040/2023 | B10: 2023 | C10: José (MFJ c/ Márcia) | D10: K-1 Two Brothers Drywall & Paint (EIN 37-2048597) | E10: USD | F10: ='05_US_TAXES'!D10 -> 75383 | G10: N/A | I10: ='02_TAX_TIMELINE'!B12 -> NÃO RESIDENTE | J10: Fonte EUA, contribuinte não residente → não tributável no BR [INFERÊNCIA TÉCNICA] | K10: [INFERÊNCIA TÉCNICA]
A11: Form 1040/2024 | B11: 2024 | C11: José (MFJ c/ Márcia) | D11: Sch C (DeSouza Painting 1099: 10.670) + K-1 Two Brothers, UPE, Royal Flush Inv. & Constr. (EIN 92-3349147) | E11: USD | F11: ='05_US_TAXES'!D11 -> 82153 | G11: N/A | I11: ='02_TAX_TIMELINE'!B13 -> NÃO RESIDENTE | J11: Fonte EUA, contribuinte não residente → não tributável no BR [INFERÊNCIA TÉCNICA] | K11: [FATO CONFIRMADO — PDF]; pagamento ao IRS NÃO comprovado
A12: Form 1040/2025 | B12: 2025 | C12: José | D12: Rendimentos EUA 2025 | E12: USD | G12: N/A | I12: NÃO RESIDENTE | J12: Não tributável no BR | K12: PENDENTE — DOCUMENTO NECESSÁRIO
A14: RECEBIMENTOS DE FONTE BR — ENTRADAS DE TERCEIROS (Nubank), por contraparte e ano — natureza a comprovar
A15: Documento | B15: Ano | C15: Contribuinte | D15: Contraparte | E15: Moeda | F15: Valor original | G15: Câmbio | H15: Valor R$ | I15: Situação fiscal no período | J15: Tratamento tributário BR | K15: Status
A16: Extratos Nubank | B16: 2024 | C16: José | D16: FELIPE DE MELO RODRIGUES | E16: BRL | F16: =SUMIFS('04_BANK_TRANSACTIONS'!$F$5:$F$168,'04_BANK_TRANSACTIONS'!$C$5:$C$168,2024,'04_BANK_TRANSACTIONS'!$E$5:$E$168,D16,'04_BANK_TRANSACTIONS'!$G$5:$G$168,"entrada",'04_BANK_TRANSACTIONS'!$H$5:$H$168,"terceiros") -> 44950 | G16: 1 | H16: =F16*G16 -> 44950 | I16: NÃO RESIDENTE | J16: =IF(COUNTIFS('04_BANK_TRANSACTIONS'!$C$5:$C$168,2024,'04_BANK_TRANSACTIONS'!$E$5:$E$168,D16,'04_BANK_TRANSACTIONS'!$K$5:$K$168,"PENDENTE")>0,"Natureza PENDENTE — se renda de fonte BR: IRRF 15%/25%; se empréstimo/venda de bem/doação: tratamento próprio","Classificado na aba 04") -> Natureza PENDENTE — se renda de fonte BR: IRRF 15%/25%; se empréstimo/venda de bem/doação: tratamento próprio | K16: PENDENTE — DOCUMENTO NECESSÁRIO
A17: Extratos Nubank | B17: 2024 | C17: José | D17: LEONARDO CARVALHO BARROS | E17: BRL | F17: =SUMIFS('04_BANK_TRANSACTIONS'!$F$5:$F$168,'04_BANK_TRANSACTIONS'!$C$5:$C$168,2024,'04_BANK_TRANSACTIONS'!$E$5:$E$168,D17,'04_BANK_TRANSACTIONS'!$G$5:$G$168,"entrada",'04_BANK_TRANSACTIONS'!$H$5:$H$168,"terceiros") -> 1500 | G17: 1 | H17: =F17*G17 -> 1500 | I17: NÃO RESIDENTE | J17: =IF(COUNTIFS('04_BANK_TRANSACTIONS'!$C$5:$C$168,2024,'04_BANK_TRANSACTIONS'!$E$5:$E$168,D17,'04_BANK_TRANSACTIONS'!$K$5:$K$168,"PENDENTE")>0,"Natureza PENDENTE — se renda de fonte BR: IRRF 15%/25%; se empréstimo/venda de bem/doação: tratamento próprio","Classificado na aba 04") -> Natureza PENDENTE — se renda de fonte BR: IRRF 15%/25%; se empréstimo/venda de bem/doação: tratamento próprio | K17: PENDENTE — DOCUMENTO NECESSÁRIO
A18: Extratos Nubank | B18: 2024 | C18: José | D18: DIEGO NOVAIS DE MELO FONSECA | E18: BRL | F18: =SUMIFS('04_BANK_TRANSACTIONS'!$F$5:$F$168,'04_BANK_TRANSACTIONS'!$C$5:$C$168,2024,'04_BANK_TRANSACTIONS'!$E$5:$E$168,D18,'04_BANK_TRANSACTIONS'!$G$5:$G$168,"entrada",'04_BANK_TRANSACTIONS'!$H$5:$H$168,"terceiros") -> 1000 | G18: 1 | H18: =F18*G18 -> 1000 | I18: NÃO RESIDENTE | J18: =IF(COUNTIFS('04_BANK_TRANSACTIONS'!$C$5:$C$168,2024,'04_BANK_TRANSACTIONS'!$E$5:$E$168,D18,'04_BANK_TRANSACTIONS'!$K$5:$K$168,"PENDENTE")>0,"Natureza PENDENTE — se renda de fonte BR: IRRF 15%/25%; se empréstimo/venda de bem/doação: tratamento próprio","Classificado na aba 04") -> Natureza PENDENTE — se renda de fonte BR: IRRF 15%/25%; se empréstimo/venda de bem/doação: tratamento próprio | K18: PENDENTE — DOCUMENTO NECESSÁRIO
A19: Extratos Nubank | B19: 2025 | C19: José | D19: REGINALDO FRANCISCO BESSA | E19: BRL | F19: =SUMIFS('04_BANK_TRANSACTIONS'!$F$5:$F$168,'04_BANK_TRANSACTIONS'!$C$5:$C$168,2025,'04_BANK_TRANSACTIONS'!$E$5:$E$168,D19,'04_BANK_TRANSACTIONS'!$G$5:$G$168,"entrada",'04_BANK_TRANSACTIONS'!$H$5:$H$168,"terceiros") -> 190000 | G19: 1 | H19: =F19*G19 -> 190000 | I19: NÃO RESIDENTE | J19: =IF(COUNTIFS('04_BANK_TRANSACTIONS'!$C$5:$C$168,2025,'04_BANK_TRANSACTIONS'!$E$5:$E$168,D19,'04_BANK_TRANSACTIONS'!$K$5:$K$168,"PENDENTE")>0,"Natureza PENDENTE — se renda de fonte BR: IRRF 15%/25%; se empréstimo/venda de bem/doação: tratamento próprio","Classificado na aba 04") -> Natureza PENDENTE — se renda de fonte BR: IRRF 15%/25%; se empréstimo/venda de bem/doação: tratamento próprio | K19: PENDENTE — DOCUMENTO NECESSÁRIO
A20: Extratos Nubank | B20: 2025 | C20: José | D20: ANDRE WERNER | E20: BRL | F20: =SUMIFS('04_BANK_TRANSACTIONS'!$F$5:$F$168,'04_BANK_TRANSACTIONS'!$C$5:$C$168,2025,'04_BANK_TRANSACTIONS'!$E$5:$E$168,D20,'04_BANK_TRANSACTIONS'!$G$5:$G$168,"entrada",'04_BANK_TRANSACTIONS'!$H$5:$H$168,"terceiros") -> 96000 | G20: 1 | H20: =F20*G20 -> 96000 | I20: NÃO RESIDENTE | J20: =IF(COUNTIFS('04_BANK_TRANSACTIONS'!$C$5:$C$168,2025,'04_BANK_TRANSACTIONS'!$E$5:$E$168,D20,'04_BANK_TRANSACTIONS'!$K$5:$K$168,"PENDENTE")>0,"Natureza PENDENTE — se renda de fonte BR: IRRF 15%/25%; se empréstimo/venda de bem/doação: tratamento próprio","Classificado na aba 04") -> Natureza PENDENTE — se renda de fonte BR: IRRF 15%/25%; se empréstimo/venda de bem/doação: tratamento próprio | K20: PENDENTE — DOCUMENTO NECESSÁRIO
A21: Extratos Nubank | B21: 2025 | C21: José | D21: WERSAN COMERCIO DE COMBUSTIVEIS LTDA | E21: BRL | F21: =SUMIFS('04_BANK_TRANSACTIONS'!$F$5:$F$168,'04_BANK_TRANSACTIONS'!$C$5:$C$168,2025,'04_BANK_TRANSACTIONS'!$E$5:$E$168,D21,'04_BANK_TRANSACTIONS'!$G$5:$G$168,"entrada",'04_BANK_TRANSACTIONS'!$H$5:$H$168,"terceiros") -> 69000 | G21: 1 | H21: =F21*G21 -> 69000 | I21: NÃO RESIDENTE | J21: =IF(COUNTIFS('04_BANK_TRANSACTIONS'!$C$5:$C$168,2025,'04_BANK_TRANSACTIONS'!$E$5:$E$168,D21,'04_BANK_TRANSACTIONS'!$K$5:$K$168,"PENDENTE")>0,"Natureza PENDENTE — se renda de fonte BR: IRRF 15%/25%; se empréstimo/venda de bem/doação: tratamento próprio","Classificado na aba 04") -> Natureza PENDENTE — se renda de fonte BR: IRRF 15%/25%; se empréstimo/venda de bem/doação: tratamento próprio | K21: PENDENTE — DOCUMENTO NECESSÁRIO
A22: Extratos Nubank | B22: 2025 | C22: José | D22: FELIPE DE MELO RODRIGUES | E22: BRL | F22: =SUMIFS('04_BANK_TRANSACTIONS'!$F$5:$F$168,'04_BANK_TRANSACTIONS'!$C$5:$C$168,2025,'04_BANK_TRANSACTIONS'!$E$5:$E$168,D22,'04_BANK_TRANSACTIONS'!$G$5:$G$168,"entrada",'04_BANK_TRANSACTIONS'!$H$5:$H$168,"terceiros") -> 61410 | G22: 1 | H22: =F22*G22 -> 61410 | I22: NÃO RESIDENTE | J22: =IF(COUNTIFS('04_BANK_TRANSACTIONS'!$C$5:$C$168,2025,'04_BANK_TRANSACTIONS'!$E$5:$E$168,D22,'04_BANK_TRANSACTIONS'!$K$5:$K$168,"PENDENTE")>0,"Natureza PENDENTE — se renda de fonte BR: IRRF 15%/25%; se empréstimo/venda de bem/doação: tratamento próprio","Classificado na aba 04") -> Natureza PENDENTE — se renda de fonte BR: IRRF 15%/25%; se empréstimo/venda de bem/doação: tratamento próprio | K22: PENDENTE — DOCUMENTO NECESSÁRIO
A23: Extratos Nubank | B23: 2025 | C23: José | D23: RODRIGO DE OLIVEIRA MACHADO | E23: BRL | F23: =SUMIFS('04_BANK_TRANSACTIONS'!$F$5:$F$168,'04_BANK_TRANSACTIONS'!$C$5:$C$168,2025,'04_BANK_TRANSACTIONS'!$E$5:$E$168,D23,'04_BANK_TRANSACTIONS'!$G$5:$G$168,"entrada",'04_BANK_TRANSACTIONS'!$H$5:$H$168,"terceiros") -> 44000 | G23: 1 | H23: =F23*G23 -> 44000 | I23: NÃO RESIDENTE | J23: =IF(COUNTIFS('04_BANK_TRANSACTIONS'!$C$5:$C$168,2025,'04_BANK_TRANSACTIONS'!$E$5:$E$168,D23,'04_BANK_TRANSACTIONS'!$K$5:$K$168,"PENDENTE")>0,"Natureza PENDENTE — se renda de fonte BR: IRRF 15%/25%; se empréstimo/venda de bem/doação: tratamento próprio","Classificado na aba 04") -> Natureza PENDENTE — se renda de fonte BR: IRRF 15%/25%; se empréstimo/venda de bem/doação: tratamento próprio | K23: PENDENTE — DOCUMENTO NECESSÁRIO
A24: Extratos Nubank | B24: 2025 | C24: José | D24: GEUCIR PEREIRA CALDEIRA | E24: BRL | F24: =SUMIFS('04_BANK_TRANSACTIONS'!$F$5:$F$168,'04_BANK_TRANSACTIONS'!$C$5:$C$168,2025,'04_BANK_TRANSACTIONS'!$E$5:$E$168,D24,'04_BANK_TRANSACTIONS'!$G$5:$G$168,"entrada",'04_BANK_TRANSACTIONS'!$H$5:$H$168,"terceiros") -> 40000 | G24: 1 | H24: =F24*G24 -> 40000 | I24: NÃO RESIDENTE | J24: =IF(COUNTIFS('04_BANK_TRANSACTIONS'!$C$5:$C$168,2025,'04_BANK_TRANSACTIONS'!$E$5:$E$168,D24,'04_BANK_TRANSACTIONS'!$K$5:$K$168,"PENDENTE")>0,"Natureza PENDENTE — se renda de fonte BR: IRRF 15%/25%; se empréstimo/venda de bem/doação: tratamento próprio","Classificado na aba 04") -> Natureza PENDENTE — se renda de fonte BR: IRRF 15%/25%; se empréstimo/venda de bem/doação: tratamento próprio | K24: PENDENTE — DOCUMENTO NECESSÁRIO
A25: Extratos Nubank | B25: 2025 | C25: José | D25: SUELY ANDREIA LEANDRO DO NASCIMENTO | E25: BRL | F25: =SUMIFS('04_BANK_TRANSACTIONS'!$F$5:$F$168,'04_BANK_TRANSACTIONS'!$C$5:$C$168,2025,'04_BANK_TRANSACTIONS'!$E$5:$E$168,D25,'04_BANK_TRANSACTIONS'!$G$5:$G$168,"entrada",'04_BANK_TRANSACTIONS'!$H$5:$H$168,"terceiros") -> 40000 | G25: 1 | H25: =F25*G25 -> 40000 | I25: NÃO RESIDENTE | J25: =IF(COUNTIFS('04_BANK_TRANSACTIONS'!$C$5:$C$168,2025,'04_BANK_TRANSACTIONS'!$E$5:$E$168,D25,'04_BANK_TRANSACTIONS'!$K$5:$K$168,"PENDENTE")>0,"Natureza PENDENTE — se renda de fonte BR: IRRF 15%/25%; se empréstimo/venda de bem/doação: tratamento próprio","Classificado na aba 04") -> Natureza PENDENTE — se renda de fonte BR: IRRF 15%/25%; se empréstimo/venda de bem/doação: tratamento próprio | K25: PENDENTE — DOCUMENTO NECESSÁRIO
A26: Extratos Nubank | B26: 2025 | C26: José | D26: DIEGO NOVAIS DE MELO FONSECA | E26: BRL | F26: =SUMIFS('04_BANK_TRANSACTIONS'!$F$5:$F$168,'04_BANK_TRANSACTIONS'!$C$5:$C$168,2025,'04_BANK_TRANSACTIONS'!$E$5:$E$168,D26,'04_BANK_TRANSACTIONS'!$G$5:$G$168,"entrada",'04_BANK_TRANSACTIONS'!$H$5:$H$168,"terceiros") -> 13500 | G26: 1 | H26: =F26*G26 -> 13500 | I26: NÃO RESIDENTE | J26: =IF(COUNTIFS('04_BANK_TRANSACTIONS'!$C$5:$C$168,2025,'04_BANK_TRANSACTIONS'!$E$5:$E$168,D26,'04_BANK_TRANSACTIONS'!$K$5:$K$168,"PENDENTE")>0,"Natureza PENDENTE — se renda de fonte BR: IRRF 15%/25%; se empréstimo/venda de bem/doação: tratamento próprio","Classificado na aba 04") -> Natureza PENDENTE — se renda de fonte BR: IRRF 15%/25%; se empréstimo/venda de bem/doação: tratamento próprio | K26: PENDENTE — DOCUMENTO NECESSÁRIO
A27: Extratos Nubank | B27: 2025 | C27: José | D27: ALEX SILVA DE SOUSA | E27: BRL | F27: =SUMIFS('04_BANK_TRANSACTIONS'!$F$5:$F$168,'04_BANK_TRANSACTIONS'!$C$5:$C$168,2025,'04_BANK_TRANSACTIONS'!$E$5:$E$168,D27,'04_BANK_TRANSACTIONS'!$G$5:$G$168,"entrada",'04_BANK_TRANSACTIONS'!$H$5:$H$168,"terceiros") -> 5870 | G27: 1 | H27: =F27*G27 -> 5870 | I27: NÃO RESIDENTE | J27: =IF(COUNTIFS('04_BANK_TRANSACTIONS'!$C$5:$C$168,2025,'04_BANK_TRANSACTIONS'!$E$5:$E$168,D27,'04_BANK_TRANSACTIONS'!$K$5:$K$168,"PENDENTE")>0,"Natureza PENDENTE — se renda de fonte BR: IRRF 15%/25%; se empréstimo/venda de bem/doação: tratamento próprio","Classificado na aba 04") -> Natureza PENDENTE — se renda de fonte BR: IRRF 15%/25%; se empréstimo/venda de bem/doação: tratamento próprio | K27: PENDENTE — DOCUMENTO NECESSÁRIO
A28: Extratos Nubank | B28: 2025 | C28: José | D28: DIEGO BRITO CORREIA | E28: BRL | F28: =SUMIFS('04_BANK_TRANSACTIONS'!$F$5:$F$168,'04_BANK_TRANSACTIONS'!$C$5:$C$168,2025,'04_BANK_TRANSACTIONS'!$E$5:$E$168,D28,'04_BANK_TRANSACTIONS'!$G$5:$G$168,"entrada",'04_BANK_TRANSACTIONS'!$H$5:$H$168,"terceiros") -> 5000 | G28: 1 | H28: =F28*G28 -> 5000 | I28: NÃO RESIDENTE | J28: =IF(COUNTIFS('04_BANK_TRANSACTIONS'!$C$5:$C$168,2025,'04_BANK_TRANSACTIONS'!$E$5:$E$168,D28,'04_BANK_TRANSACTIONS'!$K$5:$K$168,"PENDENTE")>0,"Natureza PENDENTE — se renda de fonte BR: IRRF 15%/25%; se empréstimo/venda de bem/doação: tratamento próprio","Classificado na aba 04") -> Natureza PENDENTE — se renda de fonte BR: IRRF 15%/25%; se empréstimo/venda de bem/doação: tratamento próprio | K28: PENDENTE — DOCUMENTO NECESSÁRIO
A29: Extratos Nubank | B29: 2025 | C29: José | D29: SANDRO DE ARAUJO MARRA | E29: BRL | F29: =SUMIFS('04_BANK_TRANSACTIONS'!$F$5:$F$168,'04_BANK_TRANSACTIONS'!$C$5:$C$168,2025,'04_BANK_TRANSACTIONS'!$E$5:$E$168,D29,'04_BANK_TRANSACTIONS'!$G$5:$G$168,"entrada",'04_BANK_TRANSACTIONS'!$H$5:$H$168,"terceiros") -> 1500 | G29: 1 | H29: =F29*G29 -> 1500 | I29: NÃO RESIDENTE | J29: =IF(COUNTIFS('04_BANK_TRANSACTIONS'!$C$5:$C$168,2025,'04_BANK_TRANSACTIONS'!$E$5:$E$168,D29,'04_BANK_TRANSACTIONS'!$K$5:$K$168,"PENDENTE")>0,"Natureza PENDENTE — se renda de fonte BR: IRRF 15%/25%; se empréstimo/venda de bem/doação: tratamento próprio","Classificado na aba 04") -> Natureza PENDENTE — se renda de fonte BR: IRRF 15%/25%; se empréstimo/venda de bem/doação: tratamento próprio | K29: PENDENTE — DOCUMENTO NECESSÁRIO
A30: Extratos Nubank | B30: 2025 | C30: José | D30: LEONARDO CARVALHO BARROS | E30: BRL | F30: =SUMIFS('04_BANK_TRANSACTIONS'!$F$5:$F$168,'04_BANK_TRANSACTIONS'!$C$5:$C$168,2025,'04_BANK_TRANSACTIONS'!$E$5:$E$168,D30,'04_BANK_TRANSACTIONS'!$G$5:$G$168,"entrada",'04_BANK_TRANSACTIONS'!$H$5:$H$168,"terceiros") -> 1000 | G30: 1 | H30: =F30*G30 -> 1000 | I30: NÃO RESIDENTE | J30: =IF(COUNTIFS('04_BANK_TRANSACTIONS'!$C$5:$C$168,2025,'04_BANK_TRANSACTIONS'!$E$5:$E$168,D30,'04_BANK_TRANSACTIONS'!$K$5:$K$168,"PENDENTE")>0,"Natureza PENDENTE — se renda de fonte BR: IRRF 15%/25%; se empréstimo/venda de bem/doação: tratamento próprio","Classificado na aba 04") -> Natureza PENDENTE — se renda de fonte BR: IRRF 15%/25%; se empréstimo/venda de bem/doação: tratamento próprio | K30: PENDENTE — DOCUMENTO NECESSÁRIO
... A32: Extratos Nubank | B32: 2025 | C32: José | D32: JOSIAS AMOREZE CARDOSO | E32: BRL | F32: =SUMIFS('04_BANK_TRANSACTIONS'!$F$5:$F$168,'04_BANK_TRANSACTIONS'!$C$5:$C$168,2025,'04_BANK_TRANSACTIONS'!$E$5:$E$168,D32,'04_BANK_TRANSACTIONS'!$G$5:$G$168,"entrada",'04_BANK_TRANSACTIONS'!$H$5:$H$168,"terceiros") -> 300 | G32: 1 | H32: =F32*G32 -> 300 | I32: NÃO RESIDENTE | J32: =IF(COUNTIFS('04_BANK_TRANSACTIONS'!$C$5:$C$168,2025,'04_BANK_TRANSACTIONS'!$E$5:$E$168,D32,'04_BANK_TRANSACTIONS'!$K$5:$K$168,"PENDENTE")>0,"Natureza PENDENTE — se renda de fonte BR: IRRF 15%/25%; se empréstimo/venda de bem/doação: tratamento próprio","Classificado na aba 04") -> Natureza PENDENTE — se renda de fonte BR: IRRF 15%/25%; se empréstimo/venda de bem/doação: tratamento próprio | K32: PENDENTE — DOCUMENTO NECESSÁRIO
A33: Extratos Nubank | B33: 2026 | C33: José | D33: LEONARDO CARVALHO BARROS | E33: BRL | F33: =SUMIFS('04_BANK_TRANSACTIONS'!$F$5:$F$168,'04_BANK_TRANSACTIONS'!$C$5:$C$168,2026,'04_BANK_TRANSACTIONS'!$E$5:$E$168,D33,'04_BANK_TRANSACTIONS'!$G$5:$G$168,"entrada",'04_BANK_TRANSACTIONS'!$H$5:$H$168,"terceiros") -> 8000 | G33: 1 | H33: =F33*G33 -> 8000 | I33: NÃO RESIDENTE | J33: =IF(COUNTIFS('04_BANK_TRANSACTIONS'!$C$5:$C$168,2026,'04_BANK_TRANSACTIONS'!$E$5:$E$168,D33,'04_BANK_TRANSACTIONS'!$K$5:$K$168,"PENDENTE")>0,"Natureza PENDENTE — se renda de fonte BR: IRRF 15%/25%; se empréstimo/venda de bem/doação: tratamento próprio","Classificado na aba 04") -> Natureza PENDENTE — se renda de fonte BR: IRRF 15%/25%; se empréstimo/venda de bem/doação: tratamento próprio | K33: PENDENTE — DOCUMENTO NECESSÁRIO
D34: TOTAL terceiros | H34: =SUM(H16:H33) -> 623510

Sheet 04_BANK_TRANSACTIONS
A1: 04 — MOVIMENTAÇÃO BANCÁRIA BRASIL (Nubank 89083502-4, out/2024–abr/2026) — classificação e IRRF
A2: José Adalmo Carvalho de Barros — CPF 069.351.996-70 | Resp. técnico: Robson Soares Bezerra — CRC/PR 062711/O
A3: Natureza: editar a coluna K (lista suspensa). IRRF apurado = só naturezas tributáveis. Cenários A/B = exposição máxima se a natureza PENDENTE fosse rendimento de fonte BR — NÃO é imposto devido. Vencimento do IRRF assumido na data do crédito [INFERÊNCIA TÉCNICA — confirmar]. Responsável legal pela retenção: a fonte pagadora [INFERÊNCIA TÉCNICA].
A4: ID | B4: Data | C4: Ano | D4: Descrição (extrato) | E4: Contraparte | F4: Valor BRL (+ entrada / − saída) | G4: Tipo | H4: Classe_7 (backup) | I4: Arquivo fonte | J4: Tratamento proposto | K4: Natureza (EDITAR) | L4: Material? | M4: Base ganho (só GCAP) | N4: Alíquota IRRF | O4: Base IRRF (só natureza tributável) | P4: IRRF apurado | Q4: Cenário A (15%) — só PENDENTE | R4: Cenário B (25%) — só PENDENTE | S4: Juros SELIC % | T4: Multa mora % | U4: IRRF apurado atualizado | V4: Cenário A atualizado | W4: Cenário B atualizado | X4: Vínculo imóvel
A5: 1 | B5: 45578 | C5: =YEAR(B5) -> 2024 | D5: Transferência recebida pelo Pix | BANCO DAYCOVAL SA REMITTANCE - 62.232.889 | /0001-90 - BCO DAYCOVAL S.A (0707) Agência: 1 | Conta: 1306-6 | E5: BANCO DAYCOVAL SA REMITTANCE | F5: 41475 | G5: entrada | H5: intermediario_remessa | I5: NU_890835024_01OUT2024_31OUT2024.pdf | J5: [HIPÓTESE] Remessa do exterior por instituição de câmbio — fonte estrangeira, fora do IRPF de não residente | K5: RECURSO_PROPRIO_EXTERIOR | L5: =IF(AND(G5="entrada",F5>='00_PARAMETROS'!$B$7),"SIM","NÃO") -> SIM | N5: {=IFERROR(INDEX('00_PARAMETROS'!$B$41:$B$54,MATCH(K5,'00_PARAMETROS'!$A$41:$A$54,0)),0)} -> 0 | O5: =IF(OR(G5<>"entrada",N5=0),0,IF(K5="VENDA_BEM_BR_GCAP",N(M5),F5)) -> 0 | P5: =ROUND(O5*N5,2) -> 0 | Q5: =IF(AND(G5="entrada",K5="PENDENTE"),ROUND(F5*'00_PARAMETROS'!$B$12,2),0) -> 0 | R5: =IF(AND(G5="entrada",K5="PENDENTE"),ROUND(F5*'00_PARAMETROS'!$B$13,2),0) -> 0 | S5: =IF(P5+Q5>0,SUMIFS(SELIC!$B$4:$B$96,SELIC!$A$4:$A$96,">="&DATE(YEAR(B5),MONTH(B5)+1,1),SELIC!$A$4:$A$96,"<="&DATE(YEAR('00_PARAMETROS'!$B$4),MONTH('00_PARAMETROS'!$B$4)-1,1))+'00_PARAMETROS'!$B$11,0) -> 0 | T5: =IF(P5+Q5>0,MIN('00_PARAMETROS'!$B$9,'00_PARAMETROS'!$B$8*MAX(0,'00_PARAMETROS'!$B$4-B5)),0) -> 0 | U5: =ROUND(P5*(1+S5+T5),2) -> 0 | V5: =ROUND(Q5*(1+S5+T5),2) -> 0 | W5: =ROUND(R5*(1+S5+T5),2) -> 0
A6: 2 | B6: 45578 | C6: =YEAR(B6) -> 2024 | D6: Aplicação RDB | E6: Aplicação RDB | F6: -41000 | G6: saida | H6: RDB | I6: NU_890835024_01OUT2024_31OUT2024.pdf | J6: Aplicação RDB (movimentação interna) | K6: SAIDA | L6: =IF(AND(G6="entrada",F6>='00_PARAMETROS'!$B$7),"SIM","NÃO") -> NÃO | N6: {=IFERROR(INDEX('00_PARAMETROS'!$B$41:$B$54,MATCH(K6,'00_PARAMETROS'!$A$41:$A$54,0)),0)} -> 0 | O6: =IF(OR(G6<>"entrada",N6=0),0,IF(K6="VENDA_BEM_BR_GCAP",N(M6),F6)) -> 0 | P6: =ROUND(O6*N6,2) -> 0 | Q6: =IF(AND(G6="entrada",K6="PENDENTE"),ROUND(F6*'00_PARAMETROS'!$B$12,2),0) -> 0 | R6: =IF(AND(G6="entrada",K6="PENDENTE"),ROUND(F6*'00_PARAMETROS'!$B$13,2),0) -> 0 | S6: =IF(P6+Q6>0,SUMIFS(SELIC!$B$4:$B$96,SELIC!$A$4:$A$96,">="&DATE(YEAR(B6),MONTH(B6)+1,1),SELIC!$A$4:$A$96,"<="&DATE(YEAR('00_PARAMETROS'!$B$4),MONTH('00_PARAMETROS'!$B$4)-1,1))+'00_PARAMETROS'!$B$11,0) -> 0 | T6: =IF(P6+Q6>0,MIN('00_PARAMETROS'!$B$9,'00_PARAMETROS'!$B$8*MAX(0,'00_PARAMETROS'!$B$4-B6)),0) -> 0 | U6: =ROUND(P6*(1+S6+T6),2) -> 0 | V6: =ROUND(Q6*(1+S6+T6),2) -> 0 | W6: =ROUND(R6*(1+S6+T6),2) -> 0
A7: 3 | B7: 45594 | C7: =YEAR(B7) -> 2024 | D7: Transferência enviada pelo Pix | Vitória Aparecida Carvalho de Barros - •••.947.926- | •• - CAIXA ECONOMICA FEDERAL (0104) Agência: | 108 Conta: 771878672-3 | E7: VITÓRIA APARECIDA CARVALHO DE BARROS | F7: -270 | G7: saida | H7: terceiros | I7: NU_890835024_01OUT2024_31OUT2024.pdf | J7: Débito — não é rendimento | K7: SAIDA | L7: =IF(AND(G7="entrada",F7>='00_PARAMETROS'!$B$7),"SIM","NÃO") -> NÃO | N7: {=IFERROR(INDEX('00_PARAMETROS'!$B$41:$B$54,MATCH(K7,'00_PARAMETROS'!$A$41:$A$54,0)),0)} -> 0 | O7: =IF(OR(G7<>"entrada",N7=0),0,IF(K7="VENDA_BEM_BR_GCAP",N(M7),F7)) -> 0 | P7: =ROUND(O7*N7,2) -> 0 | Q7: =IF(AND(G7="entrada",K7="PENDENTE"),ROUND(F7*'00_PARAMETROS'!$B$12,2),0) -> 0 | R7: =IF(AND(G7="entrada",K7="PENDENTE"),ROUND(F7*'00_PARAMETROS'!$B$13,2),0) -> 0 | S7: =IF(P7+Q7>0,SUMIFS(SELIC!$B$4:$B$96,SELIC!$A$4:$A$96,">="&DATE(YEAR(B7),MONTH(B7)+1,1),SELIC!$A$4:$A$96,"<="&DATE(YEAR('00_PARAMETROS'!$B$4),MONTH('00_PARAMETROS'!$B$4)-1,1))+'00_PARAMETROS'!$B$11,0) -> 0 | T7: =IF(P7+Q7>0,MIN('00_PARAMETROS'!$B$9,'00_PARAMETROS'!$B$8*MAX(0,'00_PARAMETROS'!$B$4-B7)),0) -> 0 | U7: =ROUND(P7*(1+S7+T7),2) -> 0 | V7: =ROUND(Q7*(1+S7+T7),2) -> 0 | W7: =ROUND(R7*(1+S7+T7),2) -> 0
A8: 4 | B8: 45595 | C8: =YEAR(B8) -> 2024 | D8: Transferência recebida pelo Pix | LEONARDO CARVALHO BARROS - •••.421.456-•• - | BCO DO BRASIL S.A. (0001) Agência: 25 Conta: | 510042852-6 | E8: LEONARDO CARVALHO BARROS | F8: 1000 | G8: entrada | H8: terceiros | I8: NU_890835024_01OUT2024_31OUT2024.pdf | J8: PENDENTE — DOCUMENTO NECESSÁRIO: natureza não comprovada (contrato, recibo, escritura, comprovante) | K8: PENDENTE | L8: =IF(AND(G8="entrada",F8>='00_PARAMETROS'!$B$7),"SIM","NÃO") -> NÃO | N8: {=IFERROR(INDEX('00_PARAMETROS'!$B$41:$B$54,MATCH(K8,'00_PARAMETROS'!$A$41:$A$54,0)),0)} -> 0 | O8: =IF(OR(G8<>"entrada",N8=0),0,IF(K8="VENDA_BEM_BR_GCAP",N(M8),F8)) -> 0 | P8: =ROUND(O8*N8,2) -> 0 | Q8: =IF(AND(G8="entrada",K8="PENDENTE"),ROUND(F8*'00_PARAMETROS'!$B$12,2),0) -> 150 | R8: =IF(AND(G8="entrada",K8="PENDENTE"),ROUND(F8*'00_PARAMETROS'!$B$13,2),0) -> 250 | S8: =IF(P8+Q8>0,SUMIFS(SELIC!$B$4:$B$96,SELIC!$A$4:$A$96,">="&DATE(YEAR(B8),MONTH(B8)+1,1),SELIC!$A$4:$A$96,"<="&DATE(YEAR('00_PARAMETROS'!$B$4),MONTH('00_PARAMETROS'!$B$4)-1,1))+'00_PARAMETROS'!$B$11,0) -> 0.2515 | T8: =IF(P8+Q8>0,MIN('00_PARAMETROS'!$B$9,'00_PARAMETROS'!$B$8*MAX(0,'00_PARAMETROS'!$B$4-B8)),0) -> 0.2 | U8: =ROUND(P8*(1+S8+T8),2) -> 0 | V8: =ROUND(Q8*(1+S8+T8),2) -> 217.73 | W8: =ROUND(R8*(1+S8+T8),2) -> 362.88
A9: 5 | B9: 45595 | C9: =YEAR(B9) -> 2024 | D9: Aplicação RDB | 89083502-4 | E9: 89083502-4 | F9: -1000 | G9: saida | H9: RDB | I9: NU_890835024_01OUT2024_31OUT2024.pdf | J9: Aplicação RDB (movimentação interna) | K9: SAIDA | L9: =IF(AND(G9="entrada",F9>='00_PARAMETROS'!$B$7),"SIM","NÃO") -> NÃO | N9: {=IFERROR(INDEX('00_PARAMETROS'!$B$41:$B$54,MATCH(K9,'00_PARAMETROS'!$A$41:$A$54,0)),0)} -> 0 | O9: =IF(OR(G9<>"entrada",N9=0),0,IF(K9="VENDA_BEM_BR_GCAP",N(M9),F9)) -> 0 | P9: =ROUND(O9*N9,2) -> 0 | Q9: =IF(AND(G9="entrada",K9="PENDENTE"),ROUND(F9*'00_PARAMETROS'!$B$12,2),0) -> 0 | R9: =IF(AND(G9="entrada",K9="PENDENTE"),ROUND(F9*'00_PARAMETROS'!$B$13,2),0) -> 0 | S9: =IF(P9+Q9>0,SUMIFS(SELIC!$B$4:$B$96,SELIC!$A$4:$A$96,">="&DATE(YEAR(B9),MONTH(B9)+1,1),SELIC!$A$4:$A$96,"<="&DATE(YEAR('00_PARAMETROS'!$B$4),MONTH('00_PARAMETROS'!$B$4)-1,1))+'00_PARAMETROS'!$B$11,0) -> 0 | T9: =IF(P9+Q9>0,MIN('00_PARAMETROS'!$B$9,'00_PARAMETROS'!$B$8*MAX(0,'00_PARAMETROS'!$B$4-B9)),0) -> 0 | U9: =ROUND(P9*(1+S9+T9),2) -> 0 | V9: =ROUND(Q9*(1+S9+T9),2) -> 0 | W9: =ROUND(R9*(1+S9+T9),2) -> 0
A10: 6 | B10: 45612 | C10: =YEAR(B10) -> 2024 | D10: Transferência recebida pelo Pix | FELIPE DE MELO RODRIGUES - •••.464.288-•• - ITAÚ | UNIBANCO S.A. (0341) Agência: 3247 Conta: | 40302-9 | E10: FELIPE DE MELO RODRIGUES | F10: 5000 | G10: entrada | H10: terceiros | I10: NU_890835024_01NOV2024_30NOV2024.pdf | J10: PENDENTE — DOCUMENTO NECESSÁRIO: natureza não comprovada (contrato, recibo, escritura, comprovante) | K10: PENDENTE | L10: =IF(AND(G10="entrada",F10>='00_PARAMETROS'!$B$7),"SIM","NÃO") -> NÃO | N10: {=IFERROR(INDEX('00_PARAMETROS'!$B$41:$B$54,MATCH(K10,'00_PARAMETROS'!$A$41:$A$54,0)),0)} -> 0 | O10: =IF(OR(G10<>"entrada",N10=0),0,IF(K10="VENDA_BEM_BR_GCAP",N(M10),F10)) -> 0 | P10: =ROUND(O10*N10,2) -> 0 | Q10: =IF(AND(G10="entrada",K10="PENDENTE"),ROUND(F10*'00_PARAMETROS'!$B$12,2),0) -> 750 | R10: =IF(AND(G10="entrada",K10="PENDENTE"),ROUND(F10*'00_PARAMETROS'!$B$13,2),0) -> 1250 | S10: =IF(P10+Q10>0,SUMIFS(SELIC!$B$4:$B$96,SELIC!$A$4:$A$96,">="&DATE(YEAR(B10),MONTH(B10)+1,1),SELIC!$A$4:$A$96,"<="&DATE(YEAR('00_PARAMETROS'!$B$4),MONTH('00_PARAMETROS'!$B$4)-1,1))+'00_PARAMETROS'!$B$11,0) -> 0.2436 | T10: =IF(P10+Q10>0,MIN('00_PARAMETROS'!$B$9,'00_PARAMETROS'!$B$8*MAX(0,'00_PARAMETROS'!$B$4-B10)),0) -> 0.2 | U10: =ROUND(P10*(1+S10+T10),2) -> 0 | V10: =ROUND(Q10*(1+S10+T10),2) -> 1082.7 | W10: =ROUND(R10*(1+S10+T10),2) -> 1804.5
A11: 7 | B11: 45612 | C11: =YEAR(B11) -> 2024 | D11: Transferência recebida pelo Pix | Felipe De Melo Rodrigues - •••.464.288-•• - NEON | PAGAMENTOS S.A. IP (0536) Agência: 655 Conta: | 23278478-7 | E11: FELIPE DE MELO RODRIGUES | F11: 8000 | G11: entrada | H11: terceiros | I11: NU_890835024_01NOV2024_30NOV2024.pdf | J11: PENDENTE — DOCUMENTO NECESSÁRIO: natureza não comprovada (contrato, recibo, escritura, comprovante) | K11: PENDENTE | L11: =IF(AND(G11="entrada",F11>='00_PARAMETROS'!$B$7),"SIM","NÃO") -> NÃO | N11: {=IFERROR(INDEX('00_PARAMETROS'!$B$41:$B$54,MATCH(K11,'00_PARAMETROS'!$A$41:$A$54,0)),0)} -> 0 | O11: =IF(OR(G11<>"entrada",N11=0),0,IF(K11="VENDA_BEM_BR_GCAP",N(M11),F11)) -> 0 | P11: =ROUND(O11*N11,2) -> 0 | Q11: =IF(AND(G11="entrada",K11="PENDENTE"),ROUND(F11*'00_PARAMETROS'!$B$12,2),0) -> 1200 | R11: =IF(AND(G11="entrada",K11="PENDENTE"),ROUND(F11*'00_PARAMETROS'!$B$13,2),0) -> 2000 | S11: =IF(P11+Q11>0,SUMIFS(SELIC!$B$4:$B$96,SELIC!$A$4:$A$96,">="&DATE(YEAR(B11),MONTH(B11)+1,1),SELIC!$A$4:$A$96,"<="&DATE(YEAR('00_PARAMETROS'!$B$4),MONTH('00_PARAMETROS'!$B$4)-1,1))+'00_PARAMETROS'!$B$11,0) -> 0.2436 | T11: =IF(P11+Q11>0,MIN('00_PARAMETROS'!$B$9,'00_PARAMETROS'!$B$8*MAX(0,'00_PARAMETROS'!$B$4-B11)),0) -> 0.2 | U11: =ROUND(P11*(1+S11+T11),2) -> 0 | V11: =ROUND(Q11*(1+S11+T11),2) -> 1732.32 | W11: =ROUND(R11*(1+S11+T11),2) -> 2887.2
A12: 8 | B12: 45612 | C12: =YEAR(B12) -> 2024 | D12: Transferência recebida pelo Pix | FELIPE DE MELO RODRIGUES - •••.464.288-•• - BCO | C6 S.A. (0336) Agência: 1 Conta: 15360860-9 | E12: FELIPE DE MELO RODRIGUES | F12: 3000 | G12: entrada | H12: terceiros | I12: NU_890835024_01NOV2024_30NOV2024.pdf | J12: PENDENTE — DOCUMENTO NECESSÁRIO: natureza não comprovada (contrato, recibo, escritura, comprovante) | K12: PENDENTE | L12: =IF(AND(G12="entrada",F12>='00_PARAMETROS'!$B$7),"SIM","NÃO") -> NÃO | N12: {=IFERROR(INDEX('00_PARAMETROS'!$B$41:$B$54,MATCH(K12,'00_PARAMETROS'!$A$41:$A$54,0)),0)} -> 0 | O12: =IF(OR(G12<>"entrada",N12=0),0,IF(K12="VENDA_BEM_BR_GCAP",N(M12),F12)) -> 0 | P12: =ROUND(O12*N12,2) -> 0 | Q12: =IF(AND(G12="entrada",K12="PENDENTE"),ROUND(F12*'00_PARAMETROS'!$B$12,2),0) -> 450 | R12: =IF(AND(G12="entrada",K12="PENDENTE"),ROUND(F12*'00_PARAMETROS'!$B$13,2),0) -> 750 | S12: =IF(P12+Q12>0,SUMIFS(SELIC!$B$4:$B$96,SELIC!$A$4:$A$96,">="&DATE(YEAR(B12),MONTH(B12)+1,1),SELIC!$A$4:$A$96,"<="&DATE(YEAR('00_PARAMETROS'!$B$4),MONTH('00_PARAMETROS'!$B$4)-1,1))+'00_PARAMETROS'!$B$11,0) -> 0.2436 | T12: =IF(P12+Q12>0,MIN('00_PARAMETROS'!$B$9,'00_PARAMETROS'!$B$8*MAX(0,'00_PARAMETROS'!$B$4-B12)),0) -> 0.2 | U12: =ROUND(P12*(1+S12+T12),2) -> 0 | V12: =ROUND(Q12*(1+S12+T12),2) -> 649.62 | W12: =ROUND(R12*(1+S12+T12),2) -> 1082.7
A13: 9 | B13: 45613 | C13: =YEAR(B13) -> 2024 | D13: Transferência recebida pelo Pix | FELIPE DE MELO RODRIGUES - •••.464.288-•• - ITAÚ | UNIBANCO S.A. (0341) Agência: 3247 Conta: | 40302-9 | E13: FELIPE DE MELO RODRIGUES | F13: 16000 | G13: entrada | H13: terceiros | I13: NU_890835024_01NOV2024_30NOV2024.pdf | J13: PENDENTE — DOCUMENTO NECESSÁRIO: natureza não comprovada (contrato, recibo, escritura, comprovante) | K13: PENDENTE | L13: =IF(AND(G13="entrada",F13>='00_PARAMETROS'!$B$7),"SIM","NÃO") -> SIM | N13: {=IFERROR(INDEX('00_PARAMETROS'!$B$41:$B$54,MATCH(K13,'00_PARAMETROS'!$A$41:$A$54,0)),0)} -> 0 | O13: =IF(OR(G13<>"entrada",N13=0),0,IF(K13="VENDA_BEM_BR_GCAP",N(M13),F13)) -> 0 | P13: =ROUND(O13*N13,2) -> 0 | Q13: =IF(AND(G13="entrada",K13="PENDENTE"),ROUND(F13*'00_PARAMETROS'!$B$12,2),0) -> 2400 | R13: =IF(AND(G13="entrada",K13="PENDENTE"),ROUND(F13*'00_PARAMETROS'!$B$13,2),0) -> 4000 | S13: =IF(P13+Q13>0,SUMIFS(SELIC!$B$4:$B$96,SELIC!$A$4:$A$96,">="&DATE(YEAR(B13),MONTH(B13)+1,1),SELIC!$A$4:$A$96,"<="&DATE(YEAR('00_PARAMETROS'!$B$4),MONTH('00_PARAMETROS'!$B$4)-1,1))+'00_PARAMETROS'!$B$11,0) -> 0.2436 | T13: =IF(P13+Q13>0,MIN('00_PARAMETROS'!$B$9,'00_PARAMETROS'!$B$8*MAX(0,'00_PARAMETROS'!$B$4-B13)),0) -> 0.2 | U13: =ROUND(P13*(1+S13+T13),2) -> 0 | V13: =ROUND(Q13*(1+S13+T13),2) -> 3464.64 | W13: =ROUND(R13*(1+S13+T13),2) -> 5774.4
A14: 10 | B14: 45613 | C14: =YEAR(B14) -> 2024 | D14: Transferência recebida pelo Pix | Felipe De Melo Rodrigues - •••.464.288-•• - NEON | PAGAMENTOS S.A. IP (0536) Agência: 655 Conta: | 23278478-7 | E14: FELIPE DE MELO RODRIGUES | F14: 8000 | G14: entrada | H14: terceiros | I14: NU_890835024_01NOV2024_30NOV2024.pdf | J14: PENDENTE — DOCUMENTO NECESSÁRIO: natureza não comprovada (contrato, recibo, escritura, comprovante) | K14: PENDENTE | L14: =IF(AND(G14="entrada",F14>='00_PARAMETROS'!$B$7),"SIM","NÃO") -> NÃO | N14: {=IFERROR(INDEX('00_PARAMETROS'!$B$41:$B$54,MATCH(K14,'00_PARAMETROS'!$A$41:$A$54,0)),0)} -> 0 | O14: =IF(OR(G14<>"entrada",N14=0),0,IF(K14="VENDA_BEM_BR_GCAP",N(M14),F14)) -> 0 | P14: =ROUND(O14*N14,2) -> 0 | Q14: =IF(AND(G14="entrada",K14="PENDENTE"),ROUND(F14*'00_PARAMETROS'!$B$12,2),0) -> 1200 | R14: =IF(AND(G14="entrada",K14="PENDENTE"),ROUND(F14*'00_PARAMETROS'!$B$13,2),0) -> 2000 | S14: =IF(P14+Q14>0,SUMIFS(SELIC!$B$4:$B$96,SELIC!$A$4:$A$96,">="&DATE(YEAR(B14),MONTH(B14)+1,1),SELIC!$A$4:$A$96,"<="&DATE(YEAR('00_PARAMETROS'!$B$4),MONTH('00_PARAMETROS'!$B$4)-1,1))+'00_PARAMETROS'!$B$11,0) -> 0.2436 | T14: =IF(P14+Q14>0,MIN('00_PARAMETROS'!$B$9,'00_PARAMETROS'!$B$8*MAX(0,'00_PARAMETROS'!$B$4-B14)),0) -> 0.2 | U14: =ROUND(P14*(1+S14+T14),2) -> 0 | V14: =ROUND(Q14*(1+S14+T14),2) -> 1732.32 | W14: =ROUND(R14*(1+S14+T14),2) -> 2887.2
A15: 11 | B15: 45614 | C15: =YEAR(B15) -> 2024 | D15: Transferência recebida pelo Pix | FELIPE DE MELO RODRIGUES - •••.464.288-•• - ITAÚ | UNIBANCO S.A. (0341) Agência: 3247 Conta: | 40302-9 | E15: FELIPE DE MELO RODRIGUES | F15: 4950 | G15: entrada | H15: terceiros | I15: NU_890835024_01NOV2024_30NOV2024.pdf | J15: PENDENTE — DOCUMENTO NECESSÁRIO: natureza não comprovada (contrato, recibo, escritura, comprovante) | K15: PENDENTE | L15: =IF(AND(G15="entrada",F15>='00_PARAMETROS'!$B$7),"SIM","NÃO") -> NÃO | N15: {=IFERROR(INDEX('00_PARAMETROS'!$B$41:$B$54,MATCH(K15,'00_PARAMETROS'!$A$41:$A$54,0)),0)} -> 0 | O15: =IF(OR(G15<>"entrada",N15=0),0,IF(K15="VENDA_BEM_BR_GCAP",N(M15),F15)) -> 0 | P15: =ROUND(O15*N15,2) -> 0 | Q15: =IF(AND(G15="entrada",K15="PENDENTE"),ROUND(F15*'00_PARAMETROS'!$B$12,2),0) -> 742.5 | R15: =IF(AND(G15="entrada",K15="PENDENTE"),ROUND(F15*'00_PARAMETROS'!$B$13,2),0) -> 1237.5 | S15: =IF(P15+Q15>0,SUMIFS(SELIC!$B$4:$B$96,SELIC!$A$4:$A$96,">="&DATE(YEAR(B15),MONTH(B15)+1,1),SELIC!$A$4:$A$96,"<="&DATE(YEAR('00_PARAMETROS'!$B$4),MONTH('00_PARAMETROS'!$B$4)-1,1))+'00_PARAMETROS'!$B$11,0) -> 0.2436 | T15: =IF(P15+Q15>0,MIN('00_PARAMETROS'!$B$9,'00_PARAMETROS'!$B$8*MAX(0,'00_PARAMETROS'!$B$4-B15)),0) -> 0.2 | U15: =ROUND(P15*(1+S15+T15),2) -> 0 | V15: =ROUND(Q15*(1+S15+T15),2) -> 1071.87 | W15: =ROUND(R15*(1+S15+T15),2) -> 1786.46
A16: 12 | B16: 45614 | C16: =YEAR(B16) -> 2024 | D16: Transferência enviada pelo Pix | Jasiel Greggio de Moraes - •••.117.228-•• - BCO DO | BRASIL S.A. (0001) Agência: 4094 Conta: 20226-6 | E16: JASIEL GREGGIO DE MORAES | F16: -200 | G16: saida | H16: terceiros | I16: NU_890835024_01NOV2024_30NOV2024.pdf | J16: Débito — não é rendimento | K16: SAIDA | L16: =IF(AND(G16="entrada",F16>='00_PARAMETROS'!$B$7),"SIM","NÃO") -> NÃO | N16: {=IFERROR(INDEX('00_PARAMETROS'!$B$41:$B$54,MATCH(K16,'00_PARAMETROS'!$A$41:$A$54,0)),0)} -> 0 | O16: =IF(OR(G16<>"entrada",N16=0),0,IF(K16="VENDA_BEM_BR_GCAP",N(M16),F16)) -> 0 | P16: =ROUND(O16*N16,2) -> 0 | Q16: =IF(AND(G16="entrada",K16="PENDENTE"),ROUND(F16*'00_PARAMETROS'!$B$12,2),0) -> 0 | R16: =IF(AND(G16="entrada",K16="PENDENTE"),ROUND(F16*'00_PARAMETROS'!$B$13,2),0) -> 0 | S16: =IF(P16+Q16>0,SUMIFS(SELIC!$B$4:$B$96,SELIC!$A$4:$A$96,">="&DATE(YEAR(B16),MONTH(B16)+1,1),SELIC!$A$4:$A$96,"<="&DATE(YEAR('00_PARAMETROS'!$B$4),MONTH('00_PARAMETROS'!$B$4)-1,1))+'00_PARAMETROS'!$B$11,0) -> 0 | T16: =IF(P16+Q16>0,MIN('00_PARAMETROS'!$B$9,'00_PARAMETROS'!$B$8*MAX(0,'00_PARAMETROS'!$B$4-B16)),0) -> 0 | U16: =ROUND(P16*(1+S16+T16),2) -> 0 | V16: =ROUND(Q16*(1+S16+T16),2) -> 0 | W16: =ROUND(R16*(1+S16+T16),2) -> 0
... A92: 88 | B92: 45866 | C92: =YEAR(B92) -> 2025 | D92: Transferência enviada pelo Pix | Adelio Joao Soares - •••.752.926-•• - BCO DO BRASIL | S.A. (0001) Agência: 25 Conta: 28854-3 | E92: ADELIO JOAO SOARES | F92: -150 | G92: saida | H92: terceiros | I92: 07.pdf | J92: Débito — não é rendimento | K92: SAIDA | L92: =IF(AND(G92="entrada",F92>='00_PARAMETROS'!$B$7),"SIM","NÃO") -> NÃO | N92: {=IFERROR(INDEX('00_PARAMETROS'!$B$41:$B$54,MATCH(K92,'00_PARAMETROS'!$A$41:$A$54,0)),0)} -> 0 | O92: =IF(OR(G92<>"entrada",N92=0),0,IF(K92="VENDA_BEM_BR_GCAP",N(M92),F92)) -> 0 | P92: =ROUND(O92*N92,2) -> 0 | Q92: =IF(AND(G92="entrada",K92="PENDENTE"),ROUND(F92*'00_PARAMETROS'!$B$12,2),0) -> 0 | R92: =IF(AND(G92="entrada",K92="PENDENTE"),ROUND(F92*'00_PARAMETROS'!$B$13,2),0) -> 0 | S92: =IF(P92+Q92>0,SUMIFS(SELIC!$B$4:$B$96,SELIC!$A$4:$A$96,">="&DATE(YEAR(B92),MONTH(B92)+1,1),SELIC!$A$4:$A$96,"<="&DATE(YEAR('00_PARAMETROS'!$B$4),MONTH('00_PARAMETROS'!$B$4)-1,1))+'00_PARAMETROS'!$B$11,0) -> 0 | T92: =IF(P92+Q92>0,MIN('00_PARAMETROS'!$B$9,'00_PARAMETROS'!$B$8*MAX(0,'00_PARAMETROS'!$B$4-B92)),0) -> 0 | U92: =ROUND(P92*(1+S92+T92),2) -> 0 | V92: =ROUND(Q92*(1+S92+T92),2) -> 0 | W92: =ROUND(R92*(1+S92+T92),2) -> 0
A93: 89 | B93: 45866 | C93: =YEAR(B93) -> 2025 | D93: Transferência enviada pelo Pix | N1 PORTO BELO EMPREENDIMENTOS - 43.796.362 | /0001-43 - CCLAA NOVA TRENTO Agência: 3242 | Conta: 72840-3 | E93: N1 PORTO BELO EMPREENDIMENTOS | F93: -5000 | G93: saida | H93: terceiros | I93: 07.pdf | J93: Pagamento — N1 Porto Belo / Vivapark [INFERÊNCIA — contrato indica conta VOKKAN] | K93: SAIDA | L93: =IF(AND(G93="entrada",F93>='00_PARAMETROS'!$B$7),"SIM","NÃO") -> NÃO | N93: {=IFERROR(INDEX('00_PARAMETROS'!$B$41:$B$54,MATCH(K93,'00_PARAMETROS'!$A$41:$A$54,0)),0)} -> 0 | O93: =IF(OR(G93<>"entrada",N93=0),0,IF(K93="VENDA_BEM_BR_GCAP",N(M93),F93)) -> 0 | P93: =ROUND(O93*N93,2) -> 0 | Q93: =IF(AND(G93="entrada",K93="PENDENTE"),ROUND(F93*'00_PARAMETROS'!$B$12,2),0) -> 0 | R93: =IF(AND(G93="entrada",K93="PENDENTE"),ROUND(F93*'00_PARAMETROS'!$B$13,2),0) -> 0 | S93: =IF(P93+Q93>0,SUMIFS(SELIC!$B$4:$B$96,SELIC!$A$4:$A$96,">="&DATE(YEAR(B93),MONTH(B93)+1,1),SELIC!$A$4:$A$96,"<="&DATE(YEAR('00_PARAMETROS'!$B$4),MONTH('00_PARAMETROS'!$B$4)-1,1))+'00_PARAMETROS'!$B$11,0) -> 0 | T93: =IF(P93+Q93>0,MIN('00_PARAMETROS'!$B$9,'00_PARAMETROS'!$B$8*MAX(0,'00_PARAMETROS'!$B$4-B93)),0) -> 0 | U93: =ROUND(P93*(1+S93+T93),2) -> 0 | V93: =ROUND(Q93*(1+S93+T93),2) -> 0 | W93: =ROUND(R93*(1+S93+T93),2) -> 0 | X93: N1 APTO 303
A94: 90 | B94: 45867 | C94: =YEAR(B94) -> 2025 | D94: Resgate RDB | E94: Resgate RDB | F94: 5000 | G94: entrada | H94: RDB | I94: 07.pdf | J94: [FATO CONFIRMADO] Resgate RDB — movimentação interna | K94: RDB_MOVIMENTACAO | L94: =IF(AND(G94="entrada",F94>='00_PARAMETROS'!$B$7),"SIM","NÃO") -> NÃO | N94: {=IFERROR(INDEX('00_PARAMETROS'!$B$41:$B$54,MATCH(K94,'00_PARAMETROS'!$A$41:$A$54,0)),0)} -> 0 | O94: =IF(OR(G94<>"entrada",N94=0),0,IF(K94="VENDA_BEM_BR_GCAP",N(M94),F94)) -> 0 | P94: =ROUND(O94*N94,2) -> 0 | Q94: =IF(AND(G94="entrada",K94="PENDENTE"),ROUND(F94*'00_PARAMETROS'!$B$12,2),0) -> 0 | R94: =IF(AND(G94="entrada",K94="PENDENTE"),ROUND(F94*'00_PARAMETROS'!$B$13,2),0) -> 0 | S94: =IF(P94+Q94>0,SUMIFS(SELIC!$B$4:$B$96,SELIC!$A$4:$A$96,">="&DATE(YEAR(B94),MONTH(B94)+1,1),SELIC!$A$4:$A$96,"<="&DATE(YEAR('00_PARAMETROS'!$B$4),MONTH('00_PARAMETROS'!$B$4)-1,1))+'00_PARAMETROS'!$B$11,0) -> 0 | T94: =IF(P94+Q94>0,MIN('00_PARAMETROS'!$B$9,'00_PARAMETROS'!$B$8*MAX(0,'00_PARAMETROS'!$B$4-B94)),0) -> 0 | U94: =ROUND(P94*(1+S94+T94),2) -> 0 | V94: =ROUND(Q94*(1+S94+T94),2) -> 0 | W94: =ROUND(R94*(1+S94+T94),2) -> 0
A95: 91 | B95: 45867 | C95: =YEAR(B95) -> 2025 | D95: Transferência recebida pelo Pix | WERSAN COMERCIO DE COMBUSTIVEIS LTDA - | 17.625.257/0001-31 - BCO SANTANDER (BRASIL) S. | 89083502-4 | A. (0033) Agência: 4278 Conta: 13001807-7 | E95: WERSAN COMERCIO DE COMBUSTIVEIS LTDA | F95: 49000 | G95: entrada | H95: terceiros | I95: 07.pdf | J95: PENDENTE — DOCUMENTO NECESSÁRIO: natureza não comprovada (contrato, recibo, escritura, comprovante) | K95: PENDENTE | L95: =IF(AND(G95="entrada",F95>='00_PARAMETROS'!$B$7),"SIM","NÃO") -> SIM | N95: {=IFERROR(INDEX('00_PARAMETROS'!$B$41:$B$54,MATCH(K95,'00_PARAMETROS'!$A$41:$A$54,0)),0)} -> 0 | O95: =IF(OR(G95<>"entrada",N95=0),0,IF(K95="VENDA_BEM_BR_GCAP",N(M95),F95)) -> 0 | P95: =ROUND(O95*N95,2) -> 0 | Q95: =IF(AND(G95="entrada",K95="PENDENTE"),ROUND(F95*'00_PARAMETROS'!$B$12,2),0) -> 7350 | R95: =IF(AND(G95="entrada",K95="PENDENTE"),ROUND(F95*'00_PARAMETROS'!$B$13,2),0) -> 12250 | S95: =IF(P95+Q95>0,SUMIFS(SELIC!$B$4:$B$96,SELIC!$A$4:$A$96,">="&DATE(YEAR(B95),MONTH(B95)+1,1),SELIC!$A$4:$A$96,"<="&DATE(YEAR('00_PARAMETROS'!$B$4),MONTH('00_PARAMETROS'!$B$4)-1,1))+'00_PARAMETROS'!$B$11,0) -> 0.1589 | T95: =IF(P95+Q95>0,MIN('00_PARAMETROS'!$B$9,'00_PARAMETROS'!$B$8*MAX(0,'00_PARAMETROS'!$B$4-B95)),0) -> 0.2 | U95: =ROUND(P95*(1+S95+T95),2) -> 0 | V95: =ROUND(Q95*(1+S95+T95),2) -> 9987.92 | W95: =ROUND(R95*(1+S95+T95),2) -> 16646.53
A96: 92 | B96: 45867 | C96: =YEAR(B96) -> 2025 | D96: Transferência enviada pelo Pix | Rofran Construtora Ltda - 51.819.924/0001-55 - | COOP SICREDI VALE LITORAL SC Agência: 2606 | Conta: 63110-5 | E96: ROFRAN CONSTRUTORA LTDA | F96: -5000 | G96: saida | H96: terceiros | I96: 07.pdf | J96: Pagamento — Loft 605 Blue Ocean (Rofran) | K96: SAIDA | L96: =IF(AND(G96="entrada",F96>='00_PARAMETROS'!$B$7),"SIM","NÃO") -> NÃO | N96: {=IFERROR(INDEX('00_PARAMETROS'!$B$41:$B$54,MATCH(K96,'00_PARAMETROS'!$A$41:$A$54,0)),0)} -> 0 | O96: =IF(OR(G96<>"entrada",N96=0),0,IF(K96="VENDA_BEM_BR_GCAP",N(M96),F96)) -> 0 | P96: =ROUND(O96*N96,2) -> 0 | Q96: =IF(AND(G96="entrada",K96="PENDENTE"),ROUND(F96*'00_PARAMETROS'!$B$12,2),0) -> 0 | R96: =IF(AND(G96="entrada",K96="PENDENTE"),ROUND(F96*'00_PARAMETROS'!$B$13,2),0) -> 0 | S96: =IF(P96+Q96>0,SUMIFS(SELIC!$B$4:$B$96,SELIC!$A$4:$A$96,">="&DATE(YEAR(B96),MONTH(B96)+1,1),SELIC!$A$4:$A$96,"<="&DATE(YEAR('00_PARAMETROS'!$B$4),MONTH('00_PARAMETROS'!$B$4)-1,1))+'00_PARAMETROS'!$B$11,0) -> 0 | T96: =IF(P96+Q96>0,MIN('00_PARAMETROS'!$B$9,'00_PARAMETROS'!$B$8*MAX(0,'00_PARAMETROS'!$B$4-B96)),0) -> 0 | U96: =ROUND(P96*(1+S96+T96),2) -> 0 | V96: =ROUND(Q96*(1+S96+T96),2) -> 0 | W96: =ROUND(R96*(1+S96+T96),2) -> 0 | X96: BLUE OCEAN 605
A97: 93 | B97: 45868 | C97: =YEAR(B97) -> 2025 | D97: Transferência recebida pelo Pix | ANDRE WERNER - •••.744.728-•• - ITAÚ UNIBANCO | S.A. (0341) Agência: 7012 Conta: 2282-3 | E97: ANDRE WERNER | F97: 51000 | G97: entrada | H97: terceiros | I97: 07.pdf | J97: PENDENTE — DOCUMENTO NECESSÁRIO: natureza não comprovada (contrato, recibo, escritura, comprovante) | K97: PENDENTE | L97: =IF(AND(G97="entrada",F97>='00_PARAMETROS'!$B$7),"SIM","NÃO") -> SIM | N97: {=IFERROR(INDEX('00_PARAMETROS'!$B$41:$B$54,MATCH(K97,'00_PARAMETROS'!$A$41:$A$54,0)),0)} -> 0 | O97: =IF(OR(G97<>"entrada",N97=0),0,IF(K97="VENDA_BEM_BR_GCAP",N(M97),F97)) -> 0 | P97: =ROUND(O97*N97,2) -> 0 | Q97: =IF(AND(G97="entrada",K97="PENDENTE"),ROUND(F97*'00_PARAMETROS'!$B$12,2),0) -> 7650 | R97: =IF(AND(G97="entrada",K97="PENDENTE"),ROUND(F97*'00_PARAMETROS'!$B$13,2),0) -> 12750 | S97: =IF(P97+Q97>0,SUMIFS(SELIC!$B$4:$B$96,SELIC!$A$4:$A$96,">="&DATE(YEAR(B97),MONTH(B97)+1,1),SELIC!$A$4:$A$96,"<="&DATE(YEAR('00_PARAMETROS'!$B$4),MONTH('00_PARAMETROS'!$B$4)-1,1))+'00_PARAMETROS'!$B$11,0) -> 0.1589 | T97: =IF(P97+Q97>0,MIN('00_PARAMETROS'!$B$9,'00_PARAMETROS'!$B$8*MAX(0,'00_PARAMETROS'!$B$4-B97)),0) -> 0.2 | U97: =ROUND(P97*(1+S97+T97),2) -> 0 | V97: =ROUND(Q97*(1+S97+T97),2) -> 10395.59 | W97: =ROUND(R97*(1+S97+T97),2) -> 17325.98
A98: 94 | B98: 45868 | C98: =YEAR(B98) -> 2025 | D98: Resgate RDB | E98: Resgate RDB | F98: 67269.32 | G98: entrada | H98: RDB | I98: 07.pdf | J98: [FATO CONFIRMADO] Resgate RDB — movimentação interna | K98: RDB_MOVIMENTACAO | L98: =IF(AND(G98="entrada",F98>='00_PARAMETROS'!$B$7),"SIM","NÃO") -> SIM | N98: {=IFERROR(INDEX('00_PARAMETROS'!$B$41:$B$54,MATCH(K98,'00_PARAMETROS'!$A$41:$A$54,0)),0)} -> 0 | O98: =IF(OR(G98<>"entrada",N98=0),0,IF(K98="VENDA_BEM_BR_GCAP",N(M98),F98)) -> 0 | P98: =ROUND(O98*N98,2) -> 0 | Q98: =IF(AND(G98="entrada",K98="PENDENTE"),ROUND(F98*'00_PARAMETROS'!$B$12,2),0) -> 0 | R98: =IF(AND(G98="entrada",K98="PENDENTE"),ROUND(F98*'00_PARAMETROS'!$B$13,2),0) -> 0 | S98: =IF(P98+Q98>0,SUMIFS(SELIC!$B$4:$B$96,SELIC!$A$4:$A$96,">="&DATE(YEAR(B98),MONTH(B98)+1,1),SELIC!$A$4:$A$96,"<="&DATE(YEAR('00_PARAMETROS'!$B$4),MONTH('00_PARAMETROS'!$B$4)-1,1))+'00_PARAMETROS'!$B$11,0) -> 0 | T98: =IF(P98+Q98>0,MIN('00_PARAMETROS'!$B$9,'00_PARAMETROS'!$B$8*MAX(0,'00_PARAMETROS'!$B$4-B98)),0) -> 0 | U98: =ROUND(P98*(1+S98+T98),2) -> 0 | V98: =ROUND(Q98*(1+S98+T98),2) -> 0 | W98: =ROUND(R98*(1+S98+T98),2) -> 0
A99: 95 | B99: 45868 | C99: =YEAR(B99) -> 2025 | D99: Transferência enviada pelo Pix | Vitória Aparecida Carvalho de Barros - •••.947.926- | •• - CAIXA ECONOMICA FEDERAL (0104) Agência: | 108 Conta: 771878672-3 | E99: VITÓRIA APARECIDA CARVALHO DE BARROS | F99: -392 | G99: saida | H99: terceiros | I99: 07.pdf | J99: Débito — não é rendimento | K99: SAIDA | L99: =IF(AND(G99="entrada",F99>='00_PARAMETROS'!$B$7),"SIM","NÃO") -> NÃO | N99: {=IFERROR(INDEX('00_PARAMETROS'!$B$41:$B$54,MATCH(K99,'00_PARAMETROS'!$A$41:$A$54,0)),0)} -> 0 | O99: =IF(OR(G99<>"entrada",N99=0),0,IF(K99="VENDA_BEM_BR_GCAP",N(M99),F99)) -> 0 | P99: =ROUND(O99*N99,2) -> 0 | Q99: =IF(AND(G99="entrada",K99="PENDENTE"),ROUND(F99*'00_PARAMETROS'!$B$12,2),0) -> 0 | R99: =IF(AND(G99="entrada",K99="PENDENTE"),ROUND(F99*'00_PARAMETROS'!$B$13,2),0) -> 0 | S99: =IF(P99+Q99>0,SUMIFS(SELIC!$B$4:$B$96,SELIC!$A$4:$A$96,">="&DATE(YEAR(B99),MONTH(B99)+1,1),SELIC!$A$4:$A$96,"<="&DATE(YEAR('00_PARAMETROS'!$B$4),MONTH('00_PARAMETROS'!$B$4)-1,1))+'00_PARAMETROS'!$B$11,0) -> 0 | T99: =IF(P99+Q99>0,MIN('00_PARAMETROS'!$B$9,'00_PARAMETROS'!$B$8*MAX(0,'00_PARAMETROS'!$B$4-B99)),0) -> 0 | U99: =ROUND(P99*(1+S99+T99),2) -> 0 | V99: =ROUND(Q99*(1+S99+T99),2) -> 0 | W99: =ROUND(R99*(1+S99+T99),2) -> 0
A100: 96 | B100: 45869 | C100: =YEAR(B100) -> 2025 | D100: Transferência enviada pelo Pix | N1 PORTO BELO EMPREENDIMENTOS - 43.796.362 | /0001-43 - CCLAA NOVA TRENTO Agência: 3242 | Conta: 72840-3 | 89083502-4 | E100: N1 PORTO BELO EMPREENDIMENTOS | F100: -40000 | G100: saida | H100: terceiros | I100: 07.pdf | J100: Pagamento — N1 Porto Belo / Vivapark [INFERÊNCIA — contrato indica conta VOKKAN] | K100: SAIDA | L100: =IF(AND(G100="entrada",F100>='00_PARAMETROS'!$B$7),"SIM","NÃO") -> NÃO | N100: {=IFERROR(INDEX('00_PARAMETROS'!$B$41:$B$54,MATCH(K100,'00_PARAMETROS'!$A$41:$A$54,0)),0)} -> 0 | O100: =IF(OR(G100<>"entrada",N100=0),0,IF(K100="VENDA_BEM_BR_GCAP",N(M100),F100)) -> 0 | P100: =ROUND(O100*N100,2) -> 0 | Q100: =IF(AND(G100="entrada",K100="PENDENTE"),ROUND(F100*'00_PARAMETROS'!$B$12,2),0) -> 0 | R100: =IF(AND(G100="entrada",K100="PENDENTE"),ROUND(F100*'00_PARAMETROS'!$B$13,2),0) -> 0 | S100: =IF(P100+Q100>0,SUMIFS(SELIC!$B$4:$B$96,SELIC!$A$4:$A$96,">="&DATE(YEAR(B100),MONTH(B100)+1,1),SELIC!$A$4:$A$96,"<="&DATE(YEAR('00_PARAMETROS'!$B$4),MONTH('00_PARAMETROS'!$B$4)-1,1))+'00_PARAMETROS'!$B$11,0) -> 0 | T100: =IF(P100+Q100>0,MIN('00_PARAMETROS'!$B$9,'00_PARAMETROS'!$B$8*MAX(0,'00_PARAMETROS'!$B$4-B100)),0) -> 0 | U100: =ROUND(P100*(1+S100+T100),2) -> 0 | V100: =ROUND(Q100*(1+S100+T100),2) -> 0 | W100: =ROUND(R100*(1+S100+T100),2) -> 0 | X100: N1 APTO 303
A101: 97 | B101: 45870 | C101: =YEAR(B101) -> 2025 | D101: Transferência enviada pelo Pix | Rofran Construtora Ltda - 51.819.924/0001-55 - | COOP SICREDI VALE LITORAL SC Agência: 2606 | Conta: 63110-5 | E101: ROFRAN CONSTRUTORA LTDA | F101: -45000 | G101: saida | H101: terceiros | I101: 08.pdf | J101: Pagamento — Loft 605 Blue Ocean (Rofran) | K101: SAIDA | L101: =IF(AND(G101="entrada",F101>='00_PARAMETROS'!$B$7),"SIM","NÃO") -> NÃO | N101: {=IFERROR(INDEX('00_PARAMETROS'!$B$41:$B$54,MATCH(K101,'00_PARAMETROS'!$A$41:$A$54,0)),0)} -> 0 | O101: =IF(OR(G101<>"entrada",N101=0),0,IF(K101="VENDA_BEM_BR_GCAP",N(M101),F101)) -> 0 | P101: =ROUND(O101*N101,2) -> 0 | Q101: =IF(AND(G101="entrada",K101="PENDENTE"),ROUND(F101*'00_PARAMETROS'!$B$12,2),0) -> 0 | R101: =IF(AND(G101="entrada",K101="PENDENTE"),ROUND(F101*'00_PARAMETROS'!$B$13,2),0) -> 0 | S101: =IF(P101+Q101>0,SUMIFS(SELIC!$B$4:$B$96,SELIC!$A$4:$A$96,">="&DATE(YEAR(B101),MONTH(B101)+1,1),SELIC!$A$4:$A$96,"<="&DATE(YEAR('00_PARAMETROS'!$B$4),MONTH('00_PARAMETROS'!$B$4)-1,1))+'00_PARAMETROS'!$B$11,0) -> 0 | T101: =IF(P101+Q101>0,MIN('00_PARAMETROS'!$B$9,'00_PARAMETROS'!$B$8*MAX(0,'00_PARAMETROS'!$B$4-B101)),0) -> 0 | U101: =ROUND(P101*(1+S101+T101),2) -> 0 | V101: =ROUND(Q101*(1+S101+T101),2) -> 0 | W101: =ROUND(R101*(1+S101+T101),2) -> 0 | X101: BLUE OCEAN 605
A102: 98 | B102: 45870 | C102: =YEAR(B102) -> 2025 | D102: Transferência enviada pelo Pix | N1 PORTO BELO EMPREENDIMENTOS - 43.796.362 | /0001-43 - CCLAA NOVA TRENTO Agência: 3242 | Conta: 72840-3 | E102: N1 PORTO BELO EMPREENDIMENTOS | F102: -4200 | G102: saida | H102: terceiros | I102: 08.pdf | J102: Pagamento — N1 Porto Belo / Vivapark [INFERÊNCIA — contrato indica conta VOKKAN] | K102: SAIDA | L102: =IF(AND(G102="entrada",F102>='00_PARAMETROS'!$B$7),"SIM","NÃO") -> NÃO | N102: {=IFERROR(INDEX('00_PARAMETROS'!$B$41:$B$54,MATCH(K102,'00_PARAMETROS'!$A$41:$A$54,0)),0)} -> 0 | O102: =IF(OR(G102<>"entrada",N102=0),0,IF(K102="VENDA_BEM_BR_GCAP",N(M102),F102)) -> 0 | P102: =ROUND(O102*N102,2) -> 0 | Q102: =IF(AND(G102="entrada",K102="PENDENTE"),ROUND(F102*'00_PARAMETROS'!$B$12,2),0) -> 0 | R102: =IF(AND(G102="entrada",K102="PENDENTE"),ROUND(F102*'00_PARAMETROS'!$B$13,2),0) -> 0 | S102: =IF(P102+Q102>0,SUMIFS(SELIC!$B$4:$B$96,SELIC!$A$4:$A$96,">="&DATE(YEAR(B102),MONTH(B102)+1,1),SELIC!$A$4:$A$96,"<="&DATE(YEAR('00_PARAMETROS'!$B$4),MONTH('00_PARAMETROS'!$B$4)-1,1))+'00_PARAMETROS'!$B$11,0) -> 0 | T102: =IF(P102+Q102>0,MIN('00_PARAMETROS'!$B$9,'00_PARAMETROS'!$B$8*MAX(0,'00_PARAMETROS'!$B$4-B102)),0) -> 0 | U102: =ROUND(P102*(1+S102+T102),2) -> 0 | V102: =ROUND(Q102*(1+S102+T102),2) -> 0 | W102: =ROUND(R102*(1+S102+T102),2) -> 0 | X102: N1 APTO 303
A103: 99 | B103: 45871 | C103: =YEAR(B103) -> 2025 | D103: Transferência enviada pelo Pix | Rofran Construtora Ltda - 51.819.924/0001-55 - | COOP SICREDI VALE LITORAL SC Agência: 2606 | Conta: 63110-5 | E103: ROFRAN CONSTRUTORA LTDA | F103: -45000 | G103: saida | H103: terceiros | I103: 08.pdf | J103: Pagamento — Loft 605 Blue Ocean (Rofran) | K103: SAIDA | L103: =IF(AND(G103="entrada",F103>='00_PARAMETROS'!$B$7),"SIM","NÃO") -> NÃO | N103: {=IFERROR(INDEX('00_PARAMETROS'!$B$41:$B$54,MATCH(K103,'00_PARAMETROS'!$A$41:$A$54,0)),0)} -> 0 | O103: =IF(OR(G103<>"entrada",N103=0),0,IF(K103="VENDA_BEM_BR_GCAP",N(M103),F103)) -> 0 | P103: =ROUND(O103*N103,2) -> 0 | Q103: =IF(AND(G103="entrada",K103="PENDENTE"),ROUND(F103*'00_PARAMETROS'!$B$12,2),0) -> 0 | R103: =IF(AND(G103="entrada",K103="PENDENTE"),ROUND(F103*'00_PARAMETROS'!$B$13,2),0) -> 0 | S103: =IF(P103+Q103>0,SUMIFS(SELIC!$B$4:$B$96,SELIC!$A$4:$A$96,">="&DATE(YEAR(B103),MONTH(B103)+1,1),SELIC!$A$4:$A$96,"<="&DATE(YEAR('00_PARAMETROS'!$B$4),MONTH('00_PARAMETROS'!$B$4)-1,1))+'00_PARAMETROS'!$B$11,0) -> 0 | T103: =IF(P103+Q103>0,MIN('00_PARAMETROS'!$B$9,'00_PARAMETROS'!$B$8*MAX(0,'00_PARAMETROS'!$B$4-B103)),0) -> 0 | U103: =ROUND(P103*(1+S103+T103),2) -> 0 | V103: =ROUND(Q103*(1+S103+T103),2) -> 0 | W103: =ROUND(R103*(1+S103+T103),2) -> 0 | X103: BLUE OCEAN 605
A104: 100 | B104: 45871 | C104: =YEAR(B104) -> 2025 | D104: Transferência enviada pelo Pix | Valdeni Novais de Melo - •••.252.208-•• - ITAÚ | UNIBANCO S.A. (0341) Agência: 844 Conta: 7281-9 | E104: VALDENI NOVAIS DE MELO | F104: -3000 | G104: saida | H104: terceiros | I104: 08.pdf | J104: Débito — não é rendimento | K104: SAIDA | L104: =IF(AND(G104="entrada",F104>='00_PARAMETROS'!$B$7),"SIM","NÃO") -> NÃO | N104: {=IFERROR(INDEX('00_PARAMETROS'!$B$41:$B$54,MATCH(K104,'00_PARAMETROS'!$A$41:$A$54,0)),0)} -> 0 | O104: =IF(OR(G104<>"entrada",N104=0),0,IF(K104="VENDA_BEM_BR_GCAP",N(M104),F104)) -> 0 | P104: =ROUND(O104*N104,2) -> 0 | Q104: =IF(AND(G104="entrada",K104="PENDENTE"),ROUND(F104*'00_PARAMETROS'!$B$12,2),0) -> 0 | R104: =IF(AND(G104="entrada",K104="PENDENTE"),ROUND(F104*'00_PARAMETROS'!$B$13,2),0) -> 0 | S104: =IF(P104+Q104>0,SUMIFS(SELIC!$B$4:$B$96,SELIC!$A$4:$A$96,">="&DATE(YEAR(B104),MONTH(B104)+1,1),SELIC!$A$4:$A$96,"<="&DATE(YEAR('00_PARAMETROS'!$B$4),MONTH('00_PARAMETROS'!$B$4)-1,1))+'00_PARAMETROS'!$B$11,0) -> 0 | T104: =IF(P104+Q104>0,MIN('00_PARAMETROS'!$B$9,'00_PARAMETROS'!$B$8*MAX(0,'00_PARAMETROS'!$B$4-B104)),0) -> 0 | U104: =ROUND(P104*(1+S104+T104),2) -> 0 | V104: =ROUND(Q104*(1+S104+T104),2) -> 0 | W104: =ROUND(R104*(1+S104+T104),2) -> 0
A105: 101 | B105: 45872 | C105: =YEAR(B105) -> 2025 | D105: Transferência Recebida | Marcia Novais de Melo Barros - •••.515.229-•• - NU | PAGAMENTOS - IP (0260) Agência: 1 Conta: | 368339173-1 | 89083502-4 | E105: MARCIA NOVAIS DE MELO BARROS | F105: 45000 | G105: entrada | H105: conta_conjuge | I105: 08.pdf | J105: [HIPÓTESE] Transferência da cônjuge — não é renda; comprovar a origem dos recursos dela | K105: TRANSF_CONJUGE | L105: =IF(AND(G105="entrada",F105>='00_PARAMETROS'!$B$7),"SIM","NÃO") -> SIM | N105: {=IFERROR(INDEX('00_PARAMETROS'!$B$41:$B$54,MATCH(K105,'00_PARAMETROS'!$A$41:$A$54,0)),0)} -> 0 | O105: =IF(OR(G105<>"entrada",N105=0),0,IF(K105="VENDA_BEM_BR_GCAP",N(M105),F105)) -> 0 | P105: =ROUND(O105*N105,2) -> 0 | Q105: =IF(AND(G105="entrada",K105="PENDENTE"),ROUND(F105*'00_PARAMETROS'!$B$12,2),0) -> 0 | R105: =IF(AND(G105="entrada",K105="PENDENTE"),ROUND(F105*'00_PARAMETROS'!$B$13,2),0) -> 0 | S105: =IF(P105+Q105>0,SUMIFS(SELIC!$B$4:$B$96,SELIC!$A$4:$A$96,">="&DATE(YEAR(B105),MONTH(B105)+1,1),SELIC!$A$4:$A$96,"<="&DATE(YEAR('00_PARAMETROS'!$B$4),MONTH('00_PARAMETROS'!$B$4)-1,1))+'00_PARAMETROS'!$B$11,0) -> 0 | T105: =IF(P105+Q105>0,MIN('00_PARAMETROS'!$B$9,'00_PARAMETROS'!$B$8*MAX(0,'00_PARAMETROS'!$B$4-B105)),0) -> 0 | U105: =ROUND(P105*(1+S105+T105),2) -> 0 | V105: =ROUND(Q105*(1+S105+T105),2) -> 0 | W105: =ROUND(R105*(1+S105+T105),2) -> 0
A106: 102 | B106: 45872 | C106: =YEAR(B106) -> 2025 | D106: Transferência enviada pelo Pix | Rofran Construtora Ltda - 51.819.924/0001-55 - | COOP SICREDI VALE LITORAL SC Agência: 2606 | Conta: 63110-5 | E106: ROFRAN CONSTRUTORA LTDA | F106: -25000 | G106: saida | H106: terceiros | I106: 08.pdf | J106: Pagamento — Loft 605 Blue Ocean (Rofran) | K106: SAIDA | L106: =IF(AND(G106="entrada",F106>='00_PARAMETROS'!$B$7),"SIM","NÃO") -> NÃO | N106: {=IFERROR(INDEX('00_PARAMETROS'!$B$41:$B$54,MATCH(K106,'00_PARAMETROS'!$A$41:$A$54,0)),0)} -> 0 | O106: =IF(OR(G106<>"entrada",N106=0),0,IF(K106="VENDA_BEM_BR_GCAP",N(M106),F106)) -> 0 | P106: =ROUND(O106*N106,2) -> 0 | Q106: =IF(AND(G106="entrada",K106="PENDENTE"),ROUND(F106*'00_PARAMETROS'!$B$12,2),0) -> 0 | R106: =IF(AND(G106="entrada",K106="PENDENTE"),ROUND(F106*'00_PARAMETROS'!$B$13,2),0) -> 0 | S106: =IF(P106+Q106>0,SUMIFS(SELIC!$B$4:$B$96,SELIC!$A$4:$A$96,">="&DATE(YEAR(B106),MONTH(B106)+1,1),SELIC!$A$4:$A$96,"<="&DATE(YEAR('00_PARAMETROS'!$B$4),MONTH('00_PARAMETROS'!$B$4)-1,1))+'00_PARAMETROS'!$B$11,0) -> 0 | T106: =IF(P106+Q106>0,MIN('00_PARAMETROS'!$B$9,'00_PARAMETROS'!$B$8*MAX(0,'00_PARAMETROS'!$B$4-B106)),0) -> 0 | U106: =ROUND(P106*(1+S106+T106),2) -> 0 | V106: =ROUND(Q106*(1+S106+T106),2) -> 0 | W106: =ROUND(R106*(1+S106+T106),2) -> 0 | X106: BLUE OCEAN 605
A107: 103 | B107: 45872 | C107: =YEAR(B107) -> 2025 | D107: Transferência enviada pelo Pix | Rofran Construtora Ltda - 51.819.924/0001-55 - | COOP SICREDI VALE LITORAL SC Agência: 2606 | Conta: 63110-5 | E107: ROFRAN CONSTRUTORA LTDA | F107: -25000 | G107: saida | H107: terceiros | I107: 08.pdf | J107: Pagamento — Loft 605 Blue Ocean (Rofran) | K107: SAIDA | L107: =IF(AND(G107="entrada",F107>='00_PARAMETROS'!$B$7),"SIM","NÃO") -> NÃO | N107: {=IFERROR(INDEX('00_PARAMETROS'!$B$41:$B$54,MATCH(K107,'00_PARAMETROS'!$A$41:$A$54,0)),0)} -> 0 | O107: =IF(OR(G107<>"entrada",N107=0),0,IF(K107="VENDA_BEM_BR_GCAP",N(M107),F107)) -> 0 | P107: =ROUND(O107*N107,2) -> 0 | Q107: =IF(AND(G107="entrada",K107="PENDENTE"),ROUND(F107*'00_PARAMETROS'!$B$12,2),0) -> 0 | R107: =IF(AND(G107="entrada",K107="PENDENTE"),ROUND(F107*'00_PARAMETROS'!$B$13,2),0) -> 0 | S107: =IF(P107+Q107>0,SUMIFS(SELIC!$B$4:$B$96,SELIC!$A$4:$A$96,">="&DATE(YEAR(B107),MONTH(B107)+1,1),SELIC!$A$4:$A$96,"<="&DATE(YEAR('00_PARAMETROS'!$B$4),MONTH('00_PARAMETROS'!$B$4)-1,1))+'00_PARAMETROS'!$B$11,0) -> 0 | T107: =IF(P107+Q107>0,MIN('00_PARAMETROS'!$B$9,'00_PARAMETROS'!$B$8*MAX(0,'00_PARAMETROS'!$B$4-B107)),0) -> 0 | U107: =ROUND(P107*(1+S107+T107),2) -> 0 | V107: =ROUND(Q107*(1+S107+T107),2) -> 0 | W107: =ROUND(R107*(1+S107+T107),2) -> 0 | X107: BLUE OCEAN 605
A108: 104 | B108: 45873 | C108: =YEAR(B108) -> 2025 | D108: Transferência Recebida | Marcia Novais de Melo Barros - •••.515.229-•• - NU | PAGAMENTOS - IP (0260) Agência: 1 Conta: | 368339173-1 | E108: MARCIA NOVAIS DE MELO BARROS | F108: 40000 | G108: entrada | H108: conta_conjuge | I108: 08.pdf | J108: [HIPÓTESE] Transferência da cônjuge — não é renda; comprovar a origem dos recursos dela | K108: TRANSF_CONJUGE | L108: =IF(AND(G108="entrada",F108>='00_PARAMETROS'!$B$7),"SIM","NÃO") -> SIM | N108: {=IFERROR(INDEX('00_PARAMETROS'!$B$41:$B$54,MATCH(K108,'00_PARAMETROS'!$A$41:$A$54,0)),0)} -> 0 | O108: =IF(OR(G108<>"entrada",N108=0),0,IF(K108="VENDA_BEM_BR_GCAP",N(M108),F108)) -> 0 | P108: =ROUND(O108*N108,2) -> 0 | Q108: =IF(AND(G108="entrada",K108="PENDENTE"),ROUND(F108*'00_PARAMETROS'!$B$12,2),0) -> 0 | R108: =IF(AND(G108="entrada",K108="PENDENTE"),ROUND(F108*'00_PARAMETROS'!$B$13,2),0) -> 0 | S108: =IF(P108+Q108>0,SUMIFS(SELIC!$B$4:$B$96,SELIC!$A$4:$A$96,">="&DATE(YEAR(B108),MONTH(B108)+1,1),SELIC!$A$4:$A$96,"<="&DATE(YEAR('00_PARAMETROS'!$B$4),MONTH('00_PARAMETROS'!$B$4)-1,1))+'00_PARAMETROS'!$B$11,0) -> 0 | T108: =IF(P108+Q108>0,MIN('00_PARAMETROS'!$B$9,'00_PARAMETROS'!$B$8*MAX(0,'00_PARAMETROS'!$B$4-B108)),0) -> 0 | U108: =ROUND(P108*(1+S108+T108),2) -> 0 | V108: =ROUND(Q108*(1+S108+T108),2) -> 0 | W108: =ROUND(R108*(1+S108+T108),2) -> 0
A109: 105 | B109: 45873 | C109: =YEAR(B109) -> 2025 | D109: Transferência recebida pelo Pix | WERSAN COMERCIO DE COMBUSTIVEIS LTDA - | 17.625.257/0001-31 - BCO SANTANDER (BRASIL) S. | A. (0033) Agência: 4278 Conta: 13001807-7 | E109: WERSAN COMERCIO DE COMBUSTIVEIS LTDA | F109: 20000 | G109: entrada | H109: terceiros | I109: 08.pdf | J109: PENDENTE — DOCUMENTO NECESSÁRIO: natureza não comprovada (contrato, recibo, escritura, comprovante) | K109: PENDENTE | L109: =IF(AND(G109="entrada",F109>='00_PARAMETROS'!$B$7),"SIM","NÃO") -> SIM | N109: {=IFERROR(INDEX('00_PARAMETROS'!$B$41:$B$54,MATCH(K109,'00_PARAMETROS'!$A$41:$A$54,0)),0)} -> 0 | O109: =IF(OR(G109<>"entrada",N109=0),0,IF(K109="VENDA_BEM_BR_GCAP",N(M109),F109)) -> 0 | P109: =ROUND(O109*N109,2) -> 0 | Q109: =IF(AND(G109="entrada",K109="PENDENTE"),ROUND(F109*'00_PARAMETROS'!$B$12,2),0) -> 3000 | R109: =IF(AND(G109="entrada",K109="PENDENTE"),ROUND(F109*'00_PARAMETROS'!$B$13,2),0) -> 5000 | S109: =IF(P109+Q109>0,SUMIFS(SELIC!$B$4:$B$96,SELIC!$A$4:$A$96,">="&DATE(YEAR(B109),MONTH(B109)+1,1),SELIC!$A$4:$A$96,"<="&DATE(YEAR('00_PARAMETROS'!$B$4),MONTH('00_PARAMETROS'!$B$4)-1,1))+'00_PARAMETROS'!$B$11,0) -> 0.1473 | T109: =IF(P109+Q109>0,MIN('00_PARAMETROS'!$B$9,'00_PARAMETROS'!$B$8*MAX(0,'00_PARAMETROS'!$B$4-B109)),0) -> 0.2 | U109: =ROUND(P109*(1+S109+T109),2) -> 0 | V109: =ROUND(Q109*(1+S109+T109),2) -> 4041.9 | W109: =ROUND(R109*(1+S109+T109),2) -> 6736.5
A110: 106 | B110: 45873 | C110: =YEAR(B110) -> 2025 | D110: Transferência enviada pelo Pix | Rofran Construtora Ltda - 51.819.924/0001-55 - | COOP SICREDI VALE LITORAL SC Agência: 2606 | Conta: 63110-5 | E110: ROFRAN CONSTRUTORA LTDA | F110: -20000 | G110: saida | H110: terceiros | I110: 08.pdf | J110: Pagamento — Loft 605 Blue Ocean (Rofran) | K110: SAIDA | L110: =IF(AND(G110="entrada",F110>='00_PARAMETROS'!$B$7),"SIM","NÃO") -> NÃO | N110: {=IFERROR(INDEX('00_PARAMETROS'!$B$41:$B$54,MATCH(K110,'00_PARAMETROS'!$A$41:$A$54,0)),0)} -> 0 | O110: =IF(OR(G110<>"entrada",N110=0),0,IF(K110="VENDA_BEM_BR_GCAP",N(M110),F110)) -> 0 | P110: =ROUND(O110*N110,2) -> 0 | Q110: =IF(AND(G110="entrada",K110="PENDENTE"),ROUND(F110*'00_PARAMETROS'!$B$12,2),0) -> 0 | R110: =IF(AND(G110="entrada",K110="PENDENTE"),ROUND(F110*'00_PARAMETROS'!$B$13,2),0) -> 0 | S110: =IF(P110+Q110>0,SUMIFS(SELIC!$B$4:$B$96,SELIC!$A$4:$A$96,">="&DATE(YEAR(B110),MONTH(B110)+1,1),SELIC!$A$4:$A$96,"<="&DATE(YEAR('00_PARAMETROS'!$B$4),MONTH('00_PARAMETROS'!$B$4)-1,1))+'00_PARAMETROS'!$B$11,0) -> 0 | T110: =IF(P110+Q110>0,MIN('00_PARAMETROS'!$B$9,'00_PARAMETROS'!$B$8*MAX(0,'00_PARAMETROS'!$B$4-B110)),0) -> 0 | U110: =ROUND(P110*(1+S110+T110),2) -> 0 | V110: =ROUND(Q110*(1+S110+T110),2) -> 0 | W110: =ROUND(R110*(1+S110+T110),2) -> 0 | X110: BLUE OCEAN 605
A111: 107 | B111: 45873 | C111: =YEAR(B111) -> 2025 | D111: Transferência enviada pelo Pix | Rofran Construtora Ltda - 51.819.924/0001-55 - | COOP SICREDI VALE LITORAL SC Agência: 2606 | Conta: 63110-5 | E111: ROFRAN CONSTRUTORA LTDA | F111: -30000 | G111: saida | H111: terceiros | I111: 08.pdf | J111: Pagamento — Loft 605 Blue Ocean (Rofran) | K111: SAIDA | L111: =IF(AND(G111="entrada",F111>='00_PARAMETROS'!$B$7),"SIM","NÃO") -> NÃO | N111: {=IFERROR(INDEX('00_PARAMETROS'!$B$41:$B$54,MATCH(K111,'00_PARAMETROS'!$A$41:$A$54,0)),0)} -> 0 | O111: =IF(OR(G111<>"entrada",N111=0),0,IF(K111="VENDA_BEM_BR_GCAP",N(M111),F111)) -> 0 | P111: =ROUND(O111*N111,2) -> 0 | Q111: =IF(AND(G111="entrada",K111="PENDENTE"),ROUND(F111*'00_PARAMETROS'!$B$12,2),0) -> 0 | R111: =IF(AND(G111="entrada",K111="PENDENTE"),ROUND(F111*'00_PARAMETROS'!$B$13,2),0) -> 0 | S111: =IF(P111+Q111>0,SUMIFS(SELIC!$B$4:$B$96,SELIC!$A$4:$A$96,">="&DATE(YEAR(B111),MONTH(B111)+1,1),SELIC!$A$4:$A$96,"<="&DATE(YEAR('00_PARAMETROS'!$B$4),MONTH('00_PARAMETROS'!$B$4)-1,1))+'00_PARAMETROS'!$B$11,0) -> 0 | T111: =IF(P111+Q111>0,MIN('00_PARAMETROS'!$B$9,'00_PARAMETROS'!$B$8*MAX(0,'00_PARAMETROS'!$B$4-B111)),0) -> 0 | U111: =ROUND(P111*(1+S111+T111),2) -> 0 | V111: =ROUND(Q111*(1+S111+T111),2) -> 0 | W111: =ROUND(R111*(1+S111+T111),2) -> 0 | X111: BLUE OCEAN 605
A112: 108 | B112: 45874 | C112: =YEAR(B112) -> 2025 | D112: Transferência Recebida | Rodrigo de Oliveira Machado - •••.248.649-•• - NU | 89083502-4 | PAGAMENTOS - IP (0260) Agência: 1 Conta: | 79449194-5 | E112: RODRIGO DE OLIVEIRA MACHADO | F112: 34000 | G112: entrada | H112: terceiros | I112: 08.pdf | J112: PENDENTE — DOCUMENTO NECESSÁRIO: natureza não comprovada (contrato, recibo, escritura, comprovante) | K112: PENDENTE | L112: =IF(AND(G112="entrada",F112>='00_PARAMETROS'!$B$7),"SIM","NÃO") -> SIM | N112: {=IFERROR(INDEX('00_PARAMETROS'!$B$41:$B$54,MATCH(K112,'00_PARAMETROS'!$A$41:$A$54,0)),0)} -> 0 | O112: =IF(OR(G112<>"entrada",N112=0),0,IF(K112="VENDA_BEM_BR_GCAP",N(M112),F112)) -> 0 | P112: =ROUND(O112*N112,2) -> 0 | Q112: =IF(AND(G112="entrada",K112="PENDENTE"),ROUND(F112*'00_PARAMETROS'!$B$12,2),0) -> 5100 | R112: =IF(AND(G112="entrada",K112="PENDENTE"),ROUND(F112*'00_PARAMETROS'!$B$13,2),0) -> 8500 | S112: =IF(P112+Q112>0,SUMIFS(SELIC!$B$4:$B$96,SELIC!$A$4:$A$96,">="&DATE(YEAR(B112),MONTH(B112)+1,1),SELIC!$A$4:$A$96,"<="&DATE(YEAR('00_PARAMETROS'!$B$4),MONTH('00_PARAMETROS'!$B$4)-1,1))+'00_PARAMETROS'!$B$11,0) -> 0.1473 | T112: =IF(P112+Q112>0,MIN('00_PARAMETROS'!$B$9,'00_PARAMETROS'!$B$8*MAX(0,'00_PARAMETROS'!$B$4-B112)),0) -> 0.2 | U112: =ROUND(P112*(1+S112+T112),2) -> 0 | V112: =ROUND(Q112*(1+S112+T112),2) -> 6871.23 | W112: =ROUND(R112*(1+S112+T112),2) -> 11452.05
A113: 109 | B113: 45874 | C113: =YEAR(B113) -> 2025 | D113: Transferência recebida pelo Pix | RODRIGO DE OLIVEIRA MACHADO - •••.248.649-•• - | BCO BRADESCO S.A. (0237) Agência: 382 Conta: | 1003890-1 | E113: RODRIGO DE OLIVEIRA MACHADO | F113: 10000 | G113: entrada | H113: terceiros | I113: 08.pdf | J113: PENDENTE — DOCUMENTO NECESSÁRIO: natureza não comprovada (contrato, recibo, escritura, comprovante) | K113: PENDENTE | L113: =IF(AND(G113="entrada",F113>='00_PARAMETROS'!$B$7),"SIM","NÃO") -> SIM | N113: {=IFERROR(INDEX('00_PARAMETROS'!$B$41:$B$54,MATCH(K113,'00_PARAMETROS'!$A$41:$A$54,0)),0)} -> 0 | O113: =IF(OR(G113<>"entrada",N113=0),0,IF(K113="VENDA_BEM_BR_GCAP",N(M113),F113)) -> 0 | P113: =ROUND(O113*N113,2) -> 0 | Q113: =IF(AND(G113="entrada",K113="PENDENTE"),ROUND(F113*'00_PARAMETROS'!$B$12,2),0) -> 1500 | R113: =IF(AND(G113="entrada",K113="PENDENTE"),ROUND(F113*'00_PARAMETROS'!$B$13,2),0) -> 2500 | S113: =IF(P113+Q113>0,SUMIFS(SELIC!$B$4:$B$96,SELIC!$A$4:$A$96,">="&DATE(YEAR(B113),MONTH(B113)+1,1),SELIC!$A$4:$A$96,"<="&DATE(YEAR('00_PARAMETROS'!$B$4),MONTH('00_PARAMETROS'!$B$4)-1,1))+'00_PARAMETROS'!$B$11,0) -> 0.1473 | T113: =IF(P113+Q113>0,MIN('00_PARAMETROS'!$B$9,'00_PARAMETROS'!$B$8*MAX(0,'00_PARAMETROS'!$B$4-B113)),0) -> 0.2 | U113: =ROUND(P113*(1+S113+T113),2) -> 0 | V113: =ROUND(Q113*(1+S113+T113),2) -> 2020.95 | W113: =ROUND(R113*(1+S113+T113),2) -> 3368.25
A114: 110 | B114: 45874 | C114: =YEAR(B114) -> 2025 | D114: Transferência recebida pelo Pix | ANDRE WERNER - •••.744.728-•• - ITAÚ UNIBANCO S. | A. (0341) Agência: 7012 Conta: 2282-3 | E114: ANDRE WERNER | F114: 45000 | G114: entrada | H114: terceiros | I114: 08.pdf | J114: PENDENTE — DOCUMENTO NECESSÁRIO: natureza não comprovada (contrato, recibo, escritura, comprovante) | K114: PENDENTE | L114: =IF(AND(G114="entrada",F114>='00_PARAMETROS'!$B$7),"SIM","NÃO") -> SIM | N114: {=IFERROR(INDEX('00_PARAMETROS'!$B$41:$B$54,MATCH(K114,'00_PARAMETROS'!$A$41:$A$54,0)),0)} -> 0 | O114: =IF(OR(G114<>"entrada",N114=0),0,IF(K114="VENDA_BEM_BR_GCAP",N(M114),F114)) -> 0 | P114: =ROUND(O114*N114,2) -> 0 | Q114: =IF(AND(G114="entrada",K114="PENDENTE"),ROUND(F114*'00_PARAMETROS'!$B$12,2),0) -> 6750 | R114: =IF(AND(G114="entrada",K114="PENDENTE"),ROUND(F114*'00_PARAMETROS'!$B$13,2),0) -> 11250 | S114: =IF(P114+Q114>0,SUMIFS(SELIC!$B$4:$B$96,SELIC!$A$4:$A$96,">="&DATE(YEAR(B114),MONTH(B114)+1,1),SELIC!$A$4:$A$96,"<="&DATE(YEAR('00_PARAMETROS'!$B$4),MONTH('00_PARAMETROS'!$B$4)-1,1))+'00_PARAMETROS'!$B$11,0) -> 0.1473 | T114: =IF(P114+Q114>0,MIN('00_PARAMETROS'!$B$9,'00_PARAMETROS'!$B$8*MAX(0,'00_PARAMETROS'!$B$4-B114)),0) -> 0.2 | U114: =ROUND(P114*(1+S114+T114),2) -> 0 | V114: =ROUND(Q114*(1+S114+T114),2) -> 9094.28 | W114: =ROUND(R114*(1+S114+T114),2) -> 15157.13
A115: 111 | B115: 45874 | C115: =YEAR(B115) -> 2025 | D115: Transferência enviada pelo Pix | DIEGO NOVAIS DE MELO FONSECA - •••.183.549-•• | - COOP SICREDI VALE DO PIQUIRI Agência: 726 | Conta: 46120-6 | E115: DIEGO NOVAIS DE MELO FONSECA | F115: -230 | G115: saida | H115: terceiros | I115: 08.pdf | J115: Débito — não é rendimento | K115: SAIDA | L115: =IF(AND(G115="entrada",F115>='00_PARAMETROS'!$B$7),"SIM","NÃO") -> NÃO | N115: {=IFERROR(INDEX('00_PARAMETROS'!$B$41:$B$54,MATCH(K115,'00_PARAMETROS'!$A$41:$A$54,0)),0)} -> 0 | O115: =IF(OR(G115<>"entrada",N115=0),0,IF(K115="VENDA_BEM_BR_GCAP",N(M115),F115)) -> 0 | P115: =ROUND(O115*N115,2) -> 0 | Q115: =IF(AND(G115="entrada",K115="PENDENTE"),ROUND(F115*'00_PARAMETROS'!$B$12,2),0) -> 0 | R115: =IF(AND(G115="entrada",K115="PENDENTE"),ROUND(F115*'00_PARAMETROS'!$B$13,2),0) -> 0 | S115: =IF(P115+Q115>0,SUMIFS(SELIC!$B$4:$B$96,SELIC!$A$4:$A$96,">="&DATE(YEAR(B115),MONTH(B115)+1,1),SELIC!$A$4:$A$96,"<="&DATE(YEAR('00_PARAMETROS'!$B$4),MONTH('00_PARAMETROS'!$B$4)-1,1))+'00_PARAMETROS'!$B$11,0) -> 0 | T115: =IF(P115+Q115>0,MIN('00_PARAMETROS'!$B$9,'00_PARAMETROS'!$B$8*MAX(0,'00_PARAMETROS'!$B$4-B115)),0) -> 0 | U115: =ROUND(P115*(1+S115+T115),2) -> 0 | V115: =ROUND(Q115*(1+S115+T115),2) -> 0 | W115: =ROUND(R115*(1+S115+T115),2) -> 0
A116: 112 | B116: 45874 | C116: =YEAR(B116) -> 2025 | D116: Transferência enviada pelo Pix | ROFRAN CONSTRUTORA LTDA - 51.819.924/0001- | 55 - COOP SICREDI VALE LITORAL SC Agência: | 2606 Conta: 63110-5 | E116: ROFRAN CONSTRUTORA LTDA | F116: -30000 | G116: saida | H116: terceiros | I116: 08.pdf | J116: Pagamento — Loft 605 Blue Ocean (Rofran) | K116: SAIDA | L116: =IF(AND(G116="entrada",F116>='00_PARAMETROS'!$B$7),"SIM","NÃO") -> NÃO | N116: {=IFERROR(INDEX('00_PARAMETROS'!$B$41:$B$54,MATCH(K116,'00_PARAMETROS'!$A$41:$A$54,0)),0)} -> 0 | O116: =IF(OR(G116<>"entrada",N116=0),0,IF(K116="VENDA_BEM_BR_GCAP",N(M116),F116)) -> 0 | P116: =ROUND(O116*N116,2) -> 0 | Q116: =IF(AND(G116="entrada",K116="PENDENTE"),ROUND(F116*'00_PARAMETROS'!$B$12,2),0) -> 0 | R116: =IF(AND(G116="entrada",K116="PENDENTE"),ROUND(F116*'00_PARAMETROS'!$B$13,2),0) -> 0 | S116: =IF(P116+Q116>0,SUMIFS(SELIC!$B$4:$B$96,SELIC!$A$4:$A$96,">="&DATE(YEAR(B116),MONTH(B116)+1,1),SELIC!$A$4:$A$96,"<="&DATE(YEAR('00_PARAMETROS'!$B$4),MONTH('00_PARAMETROS'!$B$4)-1,1))+'00_PARAMETROS'!$B$11,0) -> 0 | T116: =IF(P116+Q116>0,MIN('00_PARAMETROS'!$B$9,'00_PARAMETROS'!$B$8*MAX(0,'00_PARAMETROS'!$B$4-B116)),0) -> 0 | U116: =ROUND(P116*(1+S116+T116),2) -> 0 | V116: =ROUND(Q116*(1+S116+T116),2) -> 0 | W116: =ROUND(R116*(1+S116+T116),2) -> 0 | X116: BLUE OCEAN 605
A117: 113 | B117: 45874 | C117: =YEAR(B117) -> 2025 | D117: Transferência enviada pelo Pix | ROFRAN CONSTRUTORA LTDA - 51.819.924/0001- | 55 - COOP SICREDI VALE LITORAL SC Agência: | 2606 Conta: 63110-5 | E117: ROFRAN CONSTRUTORA LTDA | F117: -20000 | G117: saida | H117: terceiros | I117: 08.pdf | J117: Pagamento — Loft 605 Blue Ocean (Rofran) | K117: SAIDA | L117: =IF(AND(G117="entrada",F117>='00_PARAMETROS'!$B$7),"SIM","NÃO") -> NÃO | N117: {=IFERROR(INDEX('00_PARAMETROS'!$B$41:$B$54,MATCH(K117,'00_PARAMETROS'!$A$41:$A$54,0)),0)} -> 0 | O117: =IF(OR(G117<>"entrada",N117=0),0,IF(K117="VENDA_BEM_BR_GCAP",N(M117),F117)) -> 0 | P117: =ROUND(O117*N117,2) -> 0 | Q117: =IF(AND(G117="entrada",K117="PENDENTE"),ROUND(F117*'00_PARAMETROS'!$B$12,2),0) -> 0 | R117: =IF(AND(G117="entrada",K117="PENDENTE"),ROUND(F117*'00_PARAMETROS'!$B$13,2),0) -> 0 | S117: =IF(P117+Q117>0,SUMIFS(SELIC!$B$4:$B$96,SELIC!$A$4:$A$96,">="&DATE(YEAR(B117),MONTH(B117)+1,1),SELIC!$A$4:$A$96,"<="&DATE(YEAR('00_PARAMETROS'!$B$4),MONTH('00_PARAMETROS'!$B$4)-1,1))+'00_PARAMETROS'!$B$11,0) -> 0 | T117: =IF(P117+Q117>0,MIN('00_PARAMETROS'!$B$9,'00_PARAMETROS'!$B$8*MAX(0,'00_PARAMETROS'!$B$4-B117)),0) -> 0 | U117: =ROUND(P117*(1+S117+T117),2) -> 0 | V117: =ROUND(Q117*(1+S117+T117),2) -> 0 | W117: =ROUND(R117*(1+S117+T117),2) -> 0 | X117: BLUE OCEAN 605
A118: 114 | B118: 45875 | C118: =YEAR(B118) -> 2025 | D118: Transferência enviada pelo Pix | ROFRAN CONSTRUTORA LTDA - 51.819.924/0001- | 55 - COOP SICREDI VALE LITORAL SC Agência: | 2606 Conta: 63110-5 | E118: ROFRAN CONSTRUTORA LTDA | F118: -49000 | G118: saida | H118: terceiros | I118: 08.pdf | J118: Pagamento — Loft 605 Blue Ocean (Rofran) | K118: SAIDA | L118: =IF(AND(G118="entrada",F118>='00_PARAMETROS'!$B$7),"SIM","NÃO") -> NÃO | N118: {=IFERROR(INDEX('00_PARAMETROS'!$B$41:$B$54,MATCH(K118,'00_PARAMETROS'!$A$41:$A$54,0)),0)} -> 0 | O118: =IF(OR(G118<>"entrada",N118=0),0,IF(K118="VENDA_BEM_BR_GCAP",N(M118),F118)) -> 0 | P118: =ROUND(O118*N118,2) -> 0 | Q118: =IF(AND(G118="entrada",K118="PENDENTE"),ROUND(F118*'00_PARAMETROS'!$B$12,2),0) -> 0 | R118: =IF(AND(G118="entrada",K118="PENDENTE"),ROUND(F118*'00_PARAMETROS'!$B$13,2),0) -> 0 | S118: =IF(P118+Q118>0,SUMIFS(SELIC!$B$4:$B$96,SELIC!$A$4:$A$96,">="&DATE(YEAR(B118),MONTH(B118)+1,1),SELIC!$A$4:$A$96,"<="&DATE(YEAR('00_PARAMETROS'!$B$4),MONTH('00_PARAMETROS'!$B$4)-1,1))+'00_PARAMETROS'!$B$11,0) -> 0 | T118: =IF(P118+Q118>0,MIN('00_PARAMETROS'!$B$9,'00_PARAMETROS'!$B$8*MAX(0,'00_PARAMETROS'!$B$4-B118)),0) -> 0 | U118: =ROUND(P118*(1+S118+T118),2) -> 0 | V118: =ROUND(Q118*(1+S118+T118),2) -> 0 | W118: =ROUND(R118*(1+S118+T118),2) -> 0 | X118: BLUE OCEAN 605
A119: 115 | B119: 45876 | C119: =YEAR(B119) -> 2025 | D119: Transferência enviada pelo Pix | ROFRAN CONSTRUTORA LTDA - 51.819.924/0001- | 89083502-4 | 55 - COOP SICREDI VALE LITORAL SC Agência: | 2606 Conta: 63110-5 | E119: ROFRAN CONSTRUTORA LTDA | F119: -1000 | G119: saida | H119: terceiros | I119: 08.pdf | J119: Pagamento — Loft 605 Blue Ocean (Rofran) | K119: SAIDA | L119: =IF(AND(G119="entrada",F119>='00_PARAMETROS'!$B$7),"SIM","NÃO") -> NÃO | N119: {=IFERROR(INDEX('00_PARAMETROS'!$B$41:$B$54,MATCH(K119,'00_PARAMETROS'!$A$41:$A$54,0)),0)} -> 0 | O119: =IF(OR(G119<>"entrada",N119=0),0,IF(K119="VENDA_BEM_BR_GCAP",N(M119),F119)) -> 0 | P119: =ROUND(O119*N119,2) -> 0 | Q119: =IF(AND(G119="entrada",K119="PENDENTE"),ROUND(F119*'00_PARAMETROS'!$B$12,2),0) -> 0 | R119: =IF(AND(G119="entrada",K119="PENDENTE"),ROUND(F119*'00_PARAMETROS'!$B$13,2),0) -> 0 | S119: =IF(P119+Q119>0,SUMIFS(SELIC!$B$4:$B$96,SELIC!$A$4:$A$96,">="&DATE(YEAR(B119),MONTH(B119)+1,1),SELIC!$A$4:$A$96,"<="&DATE(YEAR('00_PARAMETROS'!$B$4),MONTH('00_PARAMETROS'!$B$4)-1,1))+'00_PARAMETROS'!$B$11,0) -> 0 | T119: =IF(P119+Q119>0,MIN('00_PARAMETROS'!$B$9,'00_PARAMETROS'!$B$8*MAX(0,'00_PARAMETROS'!$B$4-B119)),0) -> 0 | U119: =ROUND(P119*(1+S119+T119),2) -> 0 | V119: =ROUND(Q119*(1+S119+T119),2) -> 0 | W119: =ROUND(R119*(1+S119+T119),2) -> 0 | X119: BLUE OCEAN 605
A120: 116 | B120: 45881 | C120: =YEAR(B120) -> 2025 | D120: Transferência enviada pelo Pix | PEDRO DONIZETE NERY - •••.731.896-•• - BCO | BRADESCO S.A. (0237) Agência: 1792 Conta: | 1000321-0 | E120: PEDRO DONIZETE NERY | F120: -6255 | G120: saida | H120: terceiros | I120: 08.pdf | J120: Débito — não é rendimento | K120: SAIDA | L120: =IF(AND(G120="entrada",F120>='00_PARAMETROS'!$B$7),"SIM","NÃO") -> NÃO | N120: {=IFERROR(INDEX('00_PARAMETROS'!$B$41:$B$54,MATCH(K120,'00_PARAMETROS'!$A$41:$A$54,0)),0)} -> 0 | O120: =IF(OR(G120<>"entrada",N120=0),0,IF(K120="VENDA_BEM_BR_GCAP",N(M120),F120)) -> 0 | P120: =ROUND(O120*N120,2) -> 0 | Q120: =IF(AND(G120="entrada",K120="PENDENTE"),ROUND(F120*'00_PARAMETROS'!$B$12,2),0) -> 0 | R120: =IF(AND(G120="entrada",K120="PENDENTE"),ROUND(F120*'00_PARAMETROS'!$B$13,2),0) -> 0 | S120: =IF(P120+Q120>0,SUMIFS(SELIC!$B$4:$B$96,SELIC!$A$4:$A$96,">="&DATE(YEAR(B120),MONTH(B120)+1,1),SELIC!$A$4:$A$96,"<="&DATE(YEAR('00_PARAMETROS'!$B$4),MONTH('00_PARAMETROS'!$B$4)-1,1))+'00_PARAMETROS'!$B$11,0) -> 0 | T120: =IF(P120+Q120>0,MIN('00_PARAMETROS'!$B$9,'00_PARAMETROS'!$B$8*MAX(0,'00_PARAMETROS'!$B$4-B120)),0) -> 0 | U120: =ROUND(P120*(1+S120+T120),2) -> 0 | V120: =ROUND(Q120*(1+S120+T120),2) -> 0 | W120: =ROUND(R120*(1+S120+T120),2) -> 0
A121: 117 | B121: 45882 | C121: =YEAR(B121) -> 2025 | D121: Transferência enviada pelo Pix | DIEGO NOVAIS DE MELO FONSECA - •••.183.549-•• | - COOP SICREDI VALE DO PIQUIRI Agência: 726 | Conta: 46120-6 | E121: DIEGO NOVAIS DE MELO FONSECA | F121: -3000 | G121: saida | H121: terceiros | I121: 08.pdf | J121: Débito — não é rendimento | K121: SAIDA | L121: =IF(AND(G121="entrada",F121>='00_PARAMETROS'!$B$7),"SIM","NÃO") -> NÃO | N121: {=IFERROR(INDEX('00_PARAMETROS'!$B$41:$B$54,MATCH(K121,'00_PARAMETROS'!$A$41:$A$54,0)),0)} -> 0 | O121: =IF(OR(G121<>"entrada",N121=0),0,IF(K121="VENDA_BEM_BR_GCAP",N(M121),F121)) -> 0 | P121: =ROUND(O121*N121,2) -> 0 | Q121: =IF(AND(G121="entrada",K121="PENDENTE"),ROUND(F121*'00_PARAMETROS'!$B$12,2),0) -> 0 | R121: =IF(AND(G121="entrada",K121="PENDENTE"),ROUND(F121*'00_PARAMETROS'!$B$13,2),0) -> 0 | S121: =IF(P121+Q121>0,SUMIFS(SELIC!$B$4:$B$96,SELIC!$A$4:$A$96,">="&DATE(YEAR(B121),MONTH(B121)+1,1),SELIC!$A$4:$A$96,"<="&DATE(YEAR('00_PARAMETROS'!$B$4),MONTH('00_PARAMETROS'!$B$4)-1,1))+'00_PARAMETROS'!$B$11,0) -> 0 | T121: =IF(P121+Q121>0,MIN('00_PARAMETROS'!$B$9,'00_PARAMETROS'!$B$8*MAX(0,'00_PARAMETROS'!$B$4-B121)),0) -> 0 | U121: =ROUND(P121*(1+S121+T121),2) -> 0 | V121: =ROUND(Q121*(1+S121+T121),2) -> 0 | W121: =ROUND(R121*(1+S121+T121),2) -> 0
A122: 118 | B122: 45883 | C122: =YEAR(B122) -> 2025 | D122: Aplicação RDB | E122: Aplicação RDB | F122: -4997 | G122: saida | H122: RDB | I122: 08.pdf | J122: Aplicação RDB (movimentação interna) | K122: SAIDA | L122: =IF(AND(G122="entrada",F122>='00_PARAMETROS'!$B$7),"SIM","NÃO") -> NÃO | N122: {=IFERROR(INDEX('00_PARAMETROS'!$B$41:$B$54,MATCH(K122,'00_PARAMETROS'!$A$41:$A$54,0)),0)} -> 0 | O122: =IF(OR(G122<>"entrada",N122=0),0,IF(K122="VENDA_BEM_BR_GCAP",N(M122),F122)) -> 0 | P122: =ROUND(O122*N122,2) -> 0 | Q122: =IF(AND(G122="entrada",K122="PENDENTE"),ROUND(F122*'00_PARAMETROS'!$B$12,2),0) -> 0 | R122: =IF(AND(G122="entrada",K122="PENDENTE"),ROUND(F122*'00_PARAMETROS'!$B$13,2),0) -> 0 | S122: =IF(P122+Q122>0,SUMIFS(SELIC!$B$4:$B$96,SELIC!$A$4:$A$96,">="&DATE(YEAR(B122),MONTH(B122)+1,1),SELIC!$A$4:$A$96,"<="&DATE(YEAR('00_PARAMETROS'!$B$4),MONTH('00_PARAMETROS'!$B$4)-1,1))+'00_PARAMETROS'!$B$11,0) -> 0 | T122: =IF(P122+Q122>0,MIN('00_PARAMETROS'!$B$9,'00_PARAMETROS'!$B$8*MAX(0,'00_PARAMETROS'!$B$4-B122)),0) -> 0 | U122: =ROUND(P122*(1+S122+T122),2) -> 0 | V122: =ROUND(Q122*(1+S122+T122),2) -> 0 | W122: =ROUND(R122*(1+S122+T122),2) -> 0
A123: 119 | B123: 45886 | C123: =YEAR(B123) -> 2025 | D123: Transferência enviada pelo Pix | Sandro de Araujo Marra - •••.482.608-•• - WISE | BRASIL IP LTDA. Agência: 1 Conta: 114032-0 | E123: SANDRO DE ARAUJO MARRA | F123: -1500 | G123: saida | H123: terceiros | I123: 08.pdf | J123: Débito — não é rendimento | K123: SAIDA | L123: =IF(AND(G123="entrada",F123>='00_PARAMETROS'!$B$7),"SIM","NÃO") -> NÃO | N123: {=IFERROR(INDEX('00_PARAMETROS'!$B$41:$B$54,MATCH(K123,'00_PARAMETROS'!$A$41:$A$54,0)),0)} -> 0 | O123: =IF(OR(G123<>"entrada",N123=0),0,IF(K123="VENDA_BEM_BR_GCAP",N(M123),F123)) -> 0 | P123: =ROUND(O123*N123,2) -> 0 | Q123: =IF(AND(G123="entrada",K123="PENDENTE"),ROUND(F123*'00_PARAMETROS'!$B$12,2),0) -> 0 | R123: =IF(AND(G123="entrada",K123="PENDENTE"),ROUND(F123*'00_PARAMETROS'!$B$13,2),0) -> 0 | S123: =IF(P123+Q123>0,SUMIFS(SELIC!$B$4:$B$96,SELIC!$A$4:$A$96,">="&DATE(YEAR(B123),MONTH(B123)+1,1),SELIC!$A$4:$A$96,"<="&DATE(YEAR('00_PARAMETROS'!$B$4),MONTH('00_PARAMETROS'!$B$4)-1,1))+'00_PARAMETROS'!$B$11,0) -> 0 | T123: =IF(P123+Q123>0,MIN('00_PARAMETROS'!$B$9,'00_PARAMETROS'!$B$8*MAX(0,'00_PARAMETROS'!$B$4-B123)),0) -> 0 | U123: =ROUND(P123*(1+S123+T123),2) -> 0 | V123: =ROUND(Q123*(1+S123+T123),2) -> 0 | W123: =ROUND(R123*(1+S123+T123),2) -> 0
A124: 120 | B124: 45900 | C124: =YEAR(B124) -> 2025 | D124: Transferência enviada pelo Pix | OMNI NEGOCIOS DIGITAIS - 31.311.204/0001-77 - | BANCO INTER (0077) Agência: 1 Conta: 28521262-1 | 89083502-4 | E124: OMNI NEGOCIOS DIGITAIS | F124: -375 | G124: saida | H124: terceiros | I124: 08.pdf | J124: Débito — não é rendimento | K124: SAIDA | L124: =IF(AND(G124="entrada",F124>='00_PARAMETROS'!$B$7),"SIM","NÃO") -> NÃO | N124: {=IFERROR(INDEX('00_PARAMETROS'!$B$41:$B$54,MATCH(K124,'00_PARAMETROS'!$A$41:$A$54,0)),0)} -> 0 | O124: =IF(OR(G124<>"entrada",N124=0),0,IF(K124="VENDA_BEM_BR_GCAP",N(M124),F124)) -> 0 | P124: =ROUND(O124*N124,2) -> 0 | Q124: =IF(AND(G124="entrada",K124="PENDENTE"),ROUND(F124*'00_PARAMETROS'!$B$12,2),0) -> 0 | R124: =IF(AND(G124="entrada",K124="PENDENTE"),ROUND(F124*'00_PARAMETROS'!$B$13,2),0) -> 0 | S124: =IF(P124+Q124>0,SUMIFS(SELIC!$B$4:$B$96,SELIC!$A$4:$A$96,">="&DATE(YEAR(B124),MONTH(B124)+1,1),SELIC!$A$4:$A$96,"<="&DATE(YEAR('00_PARAMETROS'!$B$4),MONTH('00_PARAMETROS'!$B$4)-1,1))+'00_PARAMETROS'!$B$11,0) -> 0 | T124: =IF(P124+Q124>0,MIN('00_PARAMETROS'!$B$9,'00_PARAMETROS'!$B$8*MAX(0,'00_PARAMETROS'!$B$4-B124)),0) -> 0 | U124: =ROUND(P124*(1+S124+T124),2) -> 0 | V124: =ROUND(Q124*(1+S124+T124),2) -> 0 | W124: =ROUND(R124*(1+S124+T124),2) -> 0
A125: 121 | B125: 45904 | C125: =YEAR(B125) -> 2025 | D125: Transferência enviada pelo Pix | CELSO GAMBORGI BRANCO - •••.033.529-•• - | COOP SICREDI VALE DO PIQUIRI Agência: 726 | Conta: 68715-1 | E125: CELSO GAMBORGI BRANCO | F125: -110 | G125: saida | H125: terceiros | I125: 09.pdf | J125: Débito — não é rendimento | K125: SAIDA | L125: =IF(AND(G125="entrada",F125>='00_PARAMETROS'!$B$7),"SIM","NÃO") -> NÃO | N125: {=IFERROR(INDEX('00_PARAMETROS'!$B$41:$B$54,MATCH(K125,'00_PARAMETROS'!$A$41:$A$54,0)),0)} -> 0 | O125: =IF(OR(G125<>"entrada",N125=0),0,IF(K125="VENDA_BEM_BR_GCAP",N(M125),F125)) -> 0 | P125: =ROUND(O125*N125,2) -> 0 | Q125: =IF(AND(G125="entrada",K125="PENDENTE"),ROUND(F125*'00_PARAMETROS'!$B$12,2),0) -> 0 | R125: =IF(AND(G125="entrada",K125="PENDENTE"),ROUND(F125*'00_PARAMETROS'!$B$13,2),0) -> 0 | S125: =IF(P125+Q125>0,SUMIFS(SELIC!$B$4:$B$96,SELIC!$A$4:$A$96,">="&DATE(YEAR(B125),MONTH(B125)+1,1),SELIC!$A$4:$A$96,"<="&DATE(YEAR('00_PARAMETROS'!$B$4),MONTH('00_PARAMETROS'!$B$4)-1,1))+'00_PARAMETROS'!$B$11,0) -> 0 | T125: =IF(P125+Q125>0,MIN('00_PARAMETROS'!$B$9,'00_PARAMETROS'!$B$8*MAX(0,'00_PARAMETROS'!$B$4-B125)),0) -> 0 | U125: =ROUND(P125*(1+S125+T125),2) -> 0 | V125: =ROUND(Q125*(1+S125+T125),2) -> 0 | W125: =ROUND(R125*(1+S125+T125),2) -> 0
A126: 122 | B126: 45911 | C126: =YEAR(B126) -> 2025 | D126: Transferência recebida pelo Pix | BANCO DAYCOVAL - 62.232.889/0001-90 - BCO | DAYCOVAL S.A (0707) Agência: 1 Conta: 1306-6 | E126: BANCO DAYCOVAL | F126: 10408 | G126: entrada | H126: intermediario_remessa | I126: 09.pdf | J126: [HIPÓTESE] Remessa do exterior por instituição de câmbio — fonte estrangeira, fora do IRPF de não residente | K126: RECURSO_PROPRIO_EXTERIOR | L126: =IF(AND(G126="entrada",F126>='00_PARAMETROS'!$B$7),"SIM","NÃO") -> SIM | N126: {=IFERROR(INDEX('00_PARAMETROS'!$B$41:$B$54,MATCH(K126,'00_PARAMETROS'!$A$41:$A$54,0)),0)} -> 0 | O126: =IF(OR(G126<>"entrada",N126=0),0,IF(K126="VENDA_BEM_BR_GCAP",N(M126),F126)) -> 0 | P126: =ROUND(O126*N126,2) -> 0 | Q126: =IF(AND(G126="entrada",K126="PENDENTE"),ROUND(F126*'00_PARAMETROS'!$B$12,2),0) -> 0 | R126: =IF(AND(G126="entrada",K126="PENDENTE"),ROUND(F126*'00_PARAMETROS'!$B$13,2),0) -> 0 | S126: =IF(P126+Q126>0,SUMIFS(SELIC!$B$4:$B$96,SELIC!$A$4:$A$96,">="&DATE(YEAR(B126),MONTH(B126)+1,1),SELIC!$A$4:$A$96,"<="&DATE(YEAR('00_PARAMETROS'!$B$4),MONTH('00_PARAMETROS'!$B$4)-1,1))+'00_PARAMETROS'!$B$11,0) -> 0 | T126: =IF(P126+Q126>0,MIN('00_PARAMETROS'!$B$9,'00_PARAMETROS'!$B$8*MAX(0,'00_PARAMETROS'!$B$4-B126)),0) -> 0 | U126: =ROUND(P126*(1+S126+T126),2) -> 0 | V126: =ROUND(Q126*(1+S126+T126),2) -> 0 | W126: =ROUND(R126*(1+S126+T126),2) -> 0
A127: 123 | B127: 45911 | C127: =YEAR(B127) -> 2025 | D127: Transferência recebida pelo Pix | TAPTAP - 55.177.686/0001-82 - BCO BS2 S.A. | (0218) Agência: 1 Conta: 1163660-2 | E127: TAPTAP | F127: 10700 | G127: entrada | H127: intermediario_remessa | I127: 09.pdf | J127: [HIPÓTESE] Remessa do exterior por instituição de câmbio — fonte estrangeira, fora do IRPF de não residente | K127: RECURSO_PROPRIO_EXTERIOR | L127: =IF(AND(G127="entrada",F127>='00_PARAMETROS'!$B$7),"SIM","NÃO") -> SIM | N127: {=IFERROR(INDEX('00_PARAMETROS'!$B$41:$B$54,MATCH(K127,'00_PARAMETROS'!$A$41:$A$54,0)),0)} -> 0 | O127: =IF(OR(G127<>"entrada",N127=0),0,IF(K127="VENDA_BEM_BR_GCAP",N(M127),F127)) -> 0 | P127: =ROUND(O127*N127,2) -> 0 | Q127: =IF(AND(G127="entrada",K127="PENDENTE"),ROUND(F127*'00_PARAMETROS'!$B$12,2),0) -> 0 | R127: =IF(AND(G127="entrada",K127="PENDENTE"),ROUND(F127*'00_PARAMETROS'!$B$13,2),0) -> 0 | S127: =IF(P127+Q127>0,SUMIFS(SELIC!$B$4:$B$96,SELIC!$A$4:$A$96,">="&DATE(YEAR(B127),MONTH(B127)+1,1),SELIC!$A$4:$A$96,"<="&DATE(YEAR('00_PARAMETROS'!$B$4),MONTH('00_PARAMETROS'!$B$4)-1,1))+'00_PARAMETROS'!$B$11,0) -> 0 | T127: =IF(P127+Q127>0,MIN('00_PARAMETROS'!$B$9,'00_PARAMETROS'!$B$8*MAX(0,'00_PARAMETROS'!$B$4-B127)),0) -> 0 | U127: =ROUND(P127*(1+S127+T127),2) -> 0 | V127: =ROUND(Q127*(1+S127+T127),2) -> 0 | W127: =ROUND(R127*(1+S127+T127),2) -> 0
A128: 124 | B128: 45911 | C128: =YEAR(B128) -> 2025 | D128: Transferência recebida pelo Pix | Felipe De Melo Rodrigues - •••.464.288-•• - NEON | PAGAMENTOS S.A. IP (0536) Agência: 655 Conta: | 23278478-7 | 89083502-4 | E128: FELIPE DE MELO RODRIGUES | F128: 5210 | G128: entrada | H128: terceiros | I128: 09.pdf | J128: PENDENTE — DOCUMENTO NECESSÁRIO: natureza não comprovada (contrato, recibo, escritura, comprovante) | K128: PENDENTE | L128: =IF(AND(G128="entrada",F128>='00_PARAMETROS'!$B$7),"SIM","NÃO") -> NÃO | N128: {=IFERROR(INDEX('00_PARAMETROS'!$B$41:$B$54,MATCH(K128,'00_PARAMETROS'!$A$41:$A$54,0)),0)} -> 0 | O128: =IF(OR(G128<>"entrada",N128=0),0,IF(K128="VENDA_BEM_BR_GCAP",N(M128),F128)) -> 0 | P128: =ROUND(O128*N128,2) -> 0 | Q128: =IF(AND(G128="entrada",K128="PENDENTE"),ROUND(F128*'00_PARAMETROS'!$B$12,2),0) -> 781.5 | R128: =IF(AND(G128="entrada",K128="PENDENTE"),ROUND(F128*'00_PARAMETROS'!$B$13,2),0) -> 1302.5 | S128: =IF(P128+Q128>0,SUMIFS(SELIC!$B$4:$B$96,SELIC!$A$4:$A$96,">="&DATE(YEAR(B128),MONTH(B128)+1,1),SELIC!$A$4:$A$96,"<="&DATE(YEAR('00_PARAMETROS'!$B$4),MONTH('00_PARAMETROS'!$B$4)-1,1))+'00_PARAMETROS'!$B$11,0) -> 0.1351 | T128: =IF(P128+Q128>0,MIN('00_PARAMETROS'!$B$9,'00_PARAMETROS'!$B$8*MAX(0,'00_PARAMETROS'!$B$4-B128)),0) -> 0.2 | U128: =ROUND(P128*(1+S128+T128),2) -> 0 | V128: =ROUND(Q128*(1+S128+T128),2) -> 1043.38 | W128: =ROUND(R128*(1+S128+T128),2) -> 1738.97
A129: 125 | B129: 45911 | C129: =YEAR(B129) -> 2025 | D129: Resgate RDB | E129: Resgate RDB | F129: 2000 | G129: entrada | H129: RDB | I129: 09.pdf | J129: [FATO CONFIRMADO] Resgate RDB — movimentação interna | K129: RDB_MOVIMENTACAO | L129: =IF(AND(G129="entrada",F129>='00_PARAMETROS'!$B$7),"SIM","NÃO") -> NÃO | N129: {=IFERROR(INDEX('00_PARAMETROS'!$B$41:$B$54,MATCH(K129,'00_PARAMETROS'!$A$41:$A$54,0)),0)} -> 0 | O129: =IF(OR(G129<>"entrada",N129=0),0,IF(K129="VENDA_BEM_BR_GCAP",N(M129),F129)) -> 0 | P129: =ROUND(O129*N129,2) -> 0 | Q129: =IF(AND(G129="entrada",K129="PENDENTE"),ROUND(F129*'00_PARAMETROS'!$B$12,2),0) -> 0 | R129: =IF(AND(G129="entrada",K129="PENDENTE"),ROUND(F129*'00_PARAMETROS'!$B$13,2),0) -> 0 | S129: =IF(P129+Q129>0,SUMIFS(SELIC!$B$4:$B$96,SELIC!$A$4:$A$96,">="&DATE(YEAR(B129),MONTH(B129)+1,1),SELIC!$A$4:$A$96,"<="&DATE(YEAR('00_PARAMETROS'!$B$4),MONTH('00_PARAMETROS'!$B$4)-1,1))+'00_PARAMETROS'!$B$11,0) -> 0 | T129: =IF(P129+Q129>0,MIN('00_PARAMETROS'!$B$9,'00_PARAMETROS'!$B$8*MAX(0,'00_PARAMETROS'!$B$4-B129)),0) -> 0 | U129: =ROUND(P129*(1+S129+T129),2) -> 0 | V129: =ROUND(Q129*(1+S129+T129),2) -> 0 | W129: =ROUND(R129*(1+S129+T129),2) -> 0
A130: 126 | B130: 45911 | C130: =YEAR(B130) -> 2025 | D130: Transferência enviada pelo Pix | CELSO GAMBORGI BRANCO - •••.033.529-•• - | COOP SICREDI VALE DO PIQUIRI Agência: 726 | Conta: 68715-1 | E130: CELSO GAMBORGI BRANCO | F130: -31.92 | G130: saida | H130: terceiros | I130: 09.pdf | J130: Débito — não é rendimento | K130: SAIDA | L130: =IF(AND(G130="entrada",F130>='00_PARAMETROS'!$B$7),"SIM","NÃO") -> NÃO | N130: {=IFERROR(INDEX('00_PARAMETROS'!$B$41:$B$54,MATCH(K130,'00_PARAMETROS'!$A$41:$A$54,0)),0)} -> 0 | O130: =IF(OR(G130<>"entrada",N130=0),0,IF(K130="VENDA_BEM_BR_GCAP",N(M130),F130)) -> 0 | P130: =ROUND(O130*N130,2) -> 0 | Q130: =IF(AND(G130="entrada",K130="PENDENTE"),ROUND(F130*'00_PARAMETROS'!$B$12,2),0) -> 0 | R130: =IF(AND(G130="entrada",K130="PENDENTE"),ROUND(F130*'00_PARAMETROS'!$B$13,2),0) -> 0 | S130: =IF(P130+Q130>0,SUMIFS(SELIC!$B$4:$B$96,SELIC!$A$4:$A$96,">="&DATE(YEAR(B130),MONTH(B130)+1,1),SELIC!$A$4:$A$96,"<="&DATE(YEAR('00_PARAMETROS'!$B$4),MONTH('00_PARAMETROS'!$B$4)-1,1))+'00_PARAMETROS'!$B$11,0) -> 0 | T130: =IF(P130+Q130>0,MIN('00_PARAMETROS'!$B$9,'00_PARAMETROS'!$B$8*MAX(0,'00_PARAMETROS'!$B$4-B130)),0) -> 0 | U130: =ROUND(P130*(1+S130+T130),2) -> 0 | V130: =ROUND(Q130*(1+S130+T130),2) -> 0 | W130: =ROUND(R130*(1+S130+T130),2) -> 0
A131: 127 | B131: 45912 | C131: =YEAR(B131) -> 2025 | D131: Transferência recebida pelo Pix | BANCO DAYCOVAL - 62.232.889/0001-90 - BCO | DAYCOVAL S.A (0707) Agência: 1 Conta: 1306-6 | E131: BANCO DAYCOVAL | F131: 10344 | G131: entrada | H131: intermediario_remessa | I131: 09.pdf | J131: [HIPÓTESE] Remessa do exterior por instituição de câmbio — fonte estrangeira, fora do IRPF de não residente | K131: RECURSO_PROPRIO_EXTERIOR | L131: =IF(AND(G131="entrada",F131>='00_PARAMETROS'!$B$7),"SIM","NÃO") -> SIM | N131: {=IFERROR(INDEX('00_PARAMETROS'!$B$41:$B$54,MATCH(K131,'00_PARAMETROS'!$A$41:$A$54,0)),0)} -> 0 | O131: =IF(OR(G131<>"entrada",N131=0),0,IF(K131="VENDA_BEM_BR_GCAP",N(M131),F131)) -> 0 | P131: =ROUND(O131*N131,2) -> 0 | Q131: =IF(AND(G131="entrada",K131="PENDENTE"),ROUND(F131*'00_PARAMETROS'!$B$12,2),0) -> 0 | R131: =IF(AND(G131="entrada",K131="PENDENTE"),ROUND(F131*'00_PARAMETROS'!$B$13,2),0) -> 0 | S131: =IF(P131+Q131>0,SUMIFS(SELIC!$B$4:$B$96,SELIC!$A$4:$A$96,">="&DATE(YEAR(B131),MONTH(B131)+1,1),SELIC!$A$4:$A$96,"<="&DATE(YEAR('00_PARAMETROS'!$B$4),MONTH('00_PARAMETROS'!$B$4)-1,1))+'00_PARAMETROS'!$B$11,0) -> 0 | T131: =IF(P131+Q131>0,MIN('00_PARAMETROS'!$B$9,'00_PARAMETROS'!$B$8*MAX(0,'00_PARAMETROS'!$B$4-B131)),0) -> 0 | U131: =ROUND(P131*(1+S131+T131),2) -> 0 | V131: =ROUND(Q131*(1+S131+T131),2) -> 0 | W131: =ROUND(R131*(1+S131+T131),2) -> 0
... A168: 164 | B168: 46136 | C168: =YEAR(B168) -> 2026 | D168: Transferência enviada pelo Pix | Elizeu Goncalves Pereira (Transferência enviada) | E168: ELIZEU GONCALVES PEREIRA (TRANSFERÊNCIA ENVIADA) | F168: -400 | G168: saida | H168: terceiros | I168: NU_890835024_01ABR2026_30ABR2026.pdf | J168: Débito — não é rendimento | K168: SAIDA | L168: =IF(AND(G168="entrada",F168>='00_PARAMETROS'!$B$7),"SIM","NÃO") -> NÃO | N168: {=IFERROR(INDEX('00_PARAMETROS'!$B$41:$B$54,MATCH(K168,'00_PARAMETROS'!$A$41:$A$54,0)),0)} -> 0 | O168: =IF(OR(G168<>"entrada",N168=0),0,IF(K168="VENDA_BEM_BR_GCAP",N(M168),F168)) -> 0 | P168: =ROUND(O168*N168,2) -> 0 | Q168: =IF(AND(G168="entrada",K168="PENDENTE"),ROUND(F168*'00_PARAMETROS'!$B$12,2),0) -> 0 | R168: =IF(AND(G168="entrada",K168="PENDENTE"),ROUND(F168*'00_PARAMETROS'!$B$13,2),0) -> 0 | S168: =IF(P168+Q168>0,SUMIFS(SELIC!$B$4:$B$96,SELIC!$A$4:$A$96,">="&DATE(YEAR(B168),MONTH(B168)+1,1),SELIC!$A$4:$A$96,"<="&DATE(YEAR('00_PARAMETROS'!$B$4),MONTH('00_PARAMETROS'!$B$4)-1,1))+'00_PARAMETROS'!$B$11,0) -> 0 | T168: =IF(P168+Q168>0,MIN('00_PARAMETROS'!$B$9,'00_PARAMETROS'!$B$8*MAX(0,'00_PARAMETROS'!$B$4-B168)),0) -> 0 | U168: =ROUND(P168*(1+S168+T168),2) -> 0 | V168: =ROUND(Q168*(1+S168+T168),2) -> 0 | W168: =ROUND(R168*(1+S168+T168),2) -> 0
D170: TOTAIS | F170: =SUM(F5:F168) -> -70707.5 | P170: =SUM(P5:P168) -> 0 | Q170: =SUM(Q5:Q168) -> 93526.5 | R170: =SUM(R5:R168) -> 155877.5 | U170: =SUM(U5:U168) -> 0 | V170: =SUM(V5:V168) -> 129120.73 | W170: =SUM(W5:W168) -> 215201.21
D171: Entradas de terceiros com natureza PENDENTE | F171: =SUMIFS(F5:F168,G5:G168,"entrada",K5:K168,"PENDENTE") -> 623510
D172: Qtde. de entradas PENDENTES materiais (≥ materialidade) | F172: =COUNTIFS(G5:G168,"entrada",K5:K168,"PENDENTE",L5:L168,"SIM") -> 15

Sheet 05_US_TAXES
A1: 05 — RENDIMENTOS E TRIBUTOS NOS EUA POR ANO (valores em US$)
A2: José Adalmo Carvalho de Barros — CPF 069.351.996-70 | Resp. técnico: Robson Soares Bezerra — CRC/PR 062711/O
A3: Somente o imposto de renda FEDERAL é candidato a crédito no BR (reciprocidade — ADI SRF 28/2000). SE tax (previdência) e CT state tax: não creditáveis [INFERÊNCIA TÉCNICA — confirmar na fonte oficial].
A4: Ano | B4: Filing status | C4: Rendimento / formulário | D4: Receita bruta / wages | E4: Lucro líquido / K-1 | F4: AGI (1040 l.11) | G4: Federal income tax (após créditos) | H4: SE tax (previdência) | I4: Total federal tax | J4: Pagamentos / retenções | K4: Saldo devedor declarado | L4: CT state tax | M4: Fed tax elegível a crédito BR (US$) | N4: Fonte (linha do formulário) | O4: Status
A5: 2018 | B5: MFJ | C5: W-2 wages (empregado) | D5: 25628 | F5: 25628 | G5: 0 | H5: 0 | I5: =IF(AND(G5="",H5=""),"",N(G5)+N(H5)) -> 0 | K5: 0 | L5: 0 | M5: {=IF(INDEX('02_TAX_TIMELINE'!$B$5:$B$15,MATCH(A5,'02_TAX_TIMELINE'!$A$5:$A$15,0))="RESIDENTE",N(G5),0)} -> 0 | N5: 1040/2018 l.6 = 25.628; l.11 tax 164; l.12 CTC 164 → l.13 = 0; CT-1040 l.55 = 0 (OCR 2018_US_TAX.md) | O5: [FATO CONFIRMADO — OCR]
A6: 2019 | B6: HOH/MFJ (OCR ilegível) | C6: Schedule C (autônomo) | D6: 10000 | E6: 10000 | F6: 9293 | G6: 0 | H6: 1413 | I6: =IF(AND(G6="",H6=""),"",N(G6)+N(H6)) -> 1413 | J6: 1413 | K6: 0 | L6: 0 | M6: {=IF(INDEX('02_TAX_TIMELINE'!$B$5:$B$15,MATCH(A6,'02_TAX_TIMELINE'!$A$5:$A$15,0))="RESIDENTE",N(G6),0)} -> 0 | N6: 1040/2019 l.7b = 10.000; l.15 SE = 1.413; l.23 owed 1.413; CT AGI 9.293 (OCR 2019_US_TAX.md) | O6: [FATO CONFIRMADO — OCR]
A7: 2020 | B7: MFJ | C7: Schedule C (autônomo) | D7: 30152 | E7: 2252 | G7: 0 | H7: 318 | I7: =IF(AND(G7="",H7=""),"",N(G7)+N(H7)) -> 318 | J7: 318 | K7: 0 | M7: {=IF(INDEX('02_TAX_TIMELINE'!$B$5:$B$15,MATCH(A7,'02_TAX_TIMELINE'!$A$5:$A$15,0))="RESIDENTE",N(G7),0)} -> 0 | N7: Sch C l.1 = 30.152; Sch SE l.3 = 2.252; l.24 = 318 (OCR 2020_2021_US_TAX.md) | O7: [FATO CONFIRMADO — OCR]
A8: 2021 | B8: MFJ | C8: Schedule C (autônomo) | D8: 35335 | E8: 4870 | G8: 0 | H8: 686 | I8: =IF(AND(G8="",H8=""),"",N(G8)+N(H8)) -> 686 | K8: 0 | M8: {=IF(INDEX('02_TAX_TIMELINE'!$B$5:$B$15,MATCH(A8,'02_TAX_TIMELINE'!$A$5:$A$15,0))="RESIDENTE",N(G8),0)} -> 0 | N8: Fase 2 (OCR 2020_2021_US_TAX.md) | O8: [FATO CONFIRMADO — Fase 2]
A9: 2022 | B9: MFJ | C9: Schedule C (autônomo) | D9: 40550 | E9: 10823 | F9: 10058 | G9: 0 | H9: 1529 | I9: =IF(AND(G9="",H9=""),"",N(G9)+N(H9)) -> 1529 | K9: 0 | M9: {=IF(INDEX('02_TAX_TIMELINE'!$B$5:$B$15,MATCH(A9,'02_TAX_TIMELINE'!$A$5:$A$15,0))="RESIDENTE",N(G9),0)} -> 0 | N9: 1040/2022 l.8 = 10.823; l.11 = 10.058; l.15 taxable = 0 → income tax 0; l.23 SE = 1.529 (OCR 2022_US_TAX.md) | O9: [FATO CONFIRMADO — OCR] (laudo F6 dizia 'a confirmar')
A10: 2023 | B10: MFJ | C10: K-1 Two Brothers Drywall & Paint (EIN 37-2048597) | D10: 75383 | E10: 75383 | G10: =K10-H10 -> 4829 | H10: 10651 | I10: =IF(AND(G10="",H10=""),"",N(G10)+N(H10)) -> 15480 | K10: 15480 | M10: {=IF(INDEX('02_TAX_TIMELINE'!$B$5:$B$15,MATCH(A10,'02_TAX_TIMELINE'!$A$5:$A$15,0))="RESIDENTE",N(G10),0)} -> 0 | N10: Sch E l.32 = 75.383; SE = 10.651; l.37 owed = 15.480. Linhas 22/24 ilegíveis: fed income tax = 15.480 − 10.651 [INFERÊNCIA — pode conter multa l.38] | O10: [INFERÊNCIA TÉCNICA]
A11: 2024 | B11: MFJ (José + Márcia) | C11: Sch C (DeSouza Painting 1099: 10.670) + K-1 Two Brothers, UPE, Royal Flush Inv. & Constr. (EIN 92-3349147) | D11: 82153 | E11: 70671 | F11: 81341 | G11: 5039 | H11: 1623 | I11: =IF(AND(G11="",H11=""),"",N(G11)+N(H11)) -> 6662 | J11: 0 | K11: 6963 | M11: {=IF(INDEX('02_TAX_TIMELINE'!$B$5:$B$15,MATCH(A11,'02_TAX_TIMELINE'!$A$5:$A$15,0))="RESIDENTE",N(G11),0)} -> 0 | N11: 1040/2024 l.9 = 82.153; l.11 = 81.341; l.22 = 5.039; l.23 = 1.623; l.24 = 6.662; l.33 = 0; l.37 = 6.963 (inclui multa l.38 = 301). Sch C 11.482; Sch E 70.671 | O11: [FATO CONFIRMADO — PDF]; pagamento ao IRS NÃO comprovado
A12: 2025 | B12: PENDENTE | C12: PENDENTE — DOCUMENTO NECESSÁRIO (1040/2025) | I12: =IF(AND(G12="",H12=""),"",N(G12)+N(H12)) | M12: {=IF(INDEX('02_TAX_TIMELINE'!$B$5:$B$15,MATCH(A12,'02_TAX_TIMELINE'!$A$5:$A$15,0))="RESIDENTE",N(G12),0)} -> 0 | N12: Não localizado na pasta | O12: PENDENTE — DOCUMENTO NECESSÁRIO

Sheet 06_FOREIGN_TAX_CREDIT
A1: 06 — COMPENSAÇÃO DO IMPOSTO PAGO NOS EUA (somente anos de residência)
A2: José Adalmo Carvalho de Barros — CPF 069.351.996-70 | Resp. técnico: Robson Soares Bezerra — CRC/PR 062711/O
A4: AC 2018 — item | B4: Valor | C4: Fonte / regra
A5: Imposto de renda federal EUA efetivamente pago (US$) | B5: ='05_US_TAXES'!$G$5 -> 0 | C5: 1040/2018 l.13 = 0 (CTC 164 zerou o imposto de 164) [FATO CONFIRMADO — OCR]
A6: Imposto estadual CT (US$) — não creditável | B6: ='05_US_TAXES'!$L$5 -> 0 | C6: ADI SRF 28/2000 — reciprocidade só p/ imposto federal [confirmar na fonte oficial]
A7: Taxa de conversão do imposto pago (EDITAR) | B7: 3.8742 | C7: [HIPÓTESE] Dólar compra 28/12/2018 (BCB SGS 10813). Imposto = 0, a taxa não altera o resultado
A8: Imposto pago nos EUA convertido (R$) | B8: =ROUND(B5*B7,2) -> 0
A9: IRPF BR total do ano (R$) | B9: ='07_BRAZIL_TAX_CALCULATION'!B30 -> 10434.74 | C9: 07
A10: Parcela do IRPF BR atribuível à renda EUA (R$) | B10: =IF('07_BRAZIL_TAX_CALCULATION'!B22=0,0,ROUND(B9*'07_BRAZIL_TAX_CALCULATION'!B20/'07_BRAZIL_TAX_CALCULATION'!B22,2)) -> 10434.74 | C10: Limite: imposto BR proporcional ao mesmo rendimento (RIR/2018 — confirmar artigo)
A11: Exige comprovação de pagamento efetivo? | B11: SIM | C11: IRS Account Transcript 2018 — PENDENTE (baixa prioridade: imposto = 0)
A12: Documentação disponível? | B12: PARCIAL | C12: Só o 1040 (OCR)
A14: CRÉDITO APROVEITÁVEL AC 2018 (R$) | B14: =MIN(B8,B10) -> 0 | C14: MIN(imposto pago convertido; limite)
A15: AC 2019 (01–24/01) — crédito | B15: 0 | C15: Sem IRPF BR no período → sem crédito
A16: AC 2020 a 2025 — crédito | B16: N/A | C16: Não residente: renda EUA não tributada no BR → compensação sem objeto
A17: SE tax 2019–2024 (US$) — não creditável | B17: =SUM('05_US_TAXES'!H6:H11) -> 16220 | C17: Contribuição previdenciária (Social Security/Medicare), não imposto de renda
A20: Conclusão [INFERÊNCIA TÉCNICA]: o crédito é nulo — no único ano integral de residência (2018) o imposto federal pago foi zero. Não compensa custo de obtenção de transcripts para fins de crédito.

Sheet 07_BRAZIL_TAX_CALCULATION
A1: 07 — APURAÇÃO DO IRPF/IRRF BRASIL POR ANO E PERÍODO
A2: José Adalmo Carvalho de Barros — CPF 069.351.996-70 | Resp. técnico: Robson Soares Bezerra — CRC/PR 062711/O
A3: BLOCO A — AC 2018 — RESIDENTE (rendimentos mundiais). INFORMATIVO: DECAÍDO — ver 02/08.
A4: Mês de recebimento | B4: US$ recebido (EDITAR) | C4: Data PTAX (regra) | D4: Dólar compra (BCB) | E4: Rendimento R$ | F4: IR mensal carnê-leão | I4: Observação
A5: Jan/2018 | B5: ='05_US_TAXES'!$D$5/12 -> 2135.6667 | C5: 43084 | D5: 3.3176 | E5: =ROUND(B5*D5,2) -> 7085.29 | F5: =ROUND(MAX(0,E5*LOOKUP(E5,'00_PARAMETROS'!$A$25:$A$29,'00_PARAMETROS'!$B$25:$B$29)-LOOKUP(E5,'00_PARAMETROS'!$A$25:$A$29,'00_PARAMETROS'!$C$25:$C$29)),2) -> 1079.09 | I5: [HIPÓTESE] W-2 anual ÷ 12 — substituir pelos holerites/paystubs reais
A6: Fev/2018 | B6: ='05_US_TAXES'!$D$5/12 -> 2135.6667 | C6: 43115 | D6: 3.1957 | E6: =ROUND(B6*D6,2) -> 6824.95 | F6: =ROUND(MAX(0,E6*LOOKUP(E6,'00_PARAMETROS'!$A$25:$A$29,'00_PARAMETROS'!$B$25:$B$29)-LOOKUP(E6,'00_PARAMETROS'!$A$25:$A$29,'00_PARAMETROS'!$C$25:$C$29)),2) -> 1007.5
A7: Mar/2018 | B7: ='05_US_TAXES'!$D$5/12 -> 2135.6667 | C7: 43146 | D7: 3.2202 | E7: =ROUND(B7*D7,2) -> 6877.27 | F7: =ROUND(MAX(0,E7*LOOKUP(E7,'00_PARAMETROS'!$A$25:$A$29,'00_PARAMETROS'!$B$25:$B$29)-LOOKUP(E7,'00_PARAMETROS'!$A$25:$A$29,'00_PARAMETROS'!$C$25:$C$29)),2) -> 1021.89
A8: Abr/2018 | B8: ='05_US_TAXES'!$D$5/12 -> 2135.6667 | C8: 43174 | D8: 3.2853 | E8: =ROUND(B8*D8,2) -> 7016.31 | F8: =ROUND(MAX(0,E8*LOOKUP(E8,'00_PARAMETROS'!$A$25:$A$29,'00_PARAMETROS'!$B$25:$B$29)-LOOKUP(E8,'00_PARAMETROS'!$A$25:$A$29,'00_PARAMETROS'!$C$25:$C$29)),2) -> 1060.13
A9: Mai/2018 | B9: ='05_US_TAXES'!$D$5/12 -> 2135.6667 | C9: 43203 | D9: 3.4099 | E9: =ROUND(B9*D9,2) -> 7282.41 | F9: =ROUND(MAX(0,E9*LOOKUP(E9,'00_PARAMETROS'!$A$25:$A$29,'00_PARAMETROS'!$B$25:$B$29)-LOOKUP(E9,'00_PARAMETROS'!$A$25:$A$29,'00_PARAMETROS'!$C$25:$C$29)),2) -> 1133.3
A10: Jun/2018 | B10: ='05_US_TAXES'!$D$5/12 -> 2135.6667 | C10: 43235 | D10: 3.6747 | E10: =ROUND(B10*D10,2) -> 7847.93 | F10: =ROUND(MAX(0,E10*LOOKUP(E10,'00_PARAMETROS'!$A$25:$A$29,'00_PARAMETROS'!$B$25:$B$29)-LOOKUP(E10,'00_PARAMETROS'!$A$25:$A$29,'00_PARAMETROS'!$C$25:$C$29)),2) -> 1288.82
A11: Jul/2018 | B11: ='05_US_TAXES'!$D$5/12 -> 2135.6667 | C11: 43266 | D11: 3.7732 | E11: =ROUND(B11*D11,2) -> 8058.3 | F11: =ROUND(MAX(0,E11*LOOKUP(E11,'00_PARAMETROS'!$A$25:$A$29,'00_PARAMETROS'!$B$25:$B$29)-LOOKUP(E11,'00_PARAMETROS'!$A$25:$A$29,'00_PARAMETROS'!$C$25:$C$29)),2) -> 1346.67
A12: Ago/2018 | B12: ='05_US_TAXES'!$D$5/12 -> 2135.6667 | C12: 43294 | D12: 3.8739 | E12: =ROUND(B12*D12,2) -> 8273.36 | F12: =ROUND(MAX(0,E12*LOOKUP(E12,'00_PARAMETROS'!$A$25:$A$29,'00_PARAMETROS'!$B$25:$B$29)-LOOKUP(E12,'00_PARAMETROS'!$A$25:$A$29,'00_PARAMETROS'!$C$25:$C$29)),2) -> 1405.81
A13: Set/2018 | B13: ='05_US_TAXES'!$D$5/12 -> 2135.6667 | C13: 43327 | D13: 3.9128 | E13: =ROUND(B13*D13,2) -> 8356.44 | F13: =ROUND(MAX(0,E13*LOOKUP(E13,'00_PARAMETROS'!$A$25:$A$29,'00_PARAMETROS'!$B$25:$B$29)-LOOKUP(E13,'00_PARAMETROS'!$A$25:$A$29,'00_PARAMETROS'!$C$25:$C$29)),2) -> 1428.66
A14: Out/2018 | B14: ='05_US_TAXES'!$D$5/12 -> 2135.6667 | C14: 43357 | D14: 4.1873 | E14: =ROUND(B14*D14,2) -> 8942.68 | F14: =ROUND(MAX(0,E14*LOOKUP(E14,'00_PARAMETROS'!$A$25:$A$29,'00_PARAMETROS'!$B$25:$B$29)-LOOKUP(E14,'00_PARAMETROS'!$A$25:$A$29,'00_PARAMETROS'!$C$25:$C$29)),2) -> 1589.88
A15: Nov/2018 | B15: ='05_US_TAXES'!$D$5/12 -> 2135.6667 | C15: 43388 | D15: 3.7326 | E15: =ROUND(B15*D15,2) -> 7971.59 | F15: =ROUND(MAX(0,E15*LOOKUP(E15,'00_PARAMETROS'!$A$25:$A$29,'00_PARAMETROS'!$B$25:$B$29)-LOOKUP(E15,'00_PARAMETROS'!$A$25:$A$29,'00_PARAMETROS'!$C$25:$C$29)),2) -> 1322.83
A16: Dez/2018 | B16: ='05_US_TAXES'!$D$5/12 -> 2135.6667 | C16: 43418 | D16: 3.7918 | E16: =ROUND(B16*D16,2) -> 8098.02 | F16: =ROUND(MAX(0,E16*LOOKUP(E16,'00_PARAMETROS'!$A$25:$A$29,'00_PARAMETROS'!$B$25:$B$29)-LOOKUP(E16,'00_PARAMETROS'!$A$25:$A$29,'00_PARAMETROS'!$C$25:$C$29)),2) -> 1357.6
A17: TOTAL AC 2018 | B17: =SUM(B5:B16) -> 25628 | E17: =SUM(E5:E16) -> 92634.55 | F17: =SUM(F5:F16) -> 15042.18 | I17: Dólar compra BCB, último dia útil da 1ª quinzena do mês anterior ao recebimento (BCB SGS 10813) [INFERÊNCIA TÉCNICA sobre a regra — RIR/2018; confirmar artigo na fonte oficial].
A19: Ajuste anual AC 2018 | B19: Valor (R$) | I19: Fórmula / fonte
A20: Rendimentos do exterior (R$) | B20: =E17 -> 92634.55 | I20: Soma mensal acima
A21: Rendimentos de fonte BR 01–24/01/2018 (EDITAR) | B21: 0 | I21: PENDENTE — DOCUMENTO NECESSÁRIO (P-01). Zero por ausência de prova, não por confirmação.
A22: Total rendimentos tributáveis | B22: =B20+B21 -> 92634.55
A23: Obrigado a declarar? | B23: =IF(B22>'00_PARAMETROS'!$B$36,"SIM","NÃO") -> SIM | I23: Limite R$ 28.559,70
A24: Desconto simplificado | B24: =MIN(B22*'00_PARAMETROS'!$B$32,'00_PARAMETROS'!$B$33) -> 16754.34 | I24: 20% limitado a R$ 16.754,34
A25: Base — modelo simplificado | B25: =B22-B24 -> 75880.21
A26: Imposto — modelo simplificado | B26: =ROUND(MAX(0,B25*LOOKUP(B25,'00_PARAMETROS'!$A$17:$A$21,'00_PARAMETROS'!$B$17:$B$21)-LOOKUP(B25,'00_PARAMETROS'!$A$17:$A$21,'00_PARAMETROS'!$C$17:$C$21)),2) -> 10434.74 | I26: Tabela anual
A27: Dedução dependentes (modelo completo) | B27: ='00_PARAMETROS'!$B$35*'00_PARAMETROS'!$B$34 -> 6825.24 | I27: [HIPÓTESE] 3 dependentes
A28: Base — modelo completo | B28: =MAX(0,B22-B27) -> 85809.31 | I28: Sem outras deduções comprovadas
A29: Imposto — modelo completo | B29: =ROUND(MAX(0,B28*LOOKUP(B28,'00_PARAMETROS'!$A$17:$A$21,'00_PARAMETROS'!$B$17:$B$21)-LOOKUP(B28,'00_PARAMETROS'!$A$17:$A$21,'00_PARAMETROS'!$C$17:$C$21)),2) -> 13165.24
A30: IRPF devido (menor dos modelos) | B30: =MIN(B26,B29) -> 10434.74
A31: (−) Carnê-leão pago (EDITAR) | B31: 0 | I31: Nenhum DARF localizado
A32: (−) Crédito imposto pago nos EUA | B32: ='06_FOREIGN_TAX_CREDIT'!B14 -> 0 | I32: Ver 06
A33: IRPF a pagar — AC 2018 (principal) | B33: =MAX(0,B30-B31-B32) -> 10434.74 | I33: Informativo — DECAÍDO
A34: Referência: laudo Fase 6 | B34: 11415.06 | I34: Diferença decorre do teto do desconto simplificado e da regra cambial
A35: Diferença vs. laudo Fase 6 | B35: =B33-B34 -> -980.32
A37: BLOCO A2 — AC 2019 — RESIDENTE 01/01 a 24/01/2019 (DSDP). INFORMATIVO: DECAÍDO.
A38: Item | B38: Valor | I38: Fonte / observação
A39: Rendimento Sch C 2019 (US$) | B39: ='05_US_TAXES'!$E$6 -> 10000 | I39: [FATO CONFIRMADO — OCR] 1040/2019
A40: Dias como residente em 2019 | B40: ='00_PARAMETROS'!$B$6-DATE(2019,1,1) -> 24 | I40: Da data 01/01/2019 até a véspera da não residência
A41: US$ proporcional ao período residente | B41: =ROUND(B39*B40/365,2) -> 657.53 | I41: [HIPÓTESE] Rateio linear — sem paystubs/notas de jan/2019
A42: Dólar compra 14/12/2018 | B42: 3.9084 | I42: BCB SGS 10813 — 1ª quinzena do mês anterior (jan/2019)
A43: Rendimento R$ — período residente | B43: =ROUND(B41*B42,2) -> 2569.89
A44: Obrigado pelo limite de rendimentos? | B44: =IF(B43>'00_PARAMETROS'!$B$36,"SIM","NÃO") -> NÃO | I44: Limite R$ 28.559,70 (exercício 2020)
A45: IRPF anual (tabela sem desconto) | B45: =ROUND(MAX(0,B43*LOOKUP(B43,'00_PARAMETROS'!$A$17:$A$21,'00_PARAMETROS'!$B$17:$B$21)-LOOKUP(B43,'00_PARAMETROS'!$A$17:$A$21,'00_PARAMETROS'!$C$17:$C$21)),2) -> 0 | I45: Abaixo da faixa isenta
A46: MAED (se a DSDP for obrigatória) | B46: =MAX('00_PARAMETROS'!$B$37,0) -> 165.74 | I46: Mínimo R$ 165,74 — decaído em 31/12/2025 (02)
A48: BLOCO B — NÃO RESIDENTE (25/01/2019 em diante): renda EUA fora do IRPF; somente IRRF sobre renda de fonte BR (da aba 04)
A49: AC | B49: Renda EUA — IR BR | C49: Entradas BR (total) | D49: Entradas PENDENTES | E49: Base IRRF apurada | F49: IRRF apurado (principal) | G49: Cenário A 15% (principal) | H49: Cenário B 25% (principal) | I49: Observação
A50: 2019 | B50: 0 | C50: =SUMIFS('04_BANK_TRANSACTIONS'!$F$5:$F$168,'04_BANK_TRANSACTIONS'!$C$5:$C$168,A50,'04_BANK_TRANSACTIONS'!$G$5:$G$168,"entrada") -> 0 | D50: =SUMIFS('04_BANK_TRANSACTIONS'!$F$5:$F$168,'04_BANK_TRANSACTIONS'!$C$5:$C$168,A50,'04_BANK_TRANSACTIONS'!$G$5:$G$168,"entrada",'04_BANK_TRANSACTIONS'!$K$5:$K$168,"PENDENTE") -> 0 | E50: =SUMIFS('04_BANK_TRANSACTIONS'!$O$5:$O$168,'04_BANK_TRANSACTIONS'!$C$5:$C$168,A50) -> 0 | F50: =SUMIFS('04_BANK_TRANSACTIONS'!$P$5:$P$168,'04_BANK_TRANSACTIONS'!$C$5:$C$168,A50) -> 0 | G50: =SUMIFS('04_BANK_TRANSACTIONS'!$Q$5:$Q$168,'04_BANK_TRANSACTIONS'!$C$5:$C$168,A50) -> 0 | H50: =SUMIFS('04_BANK_TRANSACTIONS'!$R$5:$R$168,'04_BANK_TRANSACTIONS'!$C$5:$C$168,A50) -> 0 | I50: Sem extratos BR para o ano — PENDENTE — DOCUMENTO NECESSÁRIO
A51: 2020 | B51: 0 | C51: =SUMIFS('04_BANK_TRANSACTIONS'!$F$5:$F$168,'04_BANK_TRANSACTIONS'!$C$5:$C$168,A51,'04_BANK_TRANSACTIONS'!$G$5:$G$168,"entrada") -> 0 | D51: =SUMIFS('04_BANK_TRANSACTIONS'!$F$5:$F$168,'04_BANK_TRANSACTIONS'!$C$5:$C$168,A51,'04_BANK_TRANSACTIONS'!$G$5:$G$168,"entrada",'04_BANK_TRANSACTIONS'!$K$5:$K$168,"PENDENTE") -> 0 | E51: =SUMIFS('04_BANK_TRANSACTIONS'!$O$5:$O$168,'04_BANK_TRANSACTIONS'!$C$5:$C$168,A51) -> 0 | F51: =SUMIFS('04_BANK_TRANSACTIONS'!$P$5:$P$168,'04_BANK_TRANSACTIONS'!$C$5:$C$168,A51) -> 0 | G51: =SUMIFS('04_BANK_TRANSACTIONS'!$Q$5:$Q$168,'04_BANK_TRANSACTIONS'!$C$5:$C$168,A51) -> 0 | H51: =SUMIFS('04_BANK_TRANSACTIONS'!$R$5:$R$168,'04_BANK_TRANSACTIONS'!$C$5:$C$168,A51) -> 0 | I51: Sem extratos BR para o ano — PENDENTE — DOCUMENTO NECESSÁRIO
A52: 2021 | B52: 0 | C52: =SUMIFS('04_BANK_TRANSACTIONS'!$F$5:$F$168,'04_BANK_TRANSACTIONS'!$C$5:$C$168,A52,'04_BANK_TRANSACTIONS'!$G$5:$G$168,"entrada") -> 0 | D52: =SUMIFS('04_BANK_TRANSACTIONS'!$F$5:$F$168,'04_BANK_TRANSACTIONS'!$C$5:$C$168,A52,'04_BANK_TRANSACTIONS'!$G$5:$G$168,"entrada",'04_BANK_TRANSACTIONS'!$K$5:$K$168,"PENDENTE") -> 0 | E52: =SUMIFS('04_BANK_TRANSACTIONS'!$O$5:$O$168,'04_BANK_TRANSACTIONS'!$C$5:$C$168,A52) -> 0 | F52: =SUMIFS('04_BANK_TRANSACTIONS'!$P$5:$P$168,'04_BANK_TRANSACTIONS'!$C$5:$C$168,A52) -> 0 | G52: =SUMIFS('04_BANK_TRANSACTIONS'!$Q$5:$Q$168,'04_BANK_TRANSACTIONS'!$C$5:$C$168,A52) -> 0 | H52: =SUMIFS('04_BANK_TRANSACTIONS'!$R$5:$R$168,'04_BANK_TRANSACTIONS'!$C$5:$C$168,A52) -> 0 | I52: Sem extratos BR para o ano — PENDENTE — DOCUMENTO NECESSÁRIO
A53: 2022 | B53: 0 | C53: =SUMIFS('04_BANK_TRANSACTIONS'!$F$5:$F$168,'04_BANK_TRANSACTIONS'!$C$5:$C$168,A53,'04_BANK_TRANSACTIONS'!$G$5:$G$168,"entrada") -> 0 | D53: =SUMIFS('04_BANK_TRANSACTIONS'!$F$5:$F$168,'04_BANK_TRANSACTIONS'!$C$5:$C$168,A53,'04_BANK_TRANSACTIONS'!$G$5:$G$168,"entrada",'04_BANK_TRANSACTIONS'!$K$5:$K$168,"PENDENTE") -> 0 | E53: =SUMIFS('04_BANK_TRANSACTIONS'!$O$5:$O$168,'04_BANK_TRANSACTIONS'!$C$5:$C$168,A53) -> 0 | F53: =SUMIFS('04_BANK_TRANSACTIONS'!$P$5:$P$168,'04_BANK_TRANSACTIONS'!$C$5:$C$168,A53) -> 0 | G53: =SUMIFS('04_BANK_TRANSACTIONS'!$Q$5:$Q$168,'04_BANK_TRANSACTIONS'!$C$5:$C$168,A53) -> 0 | H53: =SUMIFS('04_BANK_TRANSACTIONS'!$R$5:$R$168,'04_BANK_TRANSACTIONS'!$C$5:$C$168,A53) -> 0 | I53: Sem extratos BR para o ano — PENDENTE — DOCUMENTO NECESSÁRIO
A54: 2023 | B54: 0 | C54: =SUMIFS('04_BANK_TRANSACTIONS'!$F$5:$F$168,'04_BANK_TRANSACTIONS'!$C$5:$C$168,A54,'04_BANK_TRANSACTIONS'!$G$5:$G$168,"entrada") -> 0 | D54: =SUMIFS('04_BANK_TRANSACTIONS'!$F$5:$F$168,'04_BANK_TRANSACTIONS'!$C$5:$C$168,A54,'04_BANK_TRANSACTIONS'!$G$5:$G$168,"entrada",'04_BANK_TRANSACTIONS'!$K$5:$K$168,"PENDENTE") -> 0 | E54: =SUMIFS('04_BANK_TRANSACTIONS'!$O$5:$O$168,'04_BANK_TRANSACTIONS'!$C$5:$C$168,A54) -> 0 | F54: =SUMIFS('04_BANK_TRANSACTIONS'!$P$5:$P$168,'04_BANK_TRANSACTIONS'!$C$5:$C$168,A54) -> 0 | G54: =SUMIFS('04_BANK_TRANSACTIONS'!$Q$5:$Q$168,'04_BANK_TRANSACTIONS'!$C$5:$C$168,A54) -> 0 | H54: =SUMIFS('04_BANK_TRANSACTIONS'!$R$5:$R$168,'04_BANK_TRANSACTIONS'!$C$5:$C$168,A54) -> 0 | I54: Sem extratos BR para o ano — PENDENTE — DOCUMENTO NECESSÁRIO
A55: 2024 | B55: 0 | C55: =SUMIFS('04_BANK_TRANSACTIONS'!$F$5:$F$168,'04_BANK_TRANSACTIONS'!$C$5:$C$168,A55,'04_BANK_TRANSACTIONS'!$G$5:$G$168,"entrada") -> 89125 | D55: =SUMIFS('04_BANK_TRANSACTIONS'!$F$5:$F$168,'04_BANK_TRANSACTIONS'!$C$5:$C$168,A55,'04_BANK_TRANSACTIONS'!$G$5:$G$168,"entrada",'04_BANK_TRANSACTIONS'!$K$5:$K$168,"PENDENTE") -> 47450 | E55: =SUMIFS('04_BANK_TRANSACTIONS'!$O$5:$O$168,'04_BANK_TRANSACTIONS'!$C$5:$C$168,A55) -> 0 | F55: =SUMIFS('04_BANK_TRANSACTIONS'!$P$5:$P$168,'04_BANK_TRANSACTIONS'!$C$5:$C$168,A55) -> 0 | G55: =SUMIFS('04_BANK_TRANSACTIONS'!$Q$5:$Q$168,'04_BANK_TRANSACTIONS'!$C$5:$C$168,A55) -> 7117.5 | H55: =SUMIFS('04_BANK_TRANSACTIONS'!$R$5:$R$168,'04_BANK_TRANSACTIONS'!$C$5:$C$168,A55) -> 11862.5 | I55: Extratos out–dez/2024
A56: 2025 | B56: 0 | C56: =SUMIFS('04_BANK_TRANSACTIONS'!$F$5:$F$168,'04_BANK_TRANSACTIONS'!$C$5:$C$168,A56,'04_BANK_TRANSACTIONS'!$G$5:$G$168,"entrada") -> 876334.05 | D56: =SUMIFS('04_BANK_TRANSACTIONS'!$F$5:$F$168,'04_BANK_TRANSACTIONS'!$C$5:$C$168,A56,'04_BANK_TRANSACTIONS'!$G$5:$G$168,"entrada",'04_BANK_TRANSACTIONS'!$K$5:$K$168,"PENDENTE") -> 568060 | E56: =SUMIFS('04_BANK_TRANSACTIONS'!$O$5:$O$168,'04_BANK_TRANSACTIONS'!$C$5:$C$168,A56) -> 0 | F56: =SUMIFS('04_BANK_TRANSACTIONS'!$P$5:$P$168,'04_BANK_TRANSACTIONS'!$C$5:$C$168,A56) -> 0 | G56: =SUMIFS('04_BANK_TRANSACTIONS'!$Q$5:$Q$168,'04_BANK_TRANSACTIONS'!$C$5:$C$168,A56) -> 85209 | H56: =SUMIFS('04_BANK_TRANSACTIONS'!$R$5:$R$168,'04_BANK_TRANSACTIONS'!$C$5:$C$168,A56) -> 142015 | I56: Extratos 2025 (abr e mai ausentes)
A57: 2026 | B57: 0 | C57: =SUMIFS('04_BANK_TRANSACTIONS'!$F$5:$F$168,'04_BANK_TRANSACTIONS'!$C$5:$C$168,A57,'04_BANK_TRANSACTIONS'!$G$5:$G$168,"entrada") -> 16400.06 | D57: =SUMIFS('04_BANK_TRANSACTIONS'!$F$5:$F$168,'04_BANK_TRANSACTIONS'!$C$5:$C$168,A57,'04_BANK_TRANSACTIONS'!$G$5:$G$168,"entrada",'04_BANK_TRANSACTIONS'!$K$5:$K$168,"PENDENTE") -> 8000 | E57: =SUMIFS('04_BANK_TRANSACTIONS'!$O$5:$O$168,'04_BANK_TRANSACTIONS'!$C$5:$C$168,A57) -> 0 | F57: =SUMIFS('04_BANK_TRANSACTIONS'!$P$5:$P$168,'04_BANK_TRANSACTIONS'!$C$5:$C$168,A57) -> 0 | G57: =SUMIFS('04_BANK_TRANSACTIONS'!$Q$5:$Q$168,'04_BANK_TRANSACTIONS'!$C$5:$C$168,A57) -> 1200 | H57: =SUMIFS('04_BANK_TRANSACTIONS'!$R$5:$R$168,'04_BANK_TRANSACTIONS'!$C$5:$C$168,A57) -> 2000 | I57: Extratos jan–abr/2026 parciais
A58: TOTAL | C58: =SUM(C50:C57) -> 981859.11 | D58: =SUM(D50:D57) -> 623510 | E58: =SUM(E50:E57) -> 0 | F58: =SUM(F50:F57) -> 0 | G58: =SUM(G50:G57) -> 93526.5 | H58: =SUM(H50:H57) -> 155877.5

Sheet 08_INTEREST_PENALTIES
A1: 08 — JUROS SELIC E MULTAS ATÉ A DATA-BASE
A2: José Adalmo Carvalho de Barros — CPF 069.351.996-70 | Resp. técnico: Robson Soares Bezerra — CRC/PR 062711/O
A3: ="Data-base: "&TEXT('00_PARAMETROS'!$B$4,"DD/MM/YYYY")&" | Juros = SELIC acumulada (mês seguinte ao vencimento → mês anterior ao pagamento) + 1% | Multa de mora 0,33%/dia, teto 20% (pagamento espontâneo)" -> Data-base: 30/09/2026 | Juros = SELIC acumulada (mês seguinte ao vencimento → mês anterior ao pagamento) + 1% | Multa de mora 0,33%/dia, teto 20% (pagamento espontâneo)
A5: Tributo / período | B5: Principal (R$) | C5: Vencimento | D5: Decadência | E5: Exigível? | F5: Juros % | G5: Multa % | H5: Juros R$ | I5: Multa R$ | J5: Total atualizado | K5: Total EXIGÍVEL | L5: Base legal | M5: Observação
A6: IRPF AC 2018 — ajuste anual | B6: ='07_BRAZIL_TAX_CALCULATION'!B33 -> 10434.74 | C6: 43585 | D6: ='02_TAX_TIMELINE'!F7 -> 45657 | E6: =IF('00_PARAMETROS'!$B$4>D6,"NÃO","SIM") -> NÃO | F6: =SUMIFS(SELIC!$B$4:$B$96,SELIC!$A$4:$A$96,">="&DATE(YEAR(C6),MONTH(C6)+1,1),SELIC!$A$4:$A$96,"<="&DATE(YEAR('00_PARAMETROS'!$B$4),MONTH('00_PARAMETROS'!$B$4)-1,1))+'00_PARAMETROS'!$B$11 -> 0.6869 | G6: =MIN('00_PARAMETROS'!$B$9,'00_PARAMETROS'!$B$8*MAX(0,'00_PARAMETROS'!$B$4-C6)) -> 0.2 | H6: =ROUND(B6*F6,2) -> 7167.62 | I6: =ROUND(B6*G6,2) -> 2086.95 | J6: =B6+H6+I6 -> 19689.31 | K6: =IF(E6="SIM",J6,0) -> 0 | L6: Lei 9.430/96 art. 61; CTN 173, I | M6: Informativo — crédito tributário extinto (CTN art. 156, V). Pagamento voluntário = indébito.
A7: MAED — DSDP AC 2019 | B7: ='07_BRAZIL_TAX_CALCULATION'!B46 -> 165.74 | C7: 44013 | D7: ='02_TAX_TIMELINE'!F8 -> 46022 | E7: =IF('00_PARAMETROS'!$B$4>D7,"NÃO","SIM") -> NÃO | F7: =0 -> 0 | G7: =0 -> 0 | H7: =ROUND(B7*F7,2) -> 0 | I7: =ROUND(B7*G7,2) -> 0 | J7: =B7+H7+I7 -> 165.74 | K7: =IF(E7="SIM",J7,0) -> 0 | L7: Lei 9.430/96 art. 61; CTN 173, I | M7: Multa por atraso; sem juros até lançamento. Decaída.
A8: IRRF apurado — 2019 | B8: =SUMIFS('04_BANK_TRANSACTIONS'!$P$5:$P$168,'04_BANK_TRANSACTIONS'!$C$5:$C$168,2019) -> 0 | C8: por lançamento (04) | D8: =DATE(2019+5,12,31) -> 45657 | E8: =IF('00_PARAMETROS'!$B$4>D8,"NÃO","SIM") -> NÃO | J8: =SUMIFS('04_BANK_TRANSACTIONS'!$U$5:$U$168,'04_BANK_TRANSACTIONS'!$C$5:$C$168,2019) -> 0 | K8: =IF(E8="SIM",J8,0) -> 0 | L8: IRRF não residente; Lei 9.430/96 art. 61 | M8: Juros/multa calculados linha a linha na aba 04
A9: Cenário A 15% (exposição) — 2019 | B9: =SUMIFS('04_BANK_TRANSACTIONS'!$Q$5:$Q$168,'04_BANK_TRANSACTIONS'!$C$5:$C$168,2019) -> 0 | C9: por lançamento (04) | D9: =DATE(2019+5,12,31) -> 45657 | E9: =IF('00_PARAMETROS'!$B$4>D9,"NÃO","SIM") -> NÃO | J9: =SUMIFS('04_BANK_TRANSACTIONS'!$V$5:$V$168,'04_BANK_TRANSACTIONS'!$C$5:$C$168,2019) -> 0 | K9: 0 | L9: IRRF não residente; Lei 9.430/96 art. 61 | M9: Juros/multa calculados linha a linha na aba 04 — CENÁRIO, NÃO É IMPOSTO DEVIDO
A10: Cenário B 25% (exposição) — 2019 | B10: =SUMIFS('04_BANK_TRANSACTIONS'!$R$5:$R$168,'04_BANK_TRANSACTIONS'!$C$5:$C$168,2019) -> 0 | C10: por lançamento (04) | D10: =DATE(2019+5,12,31) -> 45657 | E10: =IF('00_PARAMETROS'!$B$4>D10,"NÃO","SIM") -> NÃO | J10: =SUMIFS('04_BANK_TRANSACTIONS'!$W$5:$W$168,'04_BANK_TRANSACTIONS'!$C$5:$C$168,2019) -> 0 | K10: 0 | L10: IRRF não residente; Lei 9.430/96 art. 61 | M10: Juros/multa calculados linha a linha na aba 04 — CENÁRIO, NÃO É IMPOSTO DEVIDO
A11: IRRF apurado — 2020 | B11: =SUMIFS('04_BANK_TRANSACTIONS'!$P$5:$P$168,'04_BANK_TRANSACTIONS'!$C$5:$C$168,2020) -> 0 | C11: por lançamento (04) | D11: =DATE(2020+5,12,31) -> 46022 | E11: =IF('00_PARAMETROS'!$B$4>D11,"NÃO","SIM") -> NÃO | J11: =SUMIFS('04_BANK_TRANSACTIONS'!$U$5:$U$168,'04_BANK_TRANSACTIONS'!$C$5:$C$168,2020) -> 0 | K11: =IF(E11="SIM",J11,0) -> 0 | L11: IRRF não residente; Lei 9.430/96 art. 61 | M11: Juros/multa calculados linha a linha na aba 04
A12: Cenário A 15% (exposição) — 2020 | B12: =SUMIFS('04_BANK_TRANSACTIONS'!$Q$5:$Q$168,'04_BANK_TRANSACTIONS'!$C$5:$C$168,2020) -> 0 | C12: por lançamento (04) | D12: =DATE(2020+5,12,31) -> 46022 | E12: =IF('00_PARAMETROS'!$B$4>D12,"NÃO","SIM") -> NÃO | J12: =SUMIFS('04_BANK_TRANSACTIONS'!$V$5:$V$168,'04_BANK_TRANSACTIONS'!$C$5:$C$168,2020) -> 0 | K12: 0 | L12: IRRF não residente; Lei 9.430/96 art. 61 | M12: Juros/multa calculados linha a linha na aba 04 — CENÁRIO, NÃO É IMPOSTO DEVIDO
A13: Cenário B 25% (exposição) — 2020 | B13: =SUMIFS('04_BANK_TRANSACTIONS'!$R$5:$R$168,'04_BANK_TRANSACTIONS'!$C$5:$C$168,2020) -> 0 | C13: por lançamento (04) | D13: =DATE(2020+5,12,31) -> 46022 | E13: =IF('00_PARAMETROS'!$B$4>D13,"NÃO","SIM") -> NÃO | J13: =SUMIFS('04_BANK_TRANSACTIONS'!$W$5:$W$168,'04_BANK_TRANSACTIONS'!$C$5:$C$168,2020) -> 0 | K13: 0 | L13: IRRF não residente; Lei 9.430/96 art. 61 | M13: Juros/multa calculados linha a linha na aba 04 — CENÁRIO, NÃO É IMPOSTO DEVIDO
A14: IRRF apurado — 2021 | B14: =SUMIFS('04_BANK_TRANSACTIONS'!$P$5:$P$168,'04_BANK_TRANSACTIONS'!$C$5:$C$168,2021) -> 0 | C14: por lançamento (04) | D14: =DATE(2021+5,12,31) -> 46387 | E14: =IF('00_PARAMETROS'!$B$4>D14,"NÃO","SIM") -> SIM | J14: =SUMIFS('04_BANK_TRANSACTIONS'!$U$5:$U$168,'04_BANK_TRANSACTIONS'!$C$5:$C$168,2021) -> 0 | K14: =IF(E14="SIM",J14,0) -> 0 | L14: IRRF não residente; Lei 9.430/96 art. 61 | M14: Juros/multa calculados linha a linha na aba 04
A15: Cenário A 15% (exposição) — 2021 | B15: =SUMIFS('04_BANK_TRANSACTIONS'!$Q$5:$Q$168,'04_BANK_TRANSACTIONS'!$C$5:$C$168,2021) -> 0 | C15: por lançamento (04) | D15: =DATE(2021+5,12,31) -> 46387 | E15: =IF('00_PARAMETROS'!$B$4>D15,"NÃO","SIM") -> SIM | J15: =SUMIFS('04_BANK_TRANSACTIONS'!$V$5:$V$168,'04_BANK_TRANSACTIONS'!$C$5:$C$168,2021) -> 0 | K15: 0 | L15: IRRF não residente; Lei 9.430/96 art. 61 | M15: Juros/multa calculados linha a linha na aba 04 — CENÁRIO, NÃO É IMPOSTO DEVIDO
A16: Cenário B 25% (exposição) — 2021 | B16: =SUMIFS('04_BANK_TRANSACTIONS'!$R$5:$R$168,'04_BANK_TRANSACTIONS'!$C$5:$C$168,2021) -> 0 | C16: por lançamento (04) | D16: =DATE(2021+5,12,31) -> 46387 | E16: =IF('00_PARAMETROS'!$B$4>D16,"NÃO","SIM") -> SIM | J16: =SUMIFS('04_BANK_TRANSACTIONS'!$W$5:$W$168,'04_BANK_TRANSACTIONS'!$C$5:$C$168,2021) -> 0 | K16: 0 | L16: IRRF não residente; Lei 9.430/96 art. 61 | M16: Juros/multa calculados linha a linha na aba 04 — CENÁRIO, NÃO É IMPOSTO DEVIDO
A17: IRRF apurado — 2022 | B17: =SUMIFS('04_BANK_TRANSACTIONS'!$P$5:$P$168,'04_BANK_TRANSACTIONS'!$C$5:$C$168,2022) -> 0 | C17: por lançamento (04) | D17: =DATE(2022+5,12,31) -> 46752 | E17: =IF('00_PARAMETROS'!$B$4>D17,"NÃO","SIM") -> SIM | J17: =SUMIFS('04_BANK_TRANSACTIONS'!$U$5:$U$168,'04_BANK_TRANSACTIONS'!$C$5:$C$168,2022) -> 0 | K17: =IF(E17="SIM",J17,0) -> 0 | L17: IRRF não residente; Lei 9.430/96 art. 61 | M17: Juros/multa calculados linha a linha na aba 04
A18: Cenário A 15% (exposição) — 2022 | B18: =SUMIFS('04_BANK_TRANSACTIONS'!$Q$5:$Q$168,'04_BANK_TRANSACTIONS'!$C$5:$C$168,2022) -> 0 | C18: por lançamento (04) | D18: =DATE(2022+5,12,31) -> 46752 | E18: =IF('00_PARAMETROS'!$B$4>D18,"NÃO","SIM") -> SIM | J18: =SUMIFS('04_BANK_TRANSACTIONS'!$V$5:$V$168,'04_BANK_TRANSACTIONS'!$C$5:$C$168,2022) -> 0 | K18: 0 | L18: IRRF não residente; Lei 9.430/96 art. 61 | M18: Juros/multa calculados linha a linha na aba 04 — CENÁRIO, NÃO É IMPOSTO DEVIDO
A19: Cenário B 25% (exposição) — 2022 | B19: =SUMIFS('04_BANK_TRANSACTIONS'!$R$5:$R$168,'04_BANK_TRANSACTIONS'!$C$5:$C$168,2022) -> 0 | C19: por lançamento (04) | D19: =DATE(2022+5,12,31) -> 46752 | E19: =IF('00_PARAMETROS'!$B$4>D19,"NÃO","SIM") -> SIM | J19: =SUMIFS('04_BANK_TRANSACTIONS'!$W$5:$W$168,'04_BANK_TRANSACTIONS'!$C$5:$C$168,2022) -> 0 | K19: 0 | L19: IRRF não residente; Lei 9.430/96 art. 61 | M19: Juros/multa calculados linha a linha na aba 04 — CENÁRIO, NÃO É IMPOSTO DEVIDO
A20: IRRF apurado — 2023 | B20: =SUMIFS('04_BANK_TRANSACTIONS'!$P$5:$P$168,'04_BANK_TRANSACTIONS'!$C$5:$C$168,2023) -> 0 | C20: por lançamento (04) | D20: =DATE(2023+5,12,31) -> 47118 | E20: =IF('00_PARAMETROS'!$B$4>D20,"NÃO","SIM") -> SIM | J20: =SUMIFS('04_BANK_TRANSACTIONS'!$U$5:$U$168,'04_BANK_TRANSACTIONS'!$C$5:$C$168,2023) -> 0 | K20: =IF(E20="SIM",J20,0) -> 0 | L20: IRRF não residente; Lei 9.430/96 art. 61 | M20: Juros/multa calculados linha a linha na aba 04
A21: Cenário A 15% (exposição) — 2023 | B21: =SUMIFS('04_BANK_TRANSACTIONS'!$Q$5:$Q$168,'04_BANK_TRANSACTIONS'!$C$5:$C$168,2023) -> 0 | C21: por lançamento (04) | D21: =DATE(2023+5,12,31) -> 47118 | E21: =IF('00_PARAMETROS'!$B$4>D21,"NÃO","SIM") -> SIM | J21: =SUMIFS('04_BANK_TRANSACTIONS'!$V$5:$V$168,'04_BANK_TRANSACTIONS'!$C$5:$C$168,2023) -> 0 | K21: 0 | L21: IRRF não residente; Lei 9.430/96 art. 61 | M21: Juros/multa calculados linha a linha na aba 04 — CENÁRIO, NÃO É IMPOSTO DEVIDO
A22: Cenário B 25% (exposição) — 2023 | B22: =SUMIFS('04_BANK_TRANSACTIONS'!$R$5:$R$168,'04_BANK_TRANSACTIONS'!$C$5:$C$168,2023) -> 0 | C22: por lançamento (04) | D22: =DATE(2023+5,12,31) -> 47118 | E22: =IF('00_PARAMETROS'!$B$4>D22,"NÃO","SIM") -> SIM | J22: =SUMIFS('04_BANK_TRANSACTIONS'!$W$5:$W$168,'04_BANK_TRANSACTIONS'!$C$5:$C$168,2023) -> 0 | K22: 0 | L22: IRRF não residente; Lei 9.430/96 art. 61 | M22: Juros/multa calculados linha a linha na aba 04 — CENÁRIO, NÃO É IMPOSTO DEVIDO
A23: IRRF apurado — 2024 | B23: =SUMIFS('04_BANK_TRANSACTIONS'!$P$5:$P$168,'04_BANK_TRANSACTIONS'!$C$5:$C$168,2024) -> 0 | C23: por lançamento (04) | D23: =DATE(2024+5,12,31) -> 47483 | E23: =IF('00_PARAMETROS'!$B$4>D23,"NÃO","SIM") -> SIM | J23: =SUMIFS('04_BANK_TRANSACTIONS'!$U$5:$U$168,'04_BANK_TRANSACTIONS'!$C$5:$C$168,2024) -> 0 | K23: =IF(E23="SIM",J23,0) -> 0 | L23: IRRF não residente; Lei 9.430/96 art. 61 | M23: Juros/multa calculados linha a linha na aba 04
A24: Cenário A 15% (exposição) — 2024 | B24: =SUMIFS('04_BANK_TRANSACTIONS'!$Q$5:$Q$168,'04_BANK_TRANSACTIONS'!$C$5:$C$168,2024) -> 7117.5 | C24: por lançamento (04) | D24: =DATE(2024+5,12,31) -> 47483 | E24: =IF('00_PARAMETROS'!$B$4>D24,"NÃO","SIM") -> SIM | J24: =SUMIFS('04_BANK_TRANSACTIONS'!$V$5:$V$168,'04_BANK_TRANSACTIONS'!$C$5:$C$168,2024) -> 10275.31 | K24: 0 | L24: IRRF não residente; Lei 9.430/96 art. 61 | M24: Juros/multa calculados linha a linha na aba 04 — CENÁRIO, NÃO É IMPOSTO DEVIDO
A25: Cenário B 25% (exposição) — 2024 | B25: =SUMIFS('04_BANK_TRANSACTIONS'!$R$5:$R$168,'04_BANK_TRANSACTIONS'!$C$5:$C$168,2024) -> 11862.5 | C25: por lançamento (04) | D25: =DATE(2024+5,12,31) -> 47483 | E25: =IF('00_PARAMETROS'!$B$4>D25,"NÃO","SIM") -> SIM | J25: =SUMIFS('04_BANK_TRANSACTIONS'!$W$5:$W$168,'04_BANK_TRANSACTIONS'!$C$5:$C$168,2024) -> 17125.53 | K25: 0 | L25: IRRF não residente; Lei 9.430/96 art. 61 | M25: Juros/multa calculados linha a linha na aba 04 — CENÁRIO, NÃO É IMPOSTO DEVIDO
A26: IRRF apurado — 2025 | B26: =SUMIFS('04_BANK_TRANSACTIONS'!$P$5:$P$168,'04_BANK_TRANSACTIONS'!$C$5:$C$168,2025) -> 0 | C26: por lançamento (04) | D26: =DATE(2025+5,12,31) -> 47848 | E26: =IF('00_PARAMETROS'!$B$4>D26,"NÃO","SIM") -> SIM | J26: =SUMIFS('04_BANK_TRANSACTIONS'!$U$5:$U$168,'04_BANK_TRANSACTIONS'!$C$5:$C$168,2025) -> 0 | K26: =IF(E26="SIM",J26,0) -> 0 | L26: IRRF não residente; Lei 9.430/96 art. 61 | M26: Juros/multa calculados linha a linha na aba 04
A27: Cenário A 15% (exposição) — 2025 | B27: =SUMIFS('04_BANK_TRANSACTIONS'!$Q$5:$Q$168,'04_BANK_TRANSACTIONS'!$C$5:$C$168,2025) -> 85209 | C27: por lançamento (04) | D27: =DATE(2025+5,12,31) -> 47848 | E27: =IF('00_PARAMETROS'!$B$4>D27,"NÃO","SIM") -> SIM | J27: =SUMIFS('04_BANK_TRANSACTIONS'!$V$5:$V$168,'04_BANK_TRANSACTIONS'!$C$5:$C$168,2025) -> 117339.42 | K27: 0 | L27: IRRF não residente; Lei 9.430/96 art. 61 | M27: Juros/multa calculados linha a linha na aba 04 — CENÁRIO, NÃO É IMPOSTO DEVIDO
A28: Cenário B 25% (exposição) — 2025 | B28: =SUMIFS('04_BANK_TRANSACTIONS'!$R$5:$R$168,'04_BANK_TRANSACTIONS'!$C$5:$C$168,2025) -> 142015 | C28: por lançamento (04) | D28: =DATE(2025+5,12,31) -> 47848 | E28: =IF('00_PARAMETROS'!$B$4>D28,"NÃO","SIM") -> SIM | J28: =SUMIFS('04_BANK_TRANSACTIONS'!$W$5:$W$168,'04_BANK_TRANSACTIONS'!$C$5:$C$168,2025) -> 195565.68 | K28: 0 | L28: IRRF não residente; Lei 9.430/96 art. 61 | M28: Juros/multa calculados linha a linha na aba 04 — CENÁRIO, NÃO É IMPOSTO DEVIDO
A29: IRRF apurado — 2026 | B29: =SUMIFS('04_BANK_TRANSACTIONS'!$P$5:$P$168,'04_BANK_TRANSACTIONS'!$C$5:$C$168,2026) -> 0 | C29: por lançamento (04) | D29: =DATE(2026+5,12,31) -> 48213 | E29: =IF('00_PARAMETROS'!$B$4>D29,"NÃO","SIM") -> SIM | J29: =SUMIFS('04_BANK_TRANSACTIONS'!$U$5:$U$168,'04_BANK_TRANSACTIONS'!$C$5:$C$168,2026) -> 0 | K29: =IF(E29="SIM",J29,0) -> 0 | L29: IRRF não residente; Lei 9.430/96 art. 61 | M29: Juros/multa calculados linha a linha na aba 04
A30: Cenário A 15% (exposição) — 2026 | B30: =SUMIFS('04_BANK_TRANSACTIONS'!$Q$5:$Q$168,'04_BANK_TRANSACTIONS'!$C$5:$C$168,2026) -> 1200 | C30: por lançamento (04) | D30: =DATE(2026+5,12,31) -> 48213 | E30: =IF('00_PARAMETROS'!$B$4>D30,"NÃO","SIM") -> SIM | J30: =SUMIFS('04_BANK_TRANSACTIONS'!$V$5:$V$168,'04_BANK_TRANSACTIONS'!$C$5:$C$168,2026) -> 1506 | K30: 0 | L30: IRRF não residente; Lei 9.430/96 art. 61 | M30: Juros/multa calculados linha a linha na aba 04 — CENÁRIO, NÃO É IMPOSTO DEVIDO
A31: Cenário B 25% (exposição) — 2026 | B31: =SUMIFS('04_BANK_TRANSACTIONS'!$R$5:$R$168,'04_BANK_TRANSACTIONS'!$C$5:$C$168,2026) -> 2000 | C31: por lançamento (04) | D31: =DATE(2026+5,12,31) -> 48213 | E31: =IF('00_PARAMETROS'!$B$4>D31,"NÃO","SIM") -> SIM | J31: =SUMIFS('04_BANK_TRANSACTIONS'!$W$5:$W$168,'04_BANK_TRANSACTIONS'!$C$5:$C$168,2026) -> 2510 | K31: 0 | L31: IRRF não residente; Lei 9.430/96 art. 61 | M31: Juros/multa calculados linha a linha na aba 04 — CENÁRIO, NÃO É IMPOSTO DEVIDO
A32: TOTAL EXIGÍVEL (apurado) | K32: =SUM(K6:K31) -> 0
A33: Exposição máxima — Cenário A atualizada | J33: =SUMIFS(J8:J31,A8:A31,"Cenário A*",E8:E31,"SIM") -> 129120.73
A34: Exposição máxima — Cenário B atualizada | J34: =SUMIFS(J8:J31,A8:A31,"Cenário B*",E8:E31,"SIM") -> 215201.21
A36: Se houver lançamento de ofício, a multa de mora é substituída pela multa de ofício de 75% (art. 44, I) sobre o principal — ver 00_PARAMETROS.

Sheet 09_REAL_ESTATE
A1: 09 — IMÓVEIS ADQUIRIDOS EM 2025 E ORIGEM DOS RECURSOS
A2: José Adalmo Carvalho de Barros — CPF 069.351.996-70 | Resp. técnico: Robson Soares Bezerra — CRC/PR 062711/O
A4: Item | B4: Blue Ocean — Loft 605 | C4: N1 Porto Belo / Vivapark — Apto 303 | D4: Total | E4: Fonte / observação
A5: Vendedor / cedente | B5: Rofran Construtora Ltda (CNPJ 51.819.924/0001-55) | C5: Cedente conforme contrato; recebedora: Vokkan Reserva I Urbanismo SPE (CNPJ 32.198.324/0001-72) | E5: [FATO CONFIRMADO] contratos na pasta 2025/investimentos
A6: Data do contrato | B6: 45868 | C6: 45868 | E6: [FATO CONFIRMADO]
A7: Preço contratado (R$) | B7: 370000 | C7: 1250265 | D7: =B7+C7 -> 1620265 | E7: N1 inclui comissão de corretagem R$ 62.513,25; reajuste pelo CUB/SC
A8: Adquirente(s) | B8: José (casado com Márcia) | C8: José + Márcia | E8: [FATO CONFIRMADO]
A9: Domicílio declarado no contrato | B9: Goioerê/PR (Rua Arapongas, 303) | C9: Bethel/CT — EUA | E9: CONTRADIÇÃO: o contrato Blue Ocean declara residência no Brasil → prova contrária à tese de não residente
A10: Vencido até 31/12/2025 — nominal (R$) | B10: 370000 | C10: =80000+3*35805+2*3000 -> 193415 | D10: =B10+C10 -> 563415 | E10: Blue Ocean: 5.000 (29/07) + 365.000 (ato). N1: ato 80.000 + 3×35.805 (ago–out) + 3.000 (25/11 e 25/12). Sem correção CUB
A11: Pago via Nubank — rastreado (R$) | B11: =-SUMIFS('04_BANK_TRANSACTIONS'!$F$5:$F$168,'04_BANK_TRANSACTIONS'!$X$5:$X$168,"BLUE OCEAN 605") -> 295000 | C11: =-SUMIFS('04_BANK_TRANSACTIONS'!$F$5:$F$168,'04_BANK_TRANSACTIONS'!$X$5:$X$168,"N1 APTO 303") -> 49200 | D11: =B11+C11 -> 344200 | E11: Aba 04 (vínculo imóvel). N1: PIX a 'N1 Porto Belo Empreendimentos' — conta diferente da indicada no contrato [INFERÊNCIA]
A12: Vencido sem pagamento rastreado (R$) | B12: =B10-B11 -> 75000 | C12: =C10-C11 -> 144215 | D12: =B12+C12 -> 219215 | E12: PENDENTE — DOCUMENTO NECESSÁRIO: comprovantes de outras contas (Márcia? exterior?)
A13: Saldo a vencer a partir de 2026 — nominal (R$) | B13: 0 | C13: =C7-C10 -> 1056850 | D13: =B13+C13 -> 1056850 | E13: N1: 82 parcelas de 3.000 + 7 reforços de 88.850 (a partir de 25/07/2026) + chaves 188.900 (até 25/12/2032)
A15: ORIGEM DOS RECURSOS 2025 — ENTRADAS NA CONTA NUBANK (R$)
A16: Classe | B16: Valor 2025 | C16: Qtde. | E16: Leitura
A17: Remessas do exterior (Daycoval/Remitly/TAPTAP) | B17: =SUMIFS('04_BANK_TRANSACTIONS'!$F$5:$F$168,'04_BANK_TRANSACTIONS'!$C$5:$C$168,2025,'04_BANK_TRANSACTIONS'!$H$5:$H$168,"intermediario_remessa",'04_BANK_TRANSACTIONS'!$G$5:$G$168,"entrada") -> 133096.7 | C17: =COUNTIFS('04_BANK_TRANSACTIONS'!$C$5:$C$168,2025,'04_BANK_TRANSACTIONS'!$H$5:$H$168,"intermediario_remessa",'04_BANK_TRANSACTIONS'!$G$5:$G$168,"entrada") -> 14
A18: Terceiros no Brasil — natureza PENDENTE | B18: =SUMIFS('04_BANK_TRANSACTIONS'!$F$5:$F$168,'04_BANK_TRANSACTIONS'!$C$5:$C$168,2025,'04_BANK_TRANSACTIONS'!$H$5:$H$168,"terceiros",'04_BANK_TRANSACTIONS'!$G$5:$G$168,"entrada") -> 568060 | C18: =COUNTIFS('04_BANK_TRANSACTIONS'!$C$5:$C$168,2025,'04_BANK_TRANSACTIONS'!$H$5:$H$168,"terceiros",'04_BANK_TRANSACTIONS'!$G$5:$G$168,"entrada") -> 28 | E18: Maior bloco: terceiros BR — comprovar natureza antes de qualquer conclusão
A19: Transferências da cônjuge | B19: =SUMIFS('04_BANK_TRANSACTIONS'!$F$5:$F$168,'04_BANK_TRANSACTIONS'!$C$5:$C$168,2025,'04_BANK_TRANSACTIONS'!$H$5:$H$168,"conta_conjuge",'04_BANK_TRANSACTIONS'!$G$5:$G$168,"entrada") -> 85000 | C19: =COUNTIFS('04_BANK_TRANSACTIONS'!$C$5:$C$168,2025,'04_BANK_TRANSACTIONS'!$H$5:$H$168,"conta_conjuge",'04_BANK_TRANSACTIONS'!$G$5:$G$168,"entrada") -> 2
A20: Resgates RDB (recursos próprios já na conta) | B20: =SUMIFS('04_BANK_TRANSACTIONS'!$F$5:$F$168,'04_BANK_TRANSACTIONS'!$C$5:$C$168,2025,'04_BANK_TRANSACTIONS'!$H$5:$H$168,"RDB",'04_BANK_TRANSACTIONS'!$G$5:$G$168,"entrada") -> 89277.35 | C20: =COUNTIFS('04_BANK_TRANSACTIONS'!$C$5:$C$168,2025,'04_BANK_TRANSACTIONS'!$H$5:$H$168,"RDB",'04_BANK_TRANSACTIONS'!$G$5:$G$168,"entrada") -> 14
A21: Estornos | B21: =SUMIFS('04_BANK_TRANSACTIONS'!$F$5:$F$168,'04_BANK_TRANSACTIONS'!$C$5:$C$168,2025,'04_BANK_TRANSACTIONS'!$H$5:$H$168,"estorno",'04_BANK_TRANSACTIONS'!$G$5:$G$168,"entrada") -> 900 | C21: =COUNTIFS('04_BANK_TRANSACTIONS'!$C$5:$C$168,2025,'04_BANK_TRANSACTIONS'!$H$5:$H$168,"estorno",'04_BANK_TRANSACTIONS'!$G$5:$G$168,"entrada") -> 1
A22: TOTAL entradas 2025 | B22: =SUM(B17:B21) -> 876334.05
A23: Saldo de RDB em 31/12/2024 (EDITAR) | E23: PENDENTE — DOCUMENTO NECESSÁRIO: informe de rendimentos Nubank 2024/2025
A25: CONSEQUÊNCIAS TRIBUTÁRIAS
A26: [FATO CONFIRMADO] O preço de aquisição não é renda tributável.
A27: [INFERÊNCIA TÉCNICA] Não residente não entrega DIRPF: a aquisição não é declarada à RFB pelo adquirente. O .DEC 2026 com endereço em SP não deve ser transmitido.
A28: [INFERÊNCIA TÉCNICA] Na futura alienação, o ganho de capital do não residente é tributado a 15%–22,5%, com retenção pelo adquirente ou procurador (Lei 10.833/2003, art. 26). Guardar o custo de aquisição: contratos, comprovantes, ITBI, corretagem e correção CUB.
A29: [HIPÓTESE] Aquisição de imóvel no BR por não residente com recursos do exterior: verificar a exigência de registro de capital estrangeiro no BCB (Lei 14.286/2021; Res. BCB 278/2022) — confirmar na fonte oficial.
A30: [INFERÊNCIA TÉCNICA] Risco central: se os R$ 574 mil de terceiros em 2025 forem renda de fonte BR (serviço, venda de bem, aluguel), incide IRRF — ver 04/08. Se forem empréstimo, exigir contrato e plano de devolução.
A31: [FATO CONFIRMADO] Os contratos declaram domicílios opostos (Goioerê/PR × Bethel/CT). A escritura definitiva deve refletir a condição de não residente e indicar procurador no BR.

Sheet 10_DOCUMENT_CONTROL
A1: 10 — CONTROLE DE DOCUMENTOS
A2: José Adalmo Carvalho de Barros — CPF 069.351.996-70 | Resp. técnico: Robson Soares Bezerra — CRC/PR 062711/O
A4: # | B4: Documento (pasta G:\...\irpf JOSE ADALMO) | C4: Período | D4: Contribuinte | E4: Valores extraídos | F4: Uso nesta memória | G4: Verificação
A5: 1 | B5: 2017/06935199670-IRPF-A-2017-2016-DEC/REC.pdf | C5: AC 2016 | D5: José | E5: DIRPF entregue 10/03/2017 | F5: 02 | G5: [FATO CONFIRMADO] Lido (Fase 0)
A6: 2 | B6: 2018/ 7 imagens → 000 MD/OCR/2018_US_TAX.md | C6: 2018 | D6: José + Márcia (MFJ) | E6: Wages 25.628; tax 164; CTC 164; CT 0; W-7 de DEPENDENTE (entrada 01/25/2018) | F6: 05, 06, 07 | G6: OCR — confiança média-alta
A7: 3 | B7: 2019/ 12 imagens → OCR/2019_US_TAX.md | C7: 2019 | D7: José | E7: Sch C 10.000; SE 1.413; CT AGI 9.293 | F7: 05, 07 | G7: OCR
A8: 4 | B8: 2020/ 22 imagens → OCR/2020_2021_US_TAX.md | C8: 2020–2021 | D8: José (MFJ) | E8: 2020: 30.152 / 2.252 / SE 318 — 2021: 35.335 / 4.870 / SE 686 | F8: 05 | G8: OCR (2021 via Fase 2)
A9: 5 | B9: 2022/Jose Adalmo 22 File.pdf → OCR/2022_US_TAX.md | C9: 2022 | D9: José (MFJ) | E9: Sch C 40.550 / 10.823; AGI 10.058; taxable 0; SE 1.529 | F9: 05 | G9: OCR
A10: 6 | B10: 2023/ 17 imagens → OCR/2023_US_TAX.md | C10: 2023 | D10: José (MFJ) | E10: K-1 75.383; SE 10.651; owed 15.480; digital assets YES | F10: 05 | G10: OCR — linhas 22/24 ilegíveis
A11: 7 | B11: 2024/2024 Tax Return Documents (Client Copy).pdf | C11: 2024 | D11: José + Márcia (MFJ) | E11: Total income 82.153; AGI 81.341; tax 5.039; SE 1.623; owed 6.963; 3 partnerships | F11: 05 | G11: [FATO CONFIRMADO] lido nesta sessão (pdftotext)
A12: 8 | B12: 000 MD/DADOS/NUBANK_LEDGER.csv (Nubank 89083502-4) | C12: out/2024–abr/2026 | D12: José | E12: 164 lançamentos | F12: 04, 07, 08, 09 | G12: Derivado dos PDFs; conferir contra os extratos originais
A13: 9 | B13: 2024/NU_*_OUT–DEZ2024.pdf; 2025/01–12.pdf; 2026/NU_*.pdf | C13: 2024–2026 | D13: José | E13: Extratos originais | F13: 04 | G13: 04.txt e 05.txt vazios → abr–mai/2025 AUSENTES; mar/2026 AUSENTE
A14: 10 | B14: 2025/investimentos/BLUE OCEAN 605.pdf | C14: 30/07/2025 | D14: José | E14: R$ 370.000; domicílio Goioerê/PR | F14: 09 | G14: [FATO CONFIRMADO] lido nesta sessão
A15: 11 | B15: 2025/investimentos/PF - INC N1 - TERRENISTA - 100X.pdf | C15: 30/07/2025 | D15: José + Márcia | E15: R$ 1.250.265; cronograma até 2032; domicílio Bethel/CT | F15: 09 | G15: [FATO CONFIRMADO] lido nesta sessão
A16: 12 | B16: 06935199670-IRPF-A-2026-2025-ORIGI.DEC | C16: AC 2025 | D16: José | E16: Endereço Rua Silas 166, São Paulo/SP; sem REC | F16: 02, 11 | G16: Não transmitir
... A22: 18 | B22: Informe de rendimentos Nubank (RDB) 2024–2025 | C22: 2024–2025 | D22: José | E22: — | F22: 09 | G22: PENDENTE — DOCUMENTO NECESSÁRIO

Sheet 11_RISKS
A1: 11 — RISCOS, INCONSISTÊNCIAS, VALIDAÇÕES E AÇÕES
A2: José Adalmo Carvalho de Barros — CPF 069.351.996-70 | Resp. técnico: Robson Soares Bezerra — CRC/PR 062711/O
A4: ID | B4: Achado | C4: Período | D4: Risco | E4: Ação necessária | F4: Base / evidência | G4: Prazo | H4: Status
A5: R-01 | B5: O .DEC 2026 (AC 2025) foi gerado com endereço em São Paulo/SP | C5: AC 2025 | D5: CRÍTICO | E5: NÃO transmitir. Arquivar com nota técnica. | F5: Arquivo .DEC (registro 16) | G5: Imediato | H5: ABERTO
A6: R-02 | B6: Recebimentos de terceiros no BR sem natureza comprovada (maior bloco: R$ 190 mil Reginaldo Bessa; R$ 69 mil Wersan Combustíveis LTDA; R$ 96 mil André Werner; R$ 44 mil Rodrigo Machado; Felipe de M. Rodrigues) | C6: 2024–2026 | D6: ALTO | E6: Para cada lançamento material: contrato, recibo, escritura ou declaração do pagador. Preencher a coluna K da aba 04. | F6: Aba 04 — CORRIGE o laudo F6, que apontava como risco as remessas do exterior | G6: 30/10/2026 | H6: ABERTO
A7: R-03 | B7: A data de saída 25/01/2018 não está provada para o José (os W-7 são de dependente) | C7: 2018–2019 | D7: ALTO | E7: Passaporte, I-94, passagem, carteira de motorista CT e contrato de locação em nome dele. | F7: OCR 2018 — W-7 box 'd' (dependente) | G7: 30/10/2026 | H7: ABERTO
A8: R-04 | B8: Contrato Blue Ocean (30/07/2025) declara José residente e domiciliado em Goioerê/PR | C8: AC 2025 | D8: ALTO | E8: Aditivo ou escritura retificando o domicílio; reunir provas de residência nos EUA. | F8: Contrato Blue Ocean, cláusula I-b | G8: Antes da escritura | H8: ABERTO
A9: R-05 | B9: Pagamentos de imóveis vencidos em 2025 sem rastreio no Nubank | C9: AC 2025 | D9: ALTO | E9: Extratos das contas usadas (Márcia, outras, exterior). | F9: Aba 09 — linha 12 | G9: 30/11/2026 | H9: ABERTO
A10: R-06 | B10: Extratos ausentes: abr–mai/2025, mar/2026, 2019–2023 (exceto mai/2022) | C10: 2019–2026 | D10: MÉDIO | E10: Obter extratos completos de todas as contas no BR. | F10: 10_DOCUMENT_CONTROL | G10: 30/11/2026 | H10: ABERTO
A11: R-07 | B11: Ativos digitais: YES em 2023 (NO em 2024) | C11: AC 2023 | D11: MÉDIO | E11: Identificar exchanges; se BR, avaliar GCAP de não residente. | F11: 1040/2023 | G11: 30/11/2026 | H11: ABERTO
A12: R-08 | B12: 1040/2024: saldo de US$ 6.963 sem pagamento no formulário | C12: US 2024 | D12: MÉDIO | E12: Confirmar o pagamento ao IRS (Account Transcript). Não afeta o BR. | F12: 1040/2024 l.33 = 0; l.37 | G12: — | H12: ABERTO
A13: R-09 | B13: CPF possivelmente ainda como residente; conta Nubank de residente mantida por não residente | C13: Atual | D13: MÉDIO | E13: Regularizar o CPF como residente no exterior e nomear procurador. Consultar o banco sobre o enquadramento da conta (Lei 14.286/2021 — confirmar). | F13: [HIPÓTESE] | G13: 31/12/2026 | H13: ABERTO
A14: R-10 | B14: Márcia (CPF 023.515.229-31): residência fiscal não analisada; transferiu R$ 85 mil ao José e é coadquirente do N1 | C14: 2018–2026 | D14: MÉDIO | E14: Aplicar a mesma análise de residência à Márcia; origem dos recursos dela. | F14: Contratos + ledger | G14: 30/11/2026 | H14: ABERTO
A15: R-11 | B15: Participações em 3 partnerships nos EUA (Two Brothers, UPE, Royal Flush) | C15: 2023–2024 | D15: BAIXO | E15: CBE/BCB vale para residente no BR — não se aplica a não residente [INFERÊNCIA]. CORRIGE o laudo F6 (itens 7 e 12). | F15: Sch E 2024 | G15: — | H15: ABERTO
... A18: V-03 | B18: Correção: câmbio AC 2018 pela PTAX venda de 31/12/2018; PTAX ago/2018 digitada como 3,1353 | C18: AC 2018 | D18: BAIXO | E18: Usar o dólar de compra da 1ª quinzena do mês anterior (aba 07). | F18: Fase 2, tabela 2.1 | G18: — | H18: APLICADO
A19: V-04 | B19: Checagem: entradas × classes (ledger) | C19: 2024–2026 | D19: INFO | E19: =IF(ABS(SUMIFS('04_BANK_TRANSACTIONS'!$F$5:$F$168,'04_BANK_TRANSACTIONS'!$G$5:$G$168,"entrada")-SUM('09_REAL_ESTATE'!B17:B21)-SUMIFS('04_BANK_TRANSACTIONS'!$F$5:$F$168,'04_BANK_TRANSACTIONS'!$G$5:$G$168,"entrada",'04_BANK_TRANSACTIONS'!$C$5:$C$168,"<>2025"))<0.01,"OK","ERRO") -> OK | F19: Soma 04 = soma por classe (09) + outros anos | G19: — | H19: AUTO
A20: V-05 | B20: Checagem: possíveis duplicidades (mesma data, contraparte e valor) | C20: 2024–2026 | D20: INFO | E20: {=IF(SUMPRODUCT((COUNTIFS('04_BANK_TRANSACTIONS'!$B$5:$B$168,'04_BANK_TRANSACTIONS'!$B$5:$B$168,'04_BANK_TRANSACTIONS'!$E$5:$E$168,'04_BANK_TRANSACTIONS'!$E$5:$E$168,'04_BANK_TRANSACTIONS'!$F$5:$F$168,'04_BANK_TRANSACTIONS'!$F$5:$F$168)>1)*1)>0,"REVISAR — há repetições (ex.: Remitly 16/10/2025 3×5.256,40)","OK")} -> REVISAR — há repetições (ex.: Remitly 16/10/2025 3×5.256,40) | F20: Aba 04 | G20: — | H20: AUTO
A21: V-06 | B21: Checagem: crédito estrangeiro ≤ limite | C21: AC 2018 | D21: INFO | E21: =IF('06_FOREIGN_TAX_CREDIT'!B14<='06_FOREIGN_TAX_CREDIT'!B10,"OK","ERRO") -> OK | F21: Aba 06 | G21: — | H21: AUTO

Sheet 12_LEGAL_SOURCES
A1: 12 — FONTES NORMATIVAS E OFICIAIS
A2: José Adalmo Carvalho de Barros — CPF 069.351.996-70 | Resp. técnico: Robson Soares Bezerra — CRC/PR 062711/O
A4: Norma / fonte | B4: Regra aplicada | C4: Período | D4: Link oficial | E4: Status
A5: IN SRF 208/2002 | B5: Residência/não residência; 12 meses de ausência sem CSDP; DSDP | C5: 2002–atual | D5: http://normas.receita.fazenda.gov.br/sijut2consulta/link.action?idAto=15103 | E5: Confirmar texto
A6: CTN — Lei 5.172/1966, art. 173, I; art. 156, V | B6: Decadência sem declaração e sem pagamento; extinção do crédito | C6: Permanente | D6: https://www.planalto.gov.br/ccivil_03/leis/l5172compilado.htm | E6: Verificar
A7: STJ — Súmula 555 | B7: Aplicação do art. 173, I quando não há declaração | C7: — | D7: https://scon.stj.jus.br/SCON/sumstj/ | E7: Verificar
A8: Lei 11.482/2007, art. 1º | B8: Tabelas progressivas mensal e anual (2015–2022) | C8: AC 2018–2019 | D8: https://www.planalto.gov.br/ccivil_03/_ato2007-2010/2007/lei/l11482.htm | E8: Confirmar
A9: IN RFB 1.871/2019 | B9: DIRPF exercício 2019 (AC 2018): limite de obrigatoriedade e desconto simplificado | C9: AC 2018 | D9: http://normas.receita.fazenda.gov.br/sijut2consulta/ | E9: Confirmar
A10: Decreto 9.580/2018 (RIR/2018) | B10: Conversão cambial de rendimentos do exterior; compensação de imposto pago no exterior (PF) | C10: 2018–atual | D10: https://www.planalto.gov.br/ccivil_03/_ato2015-2018/2018/decreto/d9580.htm | E10: Confirmar artigos
A11: Lei 4.862/1965, art. 5º; ADI SRF 28/2000 | B11: Reciprocidade Brasil–EUA: somente imposto de renda federal | C11: — | D11: http://normas.receita.fazenda.gov.br/sijut2consulta/ | E11: Confirmar
A12: Lei 9.430/1996, arts. 5º, 44 e 61 | B12: Juros SELIC, multa de mora 0,33%/dia (teto 20%), multa de ofício 75% | C12: Permanente | D12: https://www.planalto.gov.br/ccivil_03/leis/l9430.htm | E12: Verificar
A13: Lei 8.981/1995, art. 88 | B13: MAED — multa por atraso de declaração (mínimo R$ 165,74) | C13: Permanente | D13: https://www.planalto.gov.br/ccivil_03/leis/l8981.htm | E13: Verificar
A14: Lei 10.833/2003, art. 26; Lei 13.259/2016 | B14: Ganho de capital de não residente: responsável o adquirente/procurador; alíquotas 15%–22,5% | C14: Permanente | D14: https://www.planalto.gov.br/ccivil_03/leis/2003/l10.833.htm | E14: Verificar
A15: RFB — Perguntas e Respostas IRPF (não residentes) | B15: IRRF 15% (regra geral) e 25% (trabalho/serviços) para residente no exterior | C15: Vigente | D15: https://www.gov.br/receitafederal/pt-br/centrais-de-conteudo/publicacoes/perguntas-e-respostas/dirpf | E15: Confirmar
... A19: IRS — Form 1040 Instructions | B19: Linhas 22 (income tax), 23 (SE tax), 24 (total tax) | C19: 2018–2024 | D19: https://www.irs.gov/forms-pubs/about-form-1040 | E19: Referência

Sheet 00_PARAMETROS
A1: 00 — PARÂMETROS, PREMISSAS E TABELAS (células amarelas = entrada editável)
A2: José Adalmo Carvalho de Barros — CPF 069.351.996-70 | Resp. técnico: Robson Soares Bezerra — CRC/PR 062711/O
A3: Parâmetro | B3: Valor | E3: Fonte / status
A4: Data-base do cálculo (atualização) | B4: 46295 | E4: [SUGESTÃO] Data-base da memória. Alterar para a data do efetivo pagamento.
A5: Data de saída do Brasil (José) | B5: 43125 | E5: [HIPÓTESE] Informada pelo cliente. Os W-7/2018 são de DEPENDENTE (box d) e a data 01/25/2018 é a entrada do dependente. PENDENTE — DOCUMENTO NECESSÁRIO: passaporte / I-94 / passagem do José.
A6: Início da condição de não residente | B6: =EDATE('00_PARAMETROS'!$B$5,12) -> 43490 | E6: [INFERÊNCIA TÉCNICA] IN SRF 208/2002: sem CSDP, a pessoa passa a não residente a partir do dia em que completa 12 meses consecutivos de ausência. Requer ausência ininterrupta (sem retorno ao BR) — confirmar na fonte oficial.
A7: Materialidade (recebimento isolado, R$) | B7: 10000 | E7: [SUGESTÃO] Valor mínimo para exigir comprovação individual de origem.
A8: Multa de mora — % ao dia | B8: 0.0033 | E8: Lei 9.430/1996, art. 61 — pagamento espontâneo (confirmar na fonte oficial).
A9: Multa de mora — teto | B9: 0.2 | E9: Lei 9.430/1996, art. 61, §2º.
A10: Multa de ofício (lançamento pela RFB) | B10: 0.75 | E10: Lei 9.430/1996, art. 44, I — aplicável só se houver lançamento de ofício (não soma com a multa de mora).
A11: Juros — mês do pagamento | B11: 0.01 | E11: Lei 9.430/1996, art. 61, §3º c/c art. 5º, §3º: SELIC acumulada do mês seguinte ao vencimento até o mês anterior ao pagamento + 1% no mês do pagamento.
A12: Alíquota de cenário A — IRRF não residente (outros rendimentos) | B12: 0.15 | E12: [INFERÊNCIA TÉCNICA] Regra geral de 15% para rendimentos de fonte BR pagos a residente no exterior (RFB — Perguntas e Respostas IRPF; confirmar na fonte oficial).
A13: Alíquota de cenário B — IRRF não residente (trabalho/serviços) | B13: 0.25 | E13: [INFERÊNCIA TÉCNICA] 25% para rendimentos do trabalho/serviços pagos a não residente (confirmar na fonte oficial).
A15: TABELA PROGRESSIVA ANUAL — AC 2018 e AC 2019 (exercícios 2019/2020)
A16: Faixa — base a partir de (R$) | B16: Alíquota | C16: Parcela a deduzir (R$) | E16: Fonte
A17: 0 | B17: 0 | C17: 0 | E17: Lei 11.482/2007 art. 1º (valores vigentes 2015–2022; IN RFB 1.871/2019) — confirmar na fonte oficial
A18: 22847.77 | B18: 0.075 | C18: 1713.58
A19: 33919.81 | B19: 0.15 | C19: 4257.57
A20: 45012.61 | B20: 0.225 | C20: 7633.51
A21: 55976.17 | B21: 0.275 | C21: 10432.32
A23: TABELA PROGRESSIVA MENSAL — 2018/2019 (carnê-leão)
A24: Faixa — base a partir de (R$) | B24: Alíquota | C24: Parcela a deduzir (R$) | E24: Fonte
A25: 0 | B25: 0 | C25: 0 | E25: Lei 11.482/2007 art. 1º — confirmar na fonte oficial
A26: 1903.99 | B26: 0.075 | C26: 142.8
A27: 2826.66 | B27: 0.15 | C27: 354.8
A28: 3751.06 | B28: 0.225 | C28: 636.13
A29: 4664.69 | B29: 0.275 | C29: 869.36
A31: OUTROS PARÂMETROS DO AJUSTE ANUAL AC 2018
A32: Desconto simplificado — % | B32: 0.2 | E32: Lei 9.250/1995 art. 10 — confirmar na fonte oficial.
A33: Desconto simplificado — teto AC 2018 (R$) | B33: 16754.34 | E33: IN RFB 1.871/2019 — confirmar na fonte oficial. (O laudo da Fase 6 NÃO aplicou o teto.)
A34: Dedução por dependente — anual (R$) | B34: 2275.08 | E34: Lei 9.250/1995 art. 8º, II, c — confirmar na fonte oficial.
A35: Nº de dependentes elegíveis na DIRPF | B35: 3 | E35: [HIPÓTESE] Márcia, Gabriel e Clara (Form 1040/2018). Elegibilidade na DIRPF depende de CPF e de requisitos legais — confirmar.
A36: Limite de obrigatoriedade — rend. tributáveis AC 2018/2019 (R$) | B36: 28559.7 | E36: IN RFB 1.871/2019 e IN RFB 1.924/2020 — confirmar na fonte oficial.
A37: MAED — multa mínima por atraso de declaração (R$) | B37: 165.74 | E37: Lei 9.250/1995 art. 88 c/c Lei 8.981/1995 art. 27 — 1% a.m. sobre o imposto devido, mínimo R$ 165,74, máximo 20%.
A39: TABELA DE NATUREZA DOS RECEBIMENTOS (usada na aba 04 — coluna Natureza)
A40: Código da natureza | B40: Alíquota IRRF | C40: Base de cálculo | D40: Tributável no BR? | E40: Fundamento / observação
A41: PENDENTE | B41: 0 | C41: — | D41: INDEFINIDO | E41: PENDENTE — DOCUMENTO NECESSÁRIO. Entra só nos cenários A/B (exposição), nunca como imposto apurado.
A42: RECURSO_PROPRIO_EXTERIOR | B42: 0 | C42: — | D42: NÃO | E42: Ingresso de recursos do exterior (câmbio). Não é renda de fonte BR. Exige contrato de câmbio / comprovante do remetente.
A43: TRANSF_CONTA_PROPRIA | B43: 0 | C43: — | D43: NÃO | E43: Transferência entre contas do próprio titular.
A44: TRANSF_CONJUGE | B44: 0 | C44: — | D44: NÃO | E44: Transferência da cônjuge (comunhão parcial). Origem dos recursos da cônjuge a comprovar.
A45: EMPRESTIMO_RECEBIDO | B45: 0 | C45: — | D45: NÃO | E45: Mútuo — exige contrato, identificação do mutuante e prova de devolução.
A46: DEVOLUCAO_EMPRESTIMO | B46: 0 | C46: — | D46: NÃO | E46: Devolução de valor emprestado anteriormente — exige prova do empréstimo original.
A47: DOACAO | B47: 0 | C47: — | D47: NÃO (IR) | E47: Fora do IR; sujeita a ITCMD estadual (fora do escopo desta memória).
A48: REEMBOLSO_ESTORNO | B48: 0 | C48: — | D48: NÃO | E48: Estorno / reembolso de pagamento anterior.
A49: RDB_MOVIMENTACAO | B49: 0 | C49: — | D49: NÃO | E49: Aplicação/resgate RDB. O rendimento do RDB sofre IRRF pelo Nubank (verificar informe de rendimentos).
A50: VENDA_BEM_BR_GCAP | B50: 0.15 | C50: GANHO | D50: SIM | E50: Ganho de capital de não residente: 15% a 22,5% (Lei 13.259/2016); responsabilidade do adquirente/procurador (Lei 10.833/2003 art. 26) — preencher a coluna 'Base ganho'.
A51: ALUGUEL_BR | B51: 0.15 | C51: VALOR | D51: SIM | E51: Aluguel de imóvel no BR pago a não residente — 15% (confirmar na fonte oficial).
A52: TRABALHO_SERVICO_BR | B52: 0.25 | C52: VALOR | D52: SIM | E52: Trabalho/serviço pago a não residente — 25% (confirmar na fonte oficial).
... A54: SAIDA | B54: 0 | C54: — | D54: N/A | E54: Débito na conta — não é rendimento.

Sheet SELIC
A1: SELIC acumulada no mês (% a.m.) — BCB/SGS série 4390
A2: José Adalmo Carvalho de Barros — CPF 069.351.996-70 | Resp. técnico: Robson Soares Bezerra — CRC/PR 062711/O
A3: Mês (1º dia) | B3: SELIC % a.m. | C3: Fonte
A4: 43466 | B4: 0.0054 | C4: BCB SGS 4390 (api.bcb.gov.br) — consulta 24/07/2026
A5: 43497 | B5: 0.0049 | C5: BCB SGS 4390 (api.bcb.gov.br) — consulta 24/07/2026
A6: 43525 | B6: 0.0047 | C6: BCB SGS 4390 (api.bcb.gov.br) — consulta 24/07/2026
A7: 43556 | B7: 0.0052 | C7: BCB SGS 4390 (api.bcb.gov.br) — consulta 24/07/2026
A8: 43586 | B8: 0.0054 | C8: BCB SGS 4390 (api.bcb.gov.br) — consulta 24/07/2026
A9: 43617 | B9: 0.0047 | C9: BCB SGS 4390 (api.bcb.gov.br) — consulta 24/07/2026
A10: 43647 | B10: 0.0057 | C10: BCB SGS 4390 (api.bcb.gov.br) — consulta 24/07/2026
A11: 43678 | B11: 0.005 | C11: BCB SGS 4390 (api.bcb.gov.br) — consulta 24/07/2026
A12: 43709 | B12: 0.0046 | C12: BCB SGS 4390 (api.bcb.gov.br) — consulta 24/07/2026
A13: 43739 | B13: 0.0048 | C13: BCB SGS 4390 (api.bcb.gov.br) — consulta 24/07/2026
A14: 43770 | B14: 0.0038 | C14: BCB SGS 4390 (api.bcb.gov.br) — consulta 24/07/2026
A15: 43800 | B15: 0.0037 | C15: BCB SGS 4390 (api.bcb.gov.br) — consulta 24/07/2026
... A96: 46266 | B96: 0.0103 | C96: BCB SGS 4390 (api.bcb.gov.br) — consulta 24/07/2026 — mês corrente, valor parcial
A98: Conferir com a tabela de juros SELIC publicada pela RFB antes de emitir DARF.
